{"id": "template_12717", "config": "# Semantic Router Configuration\n# Generated from template\n\ndecisions:\n  - name: \"general_decision\"\n    modelRefs:\n      - model: \"mistral\"\n        use_reasoning: true\n    signals:\n      - type: \"embedding\"\n        categories:\n          - \"business\"\n          - \"finance\"\n\nmodel_config:\n  mistral:\n    reasoning_family: \"mistral\"\n    preferred_endpoints:\n      - \"endpoint_mistral\"\n\nvllm_endpoints:\n  - name: \"endpoint_mistral\"\n    address: \"172.28.0.20\"\n    port: 11434\n    weight: 2\n\nsemantic_cache:\n  enabled: True\n  backend_type: \"redis\"\n  similarity_threshold: 0.7\n  max_entries: 1000\n  ttl_seconds: 3600\n\nprompt_guard:\n  enabled: False\n  threshold: 0.7\n  use_modernbert: true\n\ntools:\n  enabled: True\n  top_k: 3\n  similarity_threshold: 0.2\n", "intent": "Route queries to mistral, using embedding-based routing, with redis semantic cache, with tools auto-selection, for ai-gateway deployment", "deployment_context": "ai-gateway", "source": "template", "values": {"decision_name": "general_decision", "model_name": "mistral", "signal_type": "embedding", "category1": "business", "category2": "finance", "endpoint_address": "172.28.0.20", "endpoint_port": 11434, "endpoint_weight": 2, "cache_enabled": true, "cache_backend": "redis", "cache_threshold": 0.7, "guard_enabled": false, "guard_threshold": 0.7, "tools_enabled": true, "deployment_context": "ai-gateway"}}
{"id": "template_54054", "config": "# Semantic Router Configuration\n# Generated from template\n\ndecisions:\n  - name: \"technical_decision\"\n    modelRefs:\n      - model: \"phi4\"\n        use_reasoning: true\n    signals:\n      - type: \"keyword\"\n        categories:\n          - \"general\"\n          - \"sales\"\n\nmodel_config:\n  phi4:\n    reasoning_family: \"phi4\"\n    preferred_endpoints:\n      - \"endpoint_phi4\"\n\nvllm_endpoints:\n  - name: \"endpoint_phi4\"\n    address: \"172.28.0.20\"\n    port: 11434\n    weight: 3\n\nsemantic_cache:\n  enabled: True\n  backend_type: \"memory\"\n  similarity_threshold: 0.7\n  max_entries: 1000\n  ttl_seconds: 3600\n\nprompt_guard:\n  enabled: False\n  threshold: 0.6\n  use_modernbert: true\n\ntools:\n  enabled: False\n  top_k: 3\n  similarity_threshold: 0.2\n", "intent": "Route queries to phi4, using keyword-based routing, with memory semantic cache, for ai-gateway deployment", "deployment_context": "ai-gateway", "source": "template", "values": {"decision_name": "technical_decision", "model_name": "phi4", "signal_type": "keyword", "category1": "general", "category2": "sales", "endpoint_address": "172.28.0.20", "endpoint_port": 11434, "endpoint_weight": 3, "cache_enabled": true, "cache_backend": "memory", "cache_threshold": 0.7, "guard_enabled": false, "guard_threshold": 0.6, "tools_enabled": false, "deployment_context": "ai-gateway"}}
{"id": "template_61643", "config": "# Semantic Router Configuration\n# Generated from template\n\ndecisions:\n  - name: \"support_decision\"\n    modelRefs:\n      - model: \"llama3\"\n        use_reasoning: true\n    signals:\n      - type: \"embedding\"\n        categories:\n          - \"general\"\n          - \"engineering\"\n\nmodel_config:\n  llama3:\n    reasoning_family: \"llama3\"\n    preferred_endpoints:\n      - \"endpoint_llama3\"\n\nvllm_endpoints:\n  - name: \"endpoint_llama3\"\n    address: \"10.0.0.50\"\n    port: 8002\n    weight: 1\n\nsemantic_cache:\n  enabled: True\n  backend_type: \"redis\"\n  similarity_threshold: 0.7\n  max_entries: 1000\n  ttl_seconds: 3600\n\nprompt_guard:\n  enabled: False\n  threshold: 0.8\n  use_modernbert: true\n\ntools:\n  enabled: True\n  top_k: 3\n  similarity_threshold: 0.2\n", "intent": "Route queries to llama3, using embedding-based routing, with redis semantic cache, with tools auto-selection, for ai-gateway deployment", "deployment_context": "ai-gateway", "source": "template", "values": {"decision_name": "support_decision", "model_name": "llama3", "signal_type": "embedding", "category1": "general", "category2": "engineering", "endpoint_address": "10.0.0.50", "endpoint_port": 8002, "endpoint_weight": 1, "cache_enabled": true, "cache_backend": "redis", "cache_threshold": 0.7, "guard_enabled": false, "guard_threshold": 0.8, "tools_enabled": true, "deployment_context": "ai-gateway"}}
{"id": "template_35188", "config": "# Semantic Router Configuration\n# Generated from template\n\ndecisions:\n  - name: \"general_decision\"\n    modelRefs:\n      - model: \"mistral\"\n        use_reasoning: true\n    signals:\n      - type: \"domain\"\n        categories:\n          - \"support\"\n          - \"customer_service\"\n\nmodel_config:\n  mistral:\n    reasoning_family: \"mistral\"\n    preferred_endpoints:\n      - \"endpoint_mistral\"\n\nvllm_endpoints:\n  - name: \"endpoint_mistral\"\n    address: \"172.28.0.20\"\n    port: 11434\n    weight: 1\n\nsemantic_cache:\n  enabled: False\n  backend_type: \"milvus\"\n  similarity_threshold: 0.9\n  max_entries: 1000\n  ttl_seconds: 3600\n\nprompt_guard:\n  enabled: True\n  threshold: 0.6\n  use_modernbert: true\n\ntools:\n  enabled: False\n  top_k: 3\n  similarity_threshold: 0.2\n", "intent": "Route queries to mistral, using domain-based routing, with PII detection, for ai-gateway deployment", "deployment_context": "ai-gateway", "source": "template", "values": {"decision_name": "general_decision", "model_name": "mistral", "signal_type": "domain", "category1": "support", "category2": "customer_service", "endpoint_address": "172.28.0.20", "endpoint_port": 11434, "endpoint_weight": 1, "cache_enabled": false, "cache_backend": "milvus", "cache_threshold": 0.9, "guard_enabled": true, "guard_threshold": 0.6, "tools_enabled": false, "deployment_context": "ai-gateway"}}
{"id": "template_43090", "config": "# Semantic Router Configuration\n# Generated from template\n\ndecisions:\n  - name: \"business_decision\"\n    modelRefs:\n      - model: \"mistral\"\n        use_reasoning: true\n    signals:\n      - type: \"keyword\"\n        categories:\n          - \"business\"\n          - \"sales\"\n\nmodel_config:\n  mistral:\n    reasoning_family: \"mistral\"\n    preferred_endpoints:\n      - \"endpoint_mistral\"\n\nvllm_endpoints:\n  - name: \"endpoint_mistral\"\n    address: \"10.0.0.50\"\n    port: 8080\n    weight: 2\n\nsemantic_cache:\n  enabled: True\n  backend_type: \"redis\"\n  similarity_threshold: 0.7\n  max_entries: 1000\n  ttl_seconds: 3600\n\nprompt_guard:\n  enabled: False\n  threshold: 0.6\n  use_modernbert: true\n\ntools:\n  enabled: False\n  top_k: 3\n  similarity_threshold: 0.2\n", "intent": "Route queries to mistral, using keyword-based routing, with redis semantic cache, for kubernetes deployment", "deployment_context": "kubernetes", "source": "template", "values": {"decision_name": "business_decision", "model_name": "mistral", "signal_type": "keyword", "category1": "business", "category2": "sales", "endpoint_address": "10.0.0.50", "endpoint_port": 8080, "endpoint_weight": 2, "cache_enabled": true, "cache_backend": "redis", "cache_threshold": 0.7, "guard_enabled": false, "guard_threshold": 0.6, "tools_enabled": false, "deployment_context": "kubernetes"}}
{"id": "template_81989", "config": "# Semantic Router Configuration\n# Generated from template\n\ndecisions:\n  - name: \"general_decision\"\n    modelRefs:\n      - model: \"phi4\"\n        use_reasoning: true\n    signals:\n      - type: \"keyword\"\n        categories:\n          - \"business\"\n          - \"finance\"\n\nmodel_config:\n  phi4:\n    reasoning_family: \"phi4\"\n    preferred_endpoints:\n      - \"endpoint_phi4\"\n\nvllm_endpoints:\n  - name: \"endpoint_phi4\"\n    address: \"10.0.0.50\"\n    port: 8000\n    weight: 3\n\nsemantic_cache:\n  enabled: True\n  backend_type: \"memory\"\n  similarity_threshold: 0.7\n  max_entries: 1000\n  ttl_seconds: 3600\n\nprompt_guard:\n  enabled: True\n  threshold: 0.7\n  use_modernbert: true\n\ntools:\n  enabled: True\n  top_k: 3\n  similarity_threshold: 0.2\n", "intent": "Route queries to phi4, using keyword-based routing, with memory semantic cache, with PII detection, with tools auto-selection, for kubernetes deployment", "deployment_context": "kubernetes", "source": "template", "values": {"decision_name": "general_decision", "model_name": "phi4", "signal_type": "keyword", "category1": "business", "category2": "finance", "endpoint_address": "10.0.0.50", "endpoint_port": 8000, "endpoint_weight": 3, "cache_enabled": true, "cache_backend": "memory", "cache_threshold": 0.7, "guard_enabled": true, "guard_threshold": 0.7, "tools_enabled": true, "deployment_context": "kubernetes"}}
{"id": "template_95649", "config": "# Semantic Router Configuration\n# Generated from template\n\ndecisions:\n  - name: \"support_decision\"\n    modelRefs:\n      - model: \"mistral\"\n        use_reasoning: true\n    signals:\n      - type: \"embedding\"\n        categories:\n          - \"general\"\n          - \"engineering\"\n\nmodel_config:\n  mistral:\n    reasoning_family: \"mistral\"\n    preferred_endpoints:\n      - \"endpoint_mistral\"\n\nvllm_endpoints:\n  - name: \"endpoint_mistral\"\n    address: \"172.16.0.10\"\n    port: 8002\n    weight: 1\n\nsemantic_cache:\n  enabled: True\n  backend_type: \"memory\"\n  similarity_threshold: 0.8\n  max_entries: 1000\n  ttl_seconds: 3600\n\nprompt_guard:\n  enabled: False\n  threshold: 0.6\n  use_modernbert: true\n\ntools:\n  enabled: False\n  top_k: 3\n  similarity_threshold: 0.2\n", "intent": "Route queries to mistral, using embedding-based routing, with memory semantic cache, for ai-gateway deployment", "deployment_context": "ai-gateway", "source": "template", "values": {"decision_name": "support_decision", "model_name": "mistral", "signal_type": "embedding", "category1": "general", "category2": "engineering", "endpoint_address": "172.16.0.10", "endpoint_port": 8002, "endpoint_weight": 1, "cache_enabled": true, "cache_backend": "memory", "cache_threshold": 0.8, "guard_enabled": false, "guard_threshold": 0.6, "tools_enabled": false, "deployment_context": "ai-gateway"}}
{"id": "template_59084", "config": "# Semantic Router Configuration\n# Generated from template\n\ndecisions:\n  - name: \"support_decision\"\n    modelRefs:\n      - model: \"llama3\"\n        use_reasoning: true\n    signals:\n      - type: \"keyword\"\n        categories:\n          - \"general\"\n          - \"finance\"\n\nmodel_config:\n  llama3:\n    reasoning_family: \"llama3\"\n    preferred_endpoints:\n      - \"endpoint_llama3\"\n\nvllm_endpoints:\n  - name: \"endpoint_llama3\"\n    address: \"10.0.0.50\"\n    port: 8000\n    weight: 2\n\nsemantic_cache:\n  enabled: False\n  backend_type: \"milvus\"\n  similarity_threshold: 0.8\n  max_entries: 1000\n  ttl_seconds: 3600\n\nprompt_guard:\n  enabled: False\n  threshold: 0.7\n  use_modernbert: true\n\ntools:\n  enabled: True\n  top_k: 3\n  similarity_threshold: 0.2\n", "intent": "Route queries to llama3, using keyword-based routing, with tools auto-selection, for ai-gateway deployment", "deployment_context": "ai-gateway", "source": "template", "values": {"decision_name": "support_decision", "model_name": "llama3", "signal_type": "keyword", "category1": "general", "category2": "finance", "endpoint_address": "10.0.0.50", "endpoint_port": 8000, "endpoint_weight": 2, "cache_enabled": false, "cache_backend": "milvus", "cache_threshold": 0.8, "guard_enabled": false, "guard_threshold": 0.7, "tools_enabled": true, "deployment_context": "ai-gateway"}}
{"id": "template_8295", "config": "# Semantic Router Configuration\n# Generated from template\n\ndecisions:\n  - name: \"technical_decision\"\n    modelRefs:\n      - model: \"qwen3\"\n        use_reasoning: true\n    signals:\n      - type: \"domain\"\n        categories:\n          - \"business\"\n          - \"customer_service\"\n\nmodel_config:\n  qwen3:\n    reasoning_family: \"qwen3\"\n    preferred_endpoints:\n      - \"endpoint_qwen3\"\n\nvllm_endpoints:\n  - name: \"endpoint_qwen3\"\n    address: \"192.168.1.100\"\n    port: 8002\n    weight: 2\n\nsemantic_cache:\n  enabled: True\n  backend_type: \"memory\"\n  similarity_threshold: 0.7\n  max_entries: 1000\n  ttl_seconds: 3600\n\nprompt_guard:\n  enabled: True\n  threshold: 0.7\n  use_modernbert: true\n\ntools:\n  enabled: False\n  top_k: 3\n  similarity_threshold: 0.2\n", "intent": "Route queries to qwen3, using domain-based routing, with memory semantic cache, with PII detection, for quickstart deployment", "deployment_context": "quickstart", "source": "template", "values": {"decision_name": "technical_decision", "model_name": "qwen3", "signal_type": "domain", "category1": "business", "category2": "customer_service", "endpoint_address": "192.168.1.100", "endpoint_port": 8002, "endpoint_weight": 2, "cache_enabled": true, "cache_backend": "memory", "cache_threshold": 0.7, "guard_enabled": true, "guard_threshold": 0.7, "tools_enabled": false, "deployment_context": "quickstart"}}
{"id": "template_32494", "config": "# Semantic Router Configuration\n# Generated from template\n\ndecisions:\n  - name: \"technical_decision\"\n    modelRefs:\n      - model: \"qwen3\"\n        use_reasoning: true\n    signals:\n      - type: \"embedding\"\n        categories:\n          - \"technical\"\n          - \"engineering\"\n\nmodel_config:\n  qwen3:\n    reasoning_family: \"qwen3\"\n    preferred_endpoints:\n      - \"endpoint_qwen3\"\n\nvllm_endpoints:\n  - name: \"endpoint_qwen3\"\n    address: \"172.28.0.20\"\n    port: 8002\n    weight: 2\n\nsemantic_cache:\n  enabled: True\n  backend_type: \"redis\"\n  similarity_threshold: 0.7\n  max_entries: 1000\n  ttl_seconds: 3600\n\nprompt_guard:\n  enabled: False\n  threshold: 0.8\n  use_modernbert: true\n\ntools:\n  enabled: False\n  top_k: 3\n  similarity_threshold: 0.2\n", "intent": "Route queries to qwen3, using embedding-based routing, with redis semantic cache, for kubernetes deployment", "deployment_context": "kubernetes", "source": "template", "values": {"decision_name": "technical_decision", "model_name": "qwen3", "signal_type": "embedding", "category1": "technical", "category2": "engineering", "endpoint_address": "172.28.0.20", "endpoint_port": 8002, "endpoint_weight": 2, "cache_enabled": true, "cache_backend": "redis", "cache_threshold": 0.7, "guard_enabled": false, "guard_threshold": 0.8, "tools_enabled": false, "deployment_context": "kubernetes"}}
{"id": "template_91067", "config": "# Semantic Router Configuration\n# Generated from template\n\ndecisions:\n  - name: \"technical_decision\"\n    modelRefs:\n      - model: \"qwen3\"\n        use_reasoning: true\n    signals:\n      - type: \"embedding\"\n        categories:\n          - \"general\"\n          - \"customer_service\"\n\nmodel_config:\n  qwen3:\n    reasoning_family: \"qwen3\"\n    preferred_endpoints:\n      - \"endpoint_qwen3\"\n\nvllm_endpoints:\n  - name: \"endpoint_qwen3\"\n    address: \"10.0.0.50\"\n    port: 8080\n    weight: 3\n\nsemantic_cache:\n  enabled: True\n  backend_type: \"redis\"\n  similarity_threshold: 0.9\n  max_entries: 1000\n  ttl_seconds: 3600\n\nprompt_guard:\n  enabled: True\n  threshold: 0.8\n  use_modernbert: true\n\ntools:\n  enabled: False\n  top_k: 3\n  similarity_threshold: 0.2\n", "intent": "Route queries to qwen3, using embedding-based routing, with redis semantic cache, with PII detection, for ai-gateway deployment", "deployment_context": "ai-gateway", "source": "template", "values": {"decision_name": "technical_decision", "model_name": "qwen3", "signal_type": "embedding", "category1": "general", "category2": "customer_service", "endpoint_address": "10.0.0.50", "endpoint_port": 8080, "endpoint_weight": 3, "cache_enabled": true, "cache_backend": "redis", "cache_threshold": 0.9, "guard_enabled": true, "guard_threshold": 0.8, "tools_enabled": false, "deployment_context": "ai-gateway"}}
{"id": "template_72213", "config": "# Semantic Router Configuration\n# Generated from template\n\ndecisions:\n  - name: \"support_decision\"\n    modelRefs:\n      - model: \"mistral\"\n        use_reasoning: true\n    signals:\n      - type: \"embedding\"\n        categories:\n          - \"support\"\n          - \"engineering\"\n\nmodel_config:\n  mistral:\n    reasoning_family: \"mistral\"\n    preferred_endpoints:\n      - \"endpoint_mistral\"\n\nvllm_endpoints:\n  - name: \"endpoint_mistral\"\n    address: \"10.0.0.50\"\n    port: 11434\n    weight: 3\n\nsemantic_cache:\n  enabled: True\n  backend_type: \"memory\"\n  similarity_threshold: 0.9\n  max_entries: 1000\n  ttl_seconds: 3600\n\nprompt_guard:\n  enabled: False\n  threshold: 0.6\n  use_modernbert: true\n\ntools:\n  enabled: True\n  top_k: 3\n  similarity_threshold: 0.2\n", "intent": "Route queries to mistral, using embedding-based routing, with memory semantic cache, with tools auto-selection, for kubernetes deployment", "deployment_context": "kubernetes", "source": "template", "values": {"decision_name": "support_decision", "model_name": "mistral", "signal_type": "embedding", "category1": "support", "category2": "engineering", "endpoint_address": "10.0.0.50", "endpoint_port": 11434, "endpoint_weight": 3, "cache_enabled": true, "cache_backend": "memory", "cache_threshold": 0.9, "guard_enabled": false, "guard_threshold": 0.6, "tools_enabled": true, "deployment_context": "kubernetes"}}
{"id": "template_83104", "config": "# Semantic Router Configuration\n# Generated from template\n\ndecisions:\n  - name: \"general_decision\"\n    modelRefs:\n      - model: \"phi4\"\n        use_reasoning: true\n    signals:\n      - type: \"keyword\"\n        categories:\n          - \"general\"\n          - \"engineering\"\n\nmodel_config:\n  phi4:\n    reasoning_family: \"phi4\"\n    preferred_endpoints:\n      - \"endpoint_phi4\"\n\nvllm_endpoints:\n  - name: \"endpoint_phi4\"\n    address: \"172.28.0.20\"\n    port: 8002\n    weight: 3\n\nsemantic_cache:\n  enabled: False\n  backend_type: \"memory\"\n  similarity_threshold: 0.7\n  max_entries: 1000\n  ttl_seconds: 3600\n\nprompt_guard:\n  enabled: True\n  threshold: 0.7\n  use_modernbert: true\n\ntools:\n  enabled: True\n  top_k: 3\n  similarity_threshold: 0.2\n", "intent": "Route queries to phi4, using keyword-based routing, with PII detection, with tools auto-selection, for istio deployment", "deployment_context": "istio", "source": "template", "values": {"decision_name": "general_decision", "model_name": "phi4", "signal_type": "keyword", "category1": "general", "category2": "engineering", "endpoint_address": "172.28.0.20", "endpoint_port": 8002, "endpoint_weight": 3, "cache_enabled": false, "cache_backend": "memory", "cache_threshold": 0.7, "guard_enabled": true, "guard_threshold": 0.7, "tools_enabled": true, "deployment_context": "istio"}}
{"id": "template_86110", "config": "# Semantic Router Configuration\n# Generated from template\n\ndecisions:\n  - name: \"business_decision\"\n    modelRefs:\n      - model: \"qwen3\"\n        use_reasoning: true\n    signals:\n      - type: \"keyword\"\n        categories:\n          - \"business\"\n          - \"customer_service\"\n\nmodel_config:\n  qwen3:\n    reasoning_family: \"qwen3\"\n    preferred_endpoints:\n      - \"endpoint_qwen3\"\n\nvllm_endpoints:\n  - name: \"endpoint_qwen3\"\n    address: \"10.0.0.50\"\n    port: 11434\n    weight: 1\n\nsemantic_cache:\n  enabled: True\n  backend_type: \"milvus\"\n  similarity_threshold: 0.7\n  max_entries: 1000\n  ttl_seconds: 3600\n\nprompt_guard:\n  enabled: True\n  threshold: 0.7\n  use_modernbert: true\n\ntools:\n  enabled: True\n  top_k: 3\n  similarity_threshold: 0.2\n", "intent": "Route queries to qwen3, using keyword-based routing, with milvus semantic cache, with PII detection, with tools auto-selection, for istio deployment", "deployment_context": "istio", "source": "template", "values": {"decision_name": "business_decision", "model_name": "qwen3", "signal_type": "keyword", "category1": "business", "category2": "customer_service", "endpoint_address": "10.0.0.50", "endpoint_port": 11434, "endpoint_weight": 1, "cache_enabled": true, "cache_backend": "milvus", "cache_threshold": 0.7, "guard_enabled": true, "guard_threshold": 0.7, "tools_enabled": true, "deployment_context": "istio"}}
{"id": "template_14901", "config": "# Semantic Router Configuration\n# Generated from template\n\ndecisions:\n  - name: \"general_decision\"\n    modelRefs:\n      - model: \"llama3\"\n        use_reasoning: true\n    signals:\n      - type: \"keyword\"\n        categories:\n          - \"business\"\n          - \"sales\"\n\nmodel_config:\n  llama3:\n    reasoning_family: \"llama3\"\n    preferred_endpoints:\n      - \"endpoint_llama3\"\n\nvllm_endpoints:\n  - name: \"endpoint_llama3\"\n    address: \"172.16.0.10\"\n    port: 11434\n    weight: 2\n\nsemantic_cache:\n  enabled: False\n  backend_type: \"memory\"\n  similarity_threshold: 0.9\n  max_entries: 1000\n  ttl_seconds: 3600\n\nprompt_guard:\n  enabled: False\n  threshold: 0.8\n  use_modernbert: true\n\ntools:\n  enabled: True\n  top_k: 3\n  similarity_threshold: 0.2\n", "intent": "Route queries to llama3, using keyword-based routing, with tools auto-selection, for istio deployment", "deployment_context": "istio", "source": "template", "values": {"decision_name": "general_decision", "model_name": "llama3", "signal_type": "keyword", "category1": "business", "category2": "sales", "endpoint_address": "172.16.0.10", "endpoint_port": 11434, "endpoint_weight": 2, "cache_enabled": false, "cache_backend": "memory", "cache_threshold": 0.9, "guard_enabled": false, "guard_threshold": 0.8, "tools_enabled": true, "deployment_context": "istio"}}
{"id": "template_27403", "config": "# Semantic Router Configuration\n# Generated from template\n\ndecisions:\n  - name: \"general_decision\"\n    modelRefs:\n      - model: \"phi4\"\n        use_reasoning: true\n    signals:\n      - type: \"embedding\"\n        categories:\n          - \"support\"\n          - \"finance\"\n\nmodel_config:\n  phi4:\n    reasoning_family: \"phi4\"\n    preferred_endpoints:\n      - \"endpoint_phi4\"\n\nvllm_endpoints:\n  - name: \"endpoint_phi4\"\n    address: \"172.16.0.10\"\n    port: 8080\n    weight: 3\n\nsemantic_cache:\n  enabled: True\n  backend_type: \"memory\"\n  similarity_threshold: 0.8\n  max_entries: 1000\n  ttl_seconds: 3600\n\nprompt_guard:\n  enabled: False\n  threshold: 0.6\n  use_modernbert: true\n\ntools:\n  enabled: False\n  top_k: 3\n  similarity_threshold: 0.2\n", "intent": "Route queries to phi4, using embedding-based routing, with memory semantic cache, for ai-gateway deployment", "deployment_context": "ai-gateway", "source": "template", "values": {"decision_name": "general_decision", "model_name": "phi4", "signal_type": "embedding", "category1": "support", "category2": "finance", "endpoint_address": "172.16.0.10", "endpoint_port": 8080, "endpoint_weight": 3, "cache_enabled": true, "cache_backend": "memory", "cache_threshold": 0.8, "guard_enabled": false, "guard_threshold": 0.6, "tools_enabled": false, "deployment_context": "ai-gateway"}}
{"id": "template_7626", "config": "# Semantic Router Configuration\n# Generated from template\n\ndecisions:\n  - name: \"business_decision\"\n    modelRefs:\n      - model: \"llama3\"\n        use_reasoning: true\n    signals:\n      - type: \"keyword\"\n        categories:\n          - \"technical\"\n          - \"engineering\"\n\nmodel_config:\n  llama3:\n    reasoning_family: \"llama3\"\n    preferred_endpoints:\n      - \"endpoint_llama3\"\n\nvllm_endpoints:\n  - name: \"endpoint_llama3\"\n    address: \"172.28.0.20\"\n    port: 11434\n    weight: 1\n\nsemantic_cache:\n  enabled: True\n  backend_type: \"memory\"\n  similarity_threshold: 0.7\n  max_entries: 1000\n  ttl_seconds: 3600\n\nprompt_guard:\n  enabled: True\n  threshold: 0.6\n  use_modernbert: true\n\ntools:\n  enabled: False\n  top_k: 3\n  similarity_threshold: 0.2\n", "intent": "Route queries to llama3, using keyword-based routing, with memory semantic cache, with PII detection, for kubernetes deployment", "deployment_context": "kubernetes", "source": "template", "values": {"decision_name": "business_decision", "model_name": "llama3", "signal_type": "keyword", "category1": "technical", "category2": "engineering", "endpoint_address": "172.28.0.20", "endpoint_port": 11434, "endpoint_weight": 1, "cache_enabled": true, "cache_backend": "memory", "cache_threshold": 0.7, "guard_enabled": true, "guard_threshold": 0.6, "tools_enabled": false, "deployment_context": "kubernetes"}}
{"id": "template_82934", "config": "# Semantic Router Configuration\n# Generated from template\n\ndecisions:\n  - name: \"general_decision\"\n    modelRefs:\n      - model: \"mistral\"\n        use_reasoning: true\n    signals:\n      - type: \"domain\"\n        categories:\n          - \"business\"\n          - \"engineering\"\n\nmodel_config:\n  mistral:\n    reasoning_family: \"mistral\"\n    preferred_endpoints:\n      - \"endpoint_mistral\"\n\nvllm_endpoints:\n  - name: \"endpoint_mistral\"\n    address: \"172.16.0.10\"\n    port: 8002\n    weight: 1\n\nsemantic_cache:\n  enabled: False\n  backend_type: \"memory\"\n  similarity_threshold: 0.8\n  max_entries: 1000\n  ttl_seconds: 3600\n\nprompt_guard:\n  enabled: False\n  threshold: 0.6\n  use_modernbert: true\n\ntools:\n  enabled: False\n  top_k: 3\n  similarity_threshold: 0.2\n", "intent": "Route queries to mistral, using domain-based routing, for kubernetes deployment", "deployment_context": "kubernetes", "source": "template", "values": {"decision_name": "general_decision", "model_name": "mistral", "signal_type": "domain", "category1": "business", "category2": "engineering", "endpoint_address": "172.16.0.10", "endpoint_port": 8002, "endpoint_weight": 1, "cache_enabled": false, "cache_backend": "memory", "cache_threshold": 0.8, "guard_enabled": false, "guard_threshold": 0.6, "tools_enabled": false, "deployment_context": "kubernetes"}}
{"id": "template_35351", "config": "# Semantic Router Configuration\n# Generated from template\n\ndecisions:\n  - name: \"general_decision\"\n    modelRefs:\n      - model: \"llama3\"\n        use_reasoning: true\n    signals:\n      - type: \"embedding\"\n        categories:\n          - \"support\"\n          - \"customer_service\"\n\nmodel_config:\n  llama3:\n    reasoning_family: \"llama3\"\n    preferred_endpoints:\n      - \"endpoint_llama3\"\n\nvllm_endpoints:\n  - name: \"endpoint_llama3\"\n    address: \"172.28.0.20\"\n    port: 11434\n    weight: 3\n\nsemantic_cache:\n  enabled: False\n  backend_type: \"milvus\"\n  similarity_threshold: 0.7\n  max_entries: 1000\n  ttl_seconds: 3600\n\nprompt_guard:\n  enabled: True\n  threshold: 0.8\n  use_modernbert: true\n\ntools:\n  enabled: False\n  top_k: 3\n  similarity_threshold: 0.2\n", "intent": "Route queries to llama3, using embedding-based routing, with PII detection, for ai-gateway deployment", "deployment_context": "ai-gateway", "source": "template", "values": {"decision_name": "general_decision", "model_name": "llama3", "signal_type": "embedding", "category1": "support", "category2": "customer_service", "endpoint_address": "172.28.0.20", "endpoint_port": 11434, "endpoint_weight": 3, "cache_enabled": false, "cache_backend": "milvus", "cache_threshold": 0.7, "guard_enabled": true, "guard_threshold": 0.8, "tools_enabled": false, "deployment_context": "ai-gateway"}}
{"id": "template_38853", "config": "# Semantic Router Configuration\n# Generated from template\n\ndecisions:\n  - name: \"business_decision\"\n    modelRefs:\n      - model: \"qwen3\"\n        use_reasoning: true\n    signals:\n      - type: \"embedding\"\n        categories:\n          - \"general\"\n          - \"finance\"\n\nmodel_config:\n  qwen3:\n    reasoning_family: \"qwen3\"\n    preferred_endpoints:\n      - \"endpoint_qwen3\"\n\nvllm_endpoints:\n  - name: \"endpoint_qwen3\"\n    address: \"172.28.0.20\"\n    port: 8080\n    weight: 2\n\nsemantic_cache:\n  enabled: True\n  backend_type: \"memory\"\n  similarity_threshold: 0.7\n  max_entries: 1000\n  ttl_seconds: 3600\n\nprompt_guard:\n  enabled: True\n  threshold: 0.7\n  use_modernbert: true\n\ntools:\n  enabled: False\n  top_k: 3\n  similarity_threshold: 0.2\n", "intent": "Route queries to qwen3, using embedding-based routing, with memory semantic cache, with PII detection, for quickstart deployment", "deployment_context": "quickstart", "source": "template", "values": {"decision_name": "business_decision", "model_name": "qwen3", "signal_type": "embedding", "category1": "general", "category2": "finance", "endpoint_address": "172.28.0.20", "endpoint_port": 8080, "endpoint_weight": 2, "cache_enabled": true, "cache_backend": "memory", "cache_threshold": 0.7, "guard_enabled": true, "guard_threshold": 0.7, "tools_enabled": false, "deployment_context": "quickstart"}}
{"id": "template_12587", "config": "# Semantic Router Configuration\n# Generated from template\n\ndecisions:\n  - name: \"support_decision\"\n    modelRefs:\n      - model: \"llama3\"\n        use_reasoning: true\n    signals:\n      - type: \"keyword\"\n        categories:\n          - \"business\"\n          - \"sales\"\n\nmodel_config:\n  llama3:\n    reasoning_family: \"llama3\"\n    preferred_endpoints:\n      - \"endpoint_llama3\"\n\nvllm_endpoints:\n  - name: \"endpoint_llama3\"\n    address: \"172.28.0.20\"\n    port: 8002\n    weight: 1\n\nsemantic_cache:\n  enabled: False\n  backend_type: \"memory\"\n  similarity_threshold: 0.8\n  max_entries: 1000\n  ttl_seconds: 3600\n\nprompt_guard:\n  enabled: True\n  threshold: 0.7\n  use_modernbert: true\n\ntools:\n  enabled: False\n  top_k: 3\n  similarity_threshold: 0.2\n", "intent": "Route queries to llama3, using keyword-based routing, with PII detection, for istio deployment", "deployment_context": "istio", "source": "template", "values": {"decision_name": "support_decision", "model_name": "llama3", "signal_type": "keyword", "category1": "business", "category2": "sales", "endpoint_address": "172.28.0.20", "endpoint_port": 8002, "endpoint_weight": 1, "cache_enabled": false, "cache_backend": "memory", "cache_threshold": 0.8, "guard_enabled": true, "guard_threshold": 0.7, "tools_enabled": false, "deployment_context": "istio"}}
{"id": "template_12882", "config": "# Semantic Router Configuration\n# Generated from template\n\ndecisions:\n  - name: \"support_decision\"\n    modelRefs:\n      - model: \"mistral\"\n        use_reasoning: true\n    signals:\n      - type: \"embedding\"\n        categories:\n          - \"support\"\n          - \"finance\"\n\nmodel_config:\n  mistral:\n    reasoning_family: \"mistral\"\n    preferred_endpoints:\n      - \"endpoint_mistral\"\n\nvllm_endpoints:\n  - name: \"endpoint_mistral\"\n    address: \"172.28.0.20\"\n    port: 8000\n    weight: 1\n\nsemantic_cache:\n  enabled: True\n  backend_type: \"memory\"\n  similarity_threshold: 0.7\n  max_entries: 1000\n  ttl_seconds: 3600\n\nprompt_guard:\n  enabled: False\n  threshold: 0.8\n  use_modernbert: true\n\ntools:\n  enabled: True\n  top_k: 3\n  similarity_threshold: 0.2\n", "intent": "Route queries to mistral, using embedding-based routing, with memory semantic cache, with tools auto-selection, for quickstart deployment", "deployment_context": "quickstart", "source": "template", "values": {"decision_name": "support_decision", "model_name": "mistral", "signal_type": "embedding", "category1": "support", "category2": "finance", "endpoint_address": "172.28.0.20", "endpoint_port": 8000, "endpoint_weight": 1, "cache_enabled": true, "cache_backend": "memory", "cache_threshold": 0.7, "guard_enabled": false, "guard_threshold": 0.8, "tools_enabled": true, "deployment_context": "quickstart"}}
{"id": "template_43870", "config": "# Semantic Router Configuration\n# Generated from template\n\ndecisions:\n  - name: \"general_decision\"\n    modelRefs:\n      - model: \"mistral\"\n        use_reasoning: true\n    signals:\n      - type: \"domain\"\n        categories:\n          - \"general\"\n          - \"sales\"\n\nmodel_config:\n  mistral:\n    reasoning_family: \"mistral\"\n    preferred_endpoints:\n      - \"endpoint_mistral\"\n\nvllm_endpoints:\n  - name: \"endpoint_mistral\"\n    address: \"172.28.0.20\"\n    port: 8000\n    weight: 2\n\nsemantic_cache:\n  enabled: False\n  backend_type: \"memory\"\n  similarity_threshold: 0.9\n  max_entries: 1000\n  ttl_seconds: 3600\n\nprompt_guard:\n  enabled: False\n  threshold: 0.6\n  use_modernbert: true\n\ntools:\n  enabled: True\n  top_k: 3\n  similarity_threshold: 0.2\n", "intent": "Route queries to mistral, using domain-based routing, with tools auto-selection, for kubernetes deployment", "deployment_context": "kubernetes", "source": "template", "values": {"decision_name": "general_decision", "model_name": "mistral", "signal_type": "domain", "category1": "general", "category2": "sales", "endpoint_address": "172.28.0.20", "endpoint_port": 8000, "endpoint_weight": 2, "cache_enabled": false, "cache_backend": "memory", "cache_threshold": 0.9, "guard_enabled": false, "guard_threshold": 0.6, "tools_enabled": true, "deployment_context": "kubernetes"}}
{"id": "template_78016", "config": "# Semantic Router Configuration\n# Generated from template\n\ndecisions:\n  - name: \"technical_decision\"\n    modelRefs:\n      - model: \"phi4\"\n        use_reasoning: true\n    signals:\n      - type: \"domain\"\n        categories:\n          - \"support\"\n          - \"sales\"\n\nmodel_config:\n  phi4:\n    reasoning_family: \"phi4\"\n    preferred_endpoints:\n      - \"endpoint_phi4\"\n\nvllm_endpoints:\n  - name: \"endpoint_phi4\"\n    address: \"172.28.0.20\"\n    port: 8002\n    weight: 3\n\nsemantic_cache:\n  enabled: False\n  backend_type: \"milvus\"\n  similarity_threshold: 0.8\n  max_entries: 1000\n  ttl_seconds: 3600\n\nprompt_guard:\n  enabled: True\n  threshold: 0.6\n  use_modernbert: true\n\ntools:\n  enabled: False\n  top_k: 3\n  similarity_threshold: 0.2\n", "intent": "Route queries to phi4, using domain-based routing, with PII detection, for quickstart deployment", "deployment_context": "quickstart", "source": "template", "values": {"decision_name": "technical_decision", "model_name": "phi4", "signal_type": "domain", "category1": "support", "category2": "sales", "endpoint_address": "172.28.0.20", "endpoint_port": 8002, "endpoint_weight": 3, "cache_enabled": false, "cache_backend": "milvus", "cache_threshold": 0.8, "guard_enabled": true, "guard_threshold": 0.6, "tools_enabled": false, "deployment_context": "quickstart"}}
{"id": "template_81884", "config": "# Semantic Router Configuration\n# Generated from template\n\ndecisions:\n  - name: \"business_decision\"\n    modelRefs:\n      - model: \"qwen3\"\n        use_reasoning: true\n    signals:\n      - type: \"keyword\"\n        categories:\n          - \"business\"\n          - \"customer_service\"\n\nmodel_config:\n  qwen3:\n    reasoning_family: \"qwen3\"\n    preferred_endpoints:\n      - \"endpoint_qwen3\"\n\nvllm_endpoints:\n  - name: \"endpoint_qwen3\"\n    address: \"172.16.0.10\"\n    port: 8002\n    weight: 3\n\nsemantic_cache:\n  enabled: True\n  backend_type: \"redis\"\n  similarity_threshold: 0.7\n  max_entries: 1000\n  ttl_seconds: 3600\n\nprompt_guard:\n  enabled: False\n  threshold: 0.6\n  use_modernbert: true\n\ntools:\n  enabled: True\n  top_k: 3\n  similarity_threshold: 0.2\n", "intent": "Route queries to qwen3, using keyword-based routing, with redis semantic cache, with tools auto-selection, for kubernetes deployment", "deployment_context": "kubernetes", "source": "template", "values": {"decision_name": "business_decision", "model_name": "qwen3", "signal_type": "keyword", "category1": "business", "category2": "customer_service", "endpoint_address": "172.16.0.10", "endpoint_port": 8002, "endpoint_weight": 3, "cache_enabled": true, "cache_backend": "redis", "cache_threshold": 0.7, "guard_enabled": false, "guard_threshold": 0.6, "tools_enabled": true, "deployment_context": "kubernetes"}}
{"id": "template_44863", "config": "# Semantic Router Configuration\n# Generated from template\n\ndecisions:\n  - name: \"business_decision\"\n    modelRefs:\n      - model: \"phi4\"\n        use_reasoning: true\n    signals:\n      - type: \"keyword\"\n        categories:\n          - \"support\"\n          - \"finance\"\n\nmodel_config:\n  phi4:\n    reasoning_family: \"phi4\"\n    preferred_endpoints:\n      - \"endpoint_phi4\"\n\nvllm_endpoints:\n  - name: \"endpoint_phi4\"\n    address: \"10.0.0.50\"\n    port: 11434\n    weight: 3\n\nsemantic_cache:\n  enabled: False\n  backend_type: \"redis\"\n  similarity_threshold: 0.8\n  max_entries: 1000\n  ttl_seconds: 3600\n\nprompt_guard:\n  enabled: True\n  threshold: 0.6\n  use_modernbert: true\n\ntools:\n  enabled: True\n  top_k: 3\n  similarity_threshold: 0.2\n", "intent": "Route queries to phi4, using keyword-based routing, with PII detection, with tools auto-selection, for kubernetes deployment", "deployment_context": "kubernetes", "source": "template", "values": {"decision_name": "business_decision", "model_name": "phi4", "signal_type": "keyword", "category1": "support", "category2": "finance", "endpoint_address": "10.0.0.50", "endpoint_port": 11434, "endpoint_weight": 3, "cache_enabled": false, "cache_backend": "redis", "cache_threshold": 0.8, "guard_enabled": true, "guard_threshold": 0.6, "tools_enabled": true, "deployment_context": "kubernetes"}}
{"id": "template_41346", "config": "# Semantic Router Configuration\n# Generated from template\n\ndecisions:\n  - name: \"technical_decision\"\n    modelRefs:\n      - model: \"mistral\"\n        use_reasoning: true\n    signals:\n      - type: \"domain\"\n        categories:\n          - \"technical\"\n          - \"customer_service\"\n\nmodel_config:\n  mistral:\n    reasoning_family: \"mistral\"\n    preferred_endpoints:\n      - \"endpoint_mistral\"\n\nvllm_endpoints:\n  - name: \"endpoint_mistral\"\n    address: \"172.16.0.10\"\n    port: 8000\n    weight: 1\n\nsemantic_cache:\n  enabled: True\n  backend_type: \"milvus\"\n  similarity_threshold: 0.7\n  max_entries: 1000\n  ttl_seconds: 3600\n\nprompt_guard:\n  enabled: False\n  threshold: 0.8\n  use_modernbert: true\n\ntools:\n  enabled: True\n  top_k: 3\n  similarity_threshold: 0.2\n", "intent": "Route queries to mistral, using domain-based routing, with milvus semantic cache, with tools auto-selection, for kubernetes deployment", "deployment_context": "kubernetes", "source": "template", "values": {"decision_name": "technical_decision", "model_name": "mistral", "signal_type": "domain", "category1": "technical", "category2": "customer_service", "endpoint_address": "172.16.0.10", "endpoint_port": 8000, "endpoint_weight": 1, "cache_enabled": true, "cache_backend": "milvus", "cache_threshold": 0.7, "guard_enabled": false, "guard_threshold": 0.8, "tools_enabled": true, "deployment_context": "kubernetes"}}
{"id": "template_16497", "config": "# Semantic Router Configuration\n# Generated from template\n\ndecisions:\n  - name: \"general_decision\"\n    modelRefs:\n      - model: \"llama3\"\n        use_reasoning: true\n    signals:\n      - type: \"embedding\"\n        categories:\n          - \"technical\"\n          - \"engineering\"\n\nmodel_config:\n  llama3:\n    reasoning_family: \"llama3\"\n    preferred_endpoints:\n      - \"endpoint_llama3\"\n\nvllm_endpoints:\n  - name: \"endpoint_llama3\"\n    address: \"192.168.1.100\"\n    port: 8002\n    weight: 1\n\nsemantic_cache:\n  enabled: True\n  backend_type: \"memory\"\n  similarity_threshold: 0.7\n  max_entries: 1000\n  ttl_seconds: 3600\n\nprompt_guard:\n  enabled: False\n  threshold: 0.7\n  use_modernbert: true\n\ntools:\n  enabled: False\n  top_k: 3\n  similarity_threshold: 0.2\n", "intent": "Route queries to llama3, using embedding-based routing, with memory semantic cache, for ai-gateway deployment", "deployment_context": "ai-gateway", "source": "template", "values": {"decision_name": "general_decision", "model_name": "llama3", "signal_type": "embedding", "category1": "technical", "category2": "engineering", "endpoint_address": "192.168.1.100", "endpoint_port": 8002, "endpoint_weight": 1, "cache_enabled": true, "cache_backend": "memory", "cache_threshold": 0.7, "guard_enabled": false, "guard_threshold": 0.7, "tools_enabled": false, "deployment_context": "ai-gateway"}}
{"id": "template_56456", "config": "# Semantic Router Configuration\n# Generated from template\n\ndecisions:\n  - name: \"technical_decision\"\n    modelRefs:\n      - model: \"phi4\"\n        use_reasoning: true\n    signals:\n      - type: \"domain\"\n        categories:\n          - \"business\"\n          - \"customer_service\"\n\nmodel_config:\n  phi4:\n    reasoning_family: \"phi4\"\n    preferred_endpoints:\n      - \"endpoint_phi4\"\n\nvllm_endpoints:\n  - name: \"endpoint_phi4\"\n    address: \"172.28.0.20\"\n    port: 8000\n    weight: 2\n\nsemantic_cache:\n  enabled: False\n  backend_type: \"milvus\"\n  similarity_threshold: 0.8\n  max_entries: 1000\n  ttl_seconds: 3600\n\nprompt_guard:\n  enabled: True\n  threshold: 0.7\n  use_modernbert: true\n\ntools:\n  enabled: False\n  top_k: 3\n  similarity_threshold: 0.2\n", "intent": "Route queries to phi4, using domain-based routing, with PII detection, for ai-gateway deployment", "deployment_context": "ai-gateway", "source": "template", "values": {"decision_name": "technical_decision", "model_name": "phi4", "signal_type": "domain", "category1": "business", "category2": "customer_service", "endpoint_address": "172.28.0.20", "endpoint_port": 8000, "endpoint_weight": 2, "cache_enabled": false, "cache_backend": "milvus", "cache_threshold": 0.8, "guard_enabled": true, "guard_threshold": 0.7, "tools_enabled": false, "deployment_context": "ai-gateway"}}
{"id": "template_61448", "config": "# Semantic Router Configuration\n# Generated from template\n\ndecisions:\n  - name: \"business_decision\"\n    modelRefs:\n      - model: \"mistral\"\n        use_reasoning: true\n    signals:\n      - type: \"keyword\"\n        categories:\n          - \"business\"\n          - \"finance\"\n\nmodel_config:\n  mistral:\n    reasoning_family: \"mistral\"\n    preferred_endpoints:\n      - \"endpoint_mistral\"\n\nvllm_endpoints:\n  - name: \"endpoint_mistral\"\n    address: \"172.16.0.10\"\n    port: 11434\n    weight: 1\n\nsemantic_cache:\n  enabled: True\n  backend_type: \"redis\"\n  similarity_threshold: 0.7\n  max_entries: 1000\n  ttl_seconds: 3600\n\nprompt_guard:\n  enabled: False\n  threshold: 0.6\n  use_modernbert: true\n\ntools:\n  enabled: True\n  top_k: 3\n  similarity_threshold: 0.2\n", "intent": "Route queries to mistral, using keyword-based routing, with redis semantic cache, with tools auto-selection, for kubernetes deployment", "deployment_context": "kubernetes", "source": "template", "values": {"decision_name": "business_decision", "model_name": "mistral", "signal_type": "keyword", "category1": "business", "category2": "finance", "endpoint_address": "172.16.0.10", "endpoint_port": 11434, "endpoint_weight": 1, "cache_enabled": true, "cache_backend": "redis", "cache_threshold": 0.7, "guard_enabled": false, "guard_threshold": 0.6, "tools_enabled": true, "deployment_context": "kubernetes"}}
{"id": "template_61933", "config": "# Semantic Router Configuration\n# Generated from template\n\ndecisions:\n  - name: \"business_decision\"\n    modelRefs:\n      - model: \"llama3\"\n        use_reasoning: true\n    signals:\n      - type: \"keyword\"\n        categories:\n          - \"technical\"\n          - \"finance\"\n\nmodel_config:\n  llama3:\n    reasoning_family: \"llama3\"\n    preferred_endpoints:\n      - \"endpoint_llama3\"\n\nvllm_endpoints:\n  - name: \"endpoint_llama3\"\n    address: \"172.16.0.10\"\n    port: 11434\n    weight: 1\n\nsemantic_cache:\n  enabled: False\n  backend_type: \"redis\"\n  similarity_threshold: 0.7\n  max_entries: 1000\n  ttl_seconds: 3600\n\nprompt_guard:\n  enabled: False\n  threshold: 0.7\n  use_modernbert: true\n\ntools:\n  enabled: False\n  top_k: 3\n  similarity_threshold: 0.2\n", "intent": "Route queries to llama3, using keyword-based routing, for ai-gateway deployment", "deployment_context": "ai-gateway", "source": "template", "values": {"decision_name": "business_decision", "model_name": "llama3", "signal_type": "keyword", "category1": "technical", "category2": "finance", "endpoint_address": "172.16.0.10", "endpoint_port": 11434, "endpoint_weight": 1, "cache_enabled": false, "cache_backend": "redis", "cache_threshold": 0.7, "guard_enabled": false, "guard_threshold": 0.7, "tools_enabled": false, "deployment_context": "ai-gateway"}}
{"id": "template_87718", "config": "# Semantic Router Configuration\n# Generated from template\n\ndecisions:\n  - name: \"support_decision\"\n    modelRefs:\n      - model: \"phi4\"\n        use_reasoning: true\n    signals:\n      - type: \"embedding\"\n        categories:\n          - \"technical\"\n          - \"finance\"\n\nmodel_config:\n  phi4:\n    reasoning_family: \"phi4\"\n    preferred_endpoints:\n      - \"endpoint_phi4\"\n\nvllm_endpoints:\n  - name: \"endpoint_phi4\"\n    address: \"192.168.1.100\"\n    port: 11434\n    weight: 3\n\nsemantic_cache:\n  enabled: True\n  backend_type: \"milvus\"\n  similarity_threshold: 0.7\n  max_entries: 1000\n  ttl_seconds: 3600\n\nprompt_guard:\n  enabled: True\n  threshold: 0.8\n  use_modernbert: true\n\ntools:\n  enabled: False\n  top_k: 3\n  similarity_threshold: 0.2\n", "intent": "Route queries to phi4, using embedding-based routing, with milvus semantic cache, with PII detection, for kubernetes deployment", "deployment_context": "kubernetes", "source": "template", "values": {"decision_name": "support_decision", "model_name": "phi4", "signal_type": "embedding", "category1": "technical", "category2": "finance", "endpoint_address": "192.168.1.100", "endpoint_port": 11434, "endpoint_weight": 3, "cache_enabled": true, "cache_backend": "milvus", "cache_threshold": 0.7, "guard_enabled": true, "guard_threshold": 0.8, "tools_enabled": false, "deployment_context": "kubernetes"}}
{"id": "template_58729", "config": "# Semantic Router Configuration\n# Generated from template\n\ndecisions:\n  - name: \"general_decision\"\n    modelRefs:\n      - model: \"mistral\"\n        use_reasoning: true\n    signals:\n      - type: \"domain\"\n        categories:\n          - \"general\"\n          - \"customer_service\"\n\nmodel_config:\n  mistral:\n    reasoning_family: \"mistral\"\n    preferred_endpoints:\n      - \"endpoint_mistral\"\n\nvllm_endpoints:\n  - name: \"endpoint_mistral\"\n    address: \"172.28.0.20\"\n    port: 8080\n    weight: 2\n\nsemantic_cache:\n  enabled: True\n  backend_type: \"milvus\"\n  similarity_threshold: 0.8\n  max_entries: 1000\n  ttl_seconds: 3600\n\nprompt_guard:\n  enabled: True\n  threshold: 0.6\n  use_modernbert: true\n\ntools:\n  enabled: False\n  top_k: 3\n  similarity_threshold: 0.2\n", "intent": "Route queries to mistral, using domain-based routing, with milvus semantic cache, with PII detection, for ai-gateway deployment", "deployment_context": "ai-gateway", "source": "template", "values": {"decision_name": "general_decision", "model_name": "mistral", "signal_type": "domain", "category1": "general", "category2": "customer_service", "endpoint_address": "172.28.0.20", "endpoint_port": 8080, "endpoint_weight": 2, "cache_enabled": true, "cache_backend": "milvus", "cache_threshold": 0.8, "guard_enabled": true, "guard_threshold": 0.6, "tools_enabled": false, "deployment_context": "ai-gateway"}}
{"id": "template_5416", "config": "# Semantic Router Configuration\n# Generated from template\n\ndecisions:\n  - name: \"business_decision\"\n    modelRefs:\n      - model: \"mistral\"\n        use_reasoning: true\n    signals:\n      - type: \"domain\"\n        categories:\n          - \"support\"\n          - \"finance\"\n\nmodel_config:\n  mistral:\n    reasoning_family: \"mistral\"\n    preferred_endpoints:\n      - \"endpoint_mistral\"\n\nvllm_endpoints:\n  - name: \"endpoint_mistral\"\n    address: \"192.168.1.100\"\n    port: 8080\n    weight: 1\n\nsemantic_cache:\n  enabled: False\n  backend_type: \"milvus\"\n  similarity_threshold: 0.8\n  max_entries: 1000\n  ttl_seconds: 3600\n\nprompt_guard:\n  enabled: False\n  threshold: 0.6\n  use_modernbert: true\n\ntools:\n  enabled: True\n  top_k: 3\n  similarity_threshold: 0.2\n", "intent": "Route queries to mistral, using domain-based routing, with tools auto-selection, for istio deployment", "deployment_context": "istio", "source": "template", "values": {"decision_name": "business_decision", "model_name": "mistral", "signal_type": "domain", "category1": "support", "category2": "finance", "endpoint_address": "192.168.1.100", "endpoint_port": 8080, "endpoint_weight": 1, "cache_enabled": false, "cache_backend": "milvus", "cache_threshold": 0.8, "guard_enabled": false, "guard_threshold": 0.6, "tools_enabled": true, "deployment_context": "istio"}}
{"id": "template_60023", "config": "# Semantic Router Configuration\n# Generated from template\n\ndecisions:\n  - name: \"technical_decision\"\n    modelRefs:\n      - model: \"mistral\"\n        use_reasoning: true\n    signals:\n      - type: \"keyword\"\n        categories:\n          - \"support\"\n          - \"finance\"\n\nmodel_config:\n  mistral:\n    reasoning_family: \"mistral\"\n    preferred_endpoints:\n      - \"endpoint_mistral\"\n\nvllm_endpoints:\n  - name: \"endpoint_mistral\"\n    address: \"192.168.1.100\"\n    port: 8080\n    weight: 1\n\nsemantic_cache:\n  enabled: False\n  backend_type: \"milvus\"\n  similarity_threshold: 0.8\n  max_entries: 1000\n  ttl_seconds: 3600\n\nprompt_guard:\n  enabled: False\n  threshold: 0.6\n  use_modernbert: true\n\ntools:\n  enabled: False\n  top_k: 3\n  similarity_threshold: 0.2\n", "intent": "Route queries to mistral, using keyword-based routing, for istio deployment", "deployment_context": "istio", "source": "template", "values": {"decision_name": "technical_decision", "model_name": "mistral", "signal_type": "keyword", "category1": "support", "category2": "finance", "endpoint_address": "192.168.1.100", "endpoint_port": 8080, "endpoint_weight": 1, "cache_enabled": false, "cache_backend": "milvus", "cache_threshold": 0.8, "guard_enabled": false, "guard_threshold": 0.6, "tools_enabled": false, "deployment_context": "istio"}}
{"id": "template_17909", "config": "# Semantic Router Configuration\n# Generated from template\n\ndecisions:\n  - name: \"business_decision\"\n    modelRefs:\n      - model: \"llama3\"\n        use_reasoning: true\n    signals:\n      - type: \"domain\"\n        categories:\n          - \"general\"\n          - \"finance\"\n\nmodel_config:\n  llama3:\n    reasoning_family: \"llama3\"\n    preferred_endpoints:\n      - \"endpoint_llama3\"\n\nvllm_endpoints:\n  - name: \"endpoint_llama3\"\n    address: \"172.16.0.10\"\n    port: 11434\n    weight: 1\n\nsemantic_cache:\n  enabled: True\n  backend_type: \"memory\"\n  similarity_threshold: 0.8\n  max_entries: 1000\n  ttl_seconds: 3600\n\nprompt_guard:\n  enabled: False\n  threshold: 0.7\n  use_modernbert: true\n\ntools:\n  enabled: True\n  top_k: 3\n  similarity_threshold: 0.2\n", "intent": "Route queries to llama3, using domain-based routing, with memory semantic cache, with tools auto-selection, for quickstart deployment", "deployment_context": "quickstart", "source": "template", "values": {"decision_name": "business_decision", "model_name": "llama3", "signal_type": "domain", "category1": "general", "category2": "finance", "endpoint_address": "172.16.0.10", "endpoint_port": 11434, "endpoint_weight": 1, "cache_enabled": true, "cache_backend": "memory", "cache_threshold": 0.8, "guard_enabled": false, "guard_threshold": 0.7, "tools_enabled": true, "deployment_context": "quickstart"}}
{"id": "template_93911", "config": "# Semantic Router Configuration\n# Generated from template\n\ndecisions:\n  - name: \"technical_decision\"\n    modelRefs:\n      - model: \"llama3\"\n        use_reasoning: true\n    signals:\n      - type: \"embedding\"\n        categories:\n          - \"general\"\n          - \"finance\"\n\nmodel_config:\n  llama3:\n    reasoning_family: \"llama3\"\n    preferred_endpoints:\n      - \"endpoint_llama3\"\n\nvllm_endpoints:\n  - name: \"endpoint_llama3\"\n    address: \"172.28.0.20\"\n    port: 11434\n    weight: 3\n\nsemantic_cache:\n  enabled: False\n  backend_type: \"milvus\"\n  similarity_threshold: 0.7\n  max_entries: 1000\n  ttl_seconds: 3600\n\nprompt_guard:\n  enabled: True\n  threshold: 0.8\n  use_modernbert: true\n\ntools:\n  enabled: True\n  top_k: 3\n  similarity_threshold: 0.2\n", "intent": "Route queries to llama3, using embedding-based routing, with PII detection, with tools auto-selection, for ai-gateway deployment", "deployment_context": "ai-gateway", "source": "template", "values": {"decision_name": "technical_decision", "model_name": "llama3", "signal_type": "embedding", "category1": "general", "category2": "finance", "endpoint_address": "172.28.0.20", "endpoint_port": 11434, "endpoint_weight": 3, "cache_enabled": false, "cache_backend": "milvus", "cache_threshold": 0.7, "guard_enabled": true, "guard_threshold": 0.8, "tools_enabled": true, "deployment_context": "ai-gateway"}}
{"id": "template_98104", "config": "# Semantic Router Configuration\n# Generated from template\n\ndecisions:\n  - name: \"technical_decision\"\n    modelRefs:\n      - model: \"llama3\"\n        use_reasoning: true\n    signals:\n      - type: \"keyword\"\n        categories:\n          - \"general\"\n          - \"engineering\"\n\nmodel_config:\n  llama3:\n    reasoning_family: \"llama3\"\n    preferred_endpoints:\n      - \"endpoint_llama3\"\n\nvllm_endpoints:\n  - name: \"endpoint_llama3\"\n    address: \"172.16.0.10\"\n    port: 11434\n    weight: 3\n\nsemantic_cache:\n  enabled: True\n  backend_type: \"memory\"\n  similarity_threshold: 0.7\n  max_entries: 1000\n  ttl_seconds: 3600\n\nprompt_guard:\n  enabled: False\n  threshold: 0.7\n  use_modernbert: true\n\ntools:\n  enabled: True\n  top_k: 3\n  similarity_threshold: 0.2\n", "intent": "Route queries to llama3, using keyword-based routing, with memory semantic cache, with tools auto-selection, for ai-gateway deployment", "deployment_context": "ai-gateway", "source": "template", "values": {"decision_name": "technical_decision", "model_name": "llama3", "signal_type": "keyword", "category1": "general", "category2": "engineering", "endpoint_address": "172.16.0.10", "endpoint_port": 11434, "endpoint_weight": 3, "cache_enabled": true, "cache_backend": "memory", "cache_threshold": 0.7, "guard_enabled": false, "guard_threshold": 0.7, "tools_enabled": true, "deployment_context": "ai-gateway"}}
{"id": "template_70226", "config": "# Semantic Router Configuration\n# Generated from template\n\ndecisions:\n  - name: \"support_decision\"\n    modelRefs:\n      - model: \"qwen3\"\n        use_reasoning: true\n    signals:\n      - type: \"embedding\"\n        categories:\n          - \"business\"\n          - \"finance\"\n\nmodel_config:\n  qwen3:\n    reasoning_family: \"qwen3\"\n    preferred_endpoints:\n      - \"endpoint_qwen3\"\n\nvllm_endpoints:\n  - name: \"endpoint_qwen3\"\n    address: \"192.168.1.100\"\n    port: 8080\n    weight: 2\n\nsemantic_cache:\n  enabled: True\n  backend_type: \"redis\"\n  similarity_threshold: 0.8\n  max_entries: 1000\n  ttl_seconds: 3600\n\nprompt_guard:\n  enabled: True\n  threshold: 0.8\n  use_modernbert: true\n\ntools:\n  enabled: True\n  top_k: 3\n  similarity_threshold: 0.2\n", "intent": "Route queries to qwen3, using embedding-based routing, with redis semantic cache, with PII detection, with tools auto-selection, for kubernetes deployment", "deployment_context": "kubernetes", "source": "template", "values": {"decision_name": "support_decision", "model_name": "qwen3", "signal_type": "embedding", "category1": "business", "category2": "finance", "endpoint_address": "192.168.1.100", "endpoint_port": 8080, "endpoint_weight": 2, "cache_enabled": true, "cache_backend": "redis", "cache_threshold": 0.8, "guard_enabled": true, "guard_threshold": 0.8, "tools_enabled": true, "deployment_context": "kubernetes"}}
{"id": "template_14583", "config": "# Semantic Router Configuration\n# Generated from template\n\ndecisions:\n  - name: \"support_decision\"\n    modelRefs:\n      - model: \"llama3\"\n        use_reasoning: true\n    signals:\n      - type: \"embedding\"\n        categories:\n          - \"support\"\n          - \"engineering\"\n\nmodel_config:\n  llama3:\n    reasoning_family: \"llama3\"\n    preferred_endpoints:\n      - \"endpoint_llama3\"\n\nvllm_endpoints:\n  - name: \"endpoint_llama3\"\n    address: \"10.0.0.50\"\n    port: 8002\n    weight: 1\n\nsemantic_cache:\n  enabled: True\n  backend_type: \"redis\"\n  similarity_threshold: 0.8\n  max_entries: 1000\n  ttl_seconds: 3600\n\nprompt_guard:\n  enabled: False\n  threshold: 0.6\n  use_modernbert: true\n\ntools:\n  enabled: True\n  top_k: 3\n  similarity_threshold: 0.2\n", "intent": "Route queries to llama3, using embedding-based routing, with redis semantic cache, with tools auto-selection, for kubernetes deployment", "deployment_context": "kubernetes", "source": "template", "values": {"decision_name": "support_decision", "model_name": "llama3", "signal_type": "embedding", "category1": "support", "category2": "engineering", "endpoint_address": "10.0.0.50", "endpoint_port": 8002, "endpoint_weight": 1, "cache_enabled": true, "cache_backend": "redis", "cache_threshold": 0.8, "guard_enabled": false, "guard_threshold": 0.6, "tools_enabled": true, "deployment_context": "kubernetes"}}
{"id": "template_58742", "config": "# Semantic Router Configuration\n# Generated from template\n\ndecisions:\n  - name: \"technical_decision\"\n    modelRefs:\n      - model: \"qwen3\"\n        use_reasoning: true\n    signals:\n      - type: \"keyword\"\n        categories:\n          - \"general\"\n          - \"customer_service\"\n\nmodel_config:\n  qwen3:\n    reasoning_family: \"qwen3\"\n    preferred_endpoints:\n      - \"endpoint_qwen3\"\n\nvllm_endpoints:\n  - name: \"endpoint_qwen3\"\n    address: \"172.28.0.20\"\n    port: 8002\n    weight: 2\n\nsemantic_cache:\n  enabled: False\n  backend_type: \"redis\"\n  similarity_threshold: 0.7\n  max_entries: 1000\n  ttl_seconds: 3600\n\nprompt_guard:\n  enabled: False\n  threshold: 0.6\n  use_modernbert: true\n\ntools:\n  enabled: True\n  top_k: 3\n  similarity_threshold: 0.2\n", "intent": "Route queries to qwen3, using keyword-based routing, with tools auto-selection, for kubernetes deployment", "deployment_context": "kubernetes", "source": "template", "values": {"decision_name": "technical_decision", "model_name": "qwen3", "signal_type": "keyword", "category1": "general", "category2": "customer_service", "endpoint_address": "172.28.0.20", "endpoint_port": 8002, "endpoint_weight": 2, "cache_enabled": false, "cache_backend": "redis", "cache_threshold": 0.7, "guard_enabled": false, "guard_threshold": 0.6, "tools_enabled": true, "deployment_context": "kubernetes"}}
{"id": "template_26297", "config": "# Semantic Router Configuration\n# Generated from template\n\ndecisions:\n  - name: \"support_decision\"\n    modelRefs:\n      - model: \"qwen3\"\n        use_reasoning: true\n    signals:\n      - type: \"domain\"\n        categories:\n          - \"technical\"\n          - \"customer_service\"\n\nmodel_config:\n  qwen3:\n    reasoning_family: \"qwen3\"\n    preferred_endpoints:\n      - \"endpoint_qwen3\"\n\nvllm_endpoints:\n  - name: \"endpoint_qwen3\"\n    address: \"172.28.0.20\"\n    port: 11434\n    weight: 3\n\nsemantic_cache:\n  enabled: True\n  backend_type: \"memory\"\n  similarity_threshold: 0.7\n  max_entries: 1000\n  ttl_seconds: 3600\n\nprompt_guard:\n  enabled: True\n  threshold: 0.8\n  use_modernbert: true\n\ntools:\n  enabled: True\n  top_k: 3\n  similarity_threshold: 0.2\n", "intent": "Route queries to qwen3, using domain-based routing, with memory semantic cache, with PII detection, with tools auto-selection, for ai-gateway deployment", "deployment_context": "ai-gateway", "source": "template", "values": {"decision_name": "support_decision", "model_name": "qwen3", "signal_type": "domain", "category1": "technical", "category2": "customer_service", "endpoint_address": "172.28.0.20", "endpoint_port": 11434, "endpoint_weight": 3, "cache_enabled": true, "cache_backend": "memory", "cache_threshold": 0.7, "guard_enabled": true, "guard_threshold": 0.8, "tools_enabled": true, "deployment_context": "ai-gateway"}}
{"id": "template_73770", "config": "# Semantic Router Configuration\n# Generated from template\n\ndecisions:\n  - name: \"technical_decision\"\n    modelRefs:\n      - model: \"qwen3\"\n        use_reasoning: true\n    signals:\n      - type: \"keyword\"\n        categories:\n          - \"support\"\n          - \"finance\"\n\nmodel_config:\n  qwen3:\n    reasoning_family: \"qwen3\"\n    preferred_endpoints:\n      - \"endpoint_qwen3\"\n\nvllm_endpoints:\n  - name: \"endpoint_qwen3\"\n    address: \"172.28.0.20\"\n    port: 8000\n    weight: 3\n\nsemantic_cache:\n  enabled: True\n  backend_type: \"redis\"\n  similarity_threshold: 0.9\n  max_entries: 1000\n  ttl_seconds: 3600\n\nprompt_guard:\n  enabled: True\n  threshold: 0.6\n  use_modernbert: true\n\ntools:\n  enabled: False\n  top_k: 3\n  similarity_threshold: 0.2\n", "intent": "Route queries to qwen3, using keyword-based routing, with redis semantic cache, with PII detection, for ai-gateway deployment", "deployment_context": "ai-gateway", "source": "template", "values": {"decision_name": "technical_decision", "model_name": "qwen3", "signal_type": "keyword", "category1": "support", "category2": "finance", "endpoint_address": "172.28.0.20", "endpoint_port": 8000, "endpoint_weight": 3, "cache_enabled": true, "cache_backend": "redis", "cache_threshold": 0.9, "guard_enabled": true, "guard_threshold": 0.6, "tools_enabled": false, "deployment_context": "ai-gateway"}}
{"id": "template_78580", "config": "# Semantic Router Configuration\n# Generated from template\n\ndecisions:\n  - name: \"general_decision\"\n    modelRefs:\n      - model: \"llama3\"\n        use_reasoning: true\n    signals:\n      - type: \"domain\"\n        categories:\n          - \"general\"\n          - \"customer_service\"\n\nmodel_config:\n  llama3:\n    reasoning_family: \"llama3\"\n    preferred_endpoints:\n      - \"endpoint_llama3\"\n\nvllm_endpoints:\n  - name: \"endpoint_llama3\"\n    address: \"10.0.0.50\"\n    port: 8002\n    weight: 1\n\nsemantic_cache:\n  enabled: False\n  backend_type: \"memory\"\n  similarity_threshold: 0.9\n  max_entries: 1000\n  ttl_seconds: 3600\n\nprompt_guard:\n  enabled: False\n  threshold: 0.6\n  use_modernbert: true\n\ntools:\n  enabled: True\n  top_k: 3\n  similarity_threshold: 0.2\n", "intent": "Route queries to llama3, using domain-based routing, with tools auto-selection, for ai-gateway deployment", "deployment_context": "ai-gateway", "source": "template", "values": {"decision_name": "general_decision", "model_name": "llama3", "signal_type": "domain", "category1": "general", "category2": "customer_service", "endpoint_address": "10.0.0.50", "endpoint_port": 8002, "endpoint_weight": 1, "cache_enabled": false, "cache_backend": "memory", "cache_threshold": 0.9, "guard_enabled": false, "guard_threshold": 0.6, "tools_enabled": true, "deployment_context": "ai-gateway"}}
{"id": "template_84935", "config": "# Semantic Router Configuration\n# Generated from template\n\ndecisions:\n  - name: \"technical_decision\"\n    modelRefs:\n      - model: \"phi4\"\n        use_reasoning: true\n    signals:\n      - type: \"embedding\"\n        categories:\n          - \"business\"\n          - \"customer_service\"\n\nmodel_config:\n  phi4:\n    reasoning_family: \"phi4\"\n    preferred_endpoints:\n      - \"endpoint_phi4\"\n\nvllm_endpoints:\n  - name: \"endpoint_phi4\"\n    address: \"192.168.1.100\"\n    port: 8002\n    weight: 3\n\nsemantic_cache:\n  enabled: True\n  backend_type: \"memory\"\n  similarity_threshold: 0.7\n  max_entries: 1000\n  ttl_seconds: 3600\n\nprompt_guard:\n  enabled: True\n  threshold: 0.8\n  use_modernbert: true\n\ntools:\n  enabled: True\n  top_k: 3\n  similarity_threshold: 0.2\n", "intent": "Route queries to phi4, using embedding-based routing, with memory semantic cache, with PII detection, with tools auto-selection, for istio deployment", "deployment_context": "istio", "source": "template", "values": {"decision_name": "technical_decision", "model_name": "phi4", "signal_type": "embedding", "category1": "business", "category2": "customer_service", "endpoint_address": "192.168.1.100", "endpoint_port": 8002, "endpoint_weight": 3, "cache_enabled": true, "cache_backend": "memory", "cache_threshold": 0.7, "guard_enabled": true, "guard_threshold": 0.8, "tools_enabled": true, "deployment_context": "istio"}}
{"id": "template_64974", "config": "# Semantic Router Configuration\n# Generated from template\n\ndecisions:\n  - name: \"technical_decision\"\n    modelRefs:\n      - model: \"mistral\"\n        use_reasoning: true\n    signals:\n      - type: \"keyword\"\n        categories:\n          - \"technical\"\n          - \"customer_service\"\n\nmodel_config:\n  mistral:\n    reasoning_family: \"mistral\"\n    preferred_endpoints:\n      - \"endpoint_mistral\"\n\nvllm_endpoints:\n  - name: \"endpoint_mistral\"\n    address: \"10.0.0.50\"\n    port: 8080\n    weight: 1\n\nsemantic_cache:\n  enabled: False\n  backend_type: \"redis\"\n  similarity_threshold: 0.8\n  max_entries: 1000\n  ttl_seconds: 3600\n\nprompt_guard:\n  enabled: True\n  threshold: 0.7\n  use_modernbert: true\n\ntools:\n  enabled: False\n  top_k: 3\n  similarity_threshold: 0.2\n", "intent": "Route queries to mistral, using keyword-based routing, with PII detection, for quickstart deployment", "deployment_context": "quickstart", "source": "template", "values": {"decision_name": "technical_decision", "model_name": "mistral", "signal_type": "keyword", "category1": "technical", "category2": "customer_service", "endpoint_address": "10.0.0.50", "endpoint_port": 8080, "endpoint_weight": 1, "cache_enabled": false, "cache_backend": "redis", "cache_threshold": 0.8, "guard_enabled": true, "guard_threshold": 0.7, "tools_enabled": false, "deployment_context": "quickstart"}}
{"id": "template_57837", "config": "# Semantic Router Configuration\n# Generated from template\n\ndecisions:\n  - name: \"business_decision\"\n    modelRefs:\n      - model: \"mistral\"\n        use_reasoning: true\n    signals:\n      - type: \"domain\"\n        categories:\n          - \"business\"\n          - \"sales\"\n\nmodel_config:\n  mistral:\n    reasoning_family: \"mistral\"\n    preferred_endpoints:\n      - \"endpoint_mistral\"\n\nvllm_endpoints:\n  - name: \"endpoint_mistral\"\n    address: \"172.28.0.20\"\n    port: 11434\n    weight: 1\n\nsemantic_cache:\n  enabled: True\n  backend_type: \"memory\"\n  similarity_threshold: 0.8\n  max_entries: 1000\n  ttl_seconds: 3600\n\nprompt_guard:\n  enabled: False\n  threshold: 0.8\n  use_modernbert: true\n\ntools:\n  enabled: False\n  top_k: 3\n  similarity_threshold: 0.2\n", "intent": "Route queries to mistral, using domain-based routing, with memory semantic cache, for istio deployment", "deployment_context": "istio", "source": "template", "values": {"decision_name": "business_decision", "model_name": "mistral", "signal_type": "domain", "category1": "business", "category2": "sales", "endpoint_address": "172.28.0.20", "endpoint_port": 11434, "endpoint_weight": 1, "cache_enabled": true, "cache_backend": "memory", "cache_threshold": 0.8, "guard_enabled": false, "guard_threshold": 0.8, "tools_enabled": false, "deployment_context": "istio"}}
{"id": "template_12147", "config": "# Semantic Router Configuration\n# Generated from template\n\ndecisions:\n  - name: \"general_decision\"\n    modelRefs:\n      - model: \"qwen3\"\n        use_reasoning: true\n    signals:\n      - type: \"embedding\"\n        categories:\n          - \"technical\"\n          - \"sales\"\n\nmodel_config:\n  qwen3:\n    reasoning_family: \"qwen3\"\n    preferred_endpoints:\n      - \"endpoint_qwen3\"\n\nvllm_endpoints:\n  - name: \"endpoint_qwen3\"\n    address: \"172.16.0.10\"\n    port: 8080\n    weight: 1\n\nsemantic_cache:\n  enabled: True\n  backend_type: \"milvus\"\n  similarity_threshold: 0.7\n  max_entries: 1000\n  ttl_seconds: 3600\n\nprompt_guard:\n  enabled: False\n  threshold: 0.8\n  use_modernbert: true\n\ntools:\n  enabled: True\n  top_k: 3\n  similarity_threshold: 0.2\n", "intent": "Route queries to qwen3, using embedding-based routing, with milvus semantic cache, with tools auto-selection, for ai-gateway deployment", "deployment_context": "ai-gateway", "source": "template", "values": {"decision_name": "general_decision", "model_name": "qwen3", "signal_type": "embedding", "category1": "technical", "category2": "sales", "endpoint_address": "172.16.0.10", "endpoint_port": 8080, "endpoint_weight": 1, "cache_enabled": true, "cache_backend": "milvus", "cache_threshold": 0.7, "guard_enabled": false, "guard_threshold": 0.8, "tools_enabled": true, "deployment_context": "ai-gateway"}}
{"id": "template_69820", "config": "# Semantic Router Configuration\n# Generated from template\n\ndecisions:\n  - name: \"business_decision\"\n    modelRefs:\n      - model: \"mistral\"\n        use_reasoning: true\n    signals:\n      - type: \"domain\"\n        categories:\n          - \"support\"\n          - \"finance\"\n\nmodel_config:\n  mistral:\n    reasoning_family: \"mistral\"\n    preferred_endpoints:\n      - \"endpoint_mistral\"\n\nvllm_endpoints:\n  - name: \"endpoint_mistral\"\n    address: \"172.16.0.10\"\n    port: 8002\n    weight: 2\n\nsemantic_cache:\n  enabled: False\n  backend_type: \"redis\"\n  similarity_threshold: 0.9\n  max_entries: 1000\n  ttl_seconds: 3600\n\nprompt_guard:\n  enabled: False\n  threshold: 0.6\n  use_modernbert: true\n\ntools:\n  enabled: True\n  top_k: 3\n  similarity_threshold: 0.2\n", "intent": "Route queries to mistral, using domain-based routing, with tools auto-selection, for istio deployment", "deployment_context": "istio", "source": "template", "values": {"decision_name": "business_decision", "model_name": "mistral", "signal_type": "domain", "category1": "support", "category2": "finance", "endpoint_address": "172.16.0.10", "endpoint_port": 8002, "endpoint_weight": 2, "cache_enabled": false, "cache_backend": "redis", "cache_threshold": 0.9, "guard_enabled": false, "guard_threshold": 0.6, "tools_enabled": true, "deployment_context": "istio"}}
{"id": "template_11671", "config": "# Semantic Router Configuration\n# Generated from template\n\ndecisions:\n  - name: \"business_decision\"\n    modelRefs:\n      - model: \"llama3\"\n        use_reasoning: true\n    signals:\n      - type: \"embedding\"\n        categories:\n          - \"general\"\n          - \"sales\"\n\nmodel_config:\n  llama3:\n    reasoning_family: \"llama3\"\n    preferred_endpoints:\n      - \"endpoint_llama3\"\n\nvllm_endpoints:\n  - name: \"endpoint_llama3\"\n    address: \"172.16.0.10\"\n    port: 11434\n    weight: 2\n\nsemantic_cache:\n  enabled: False\n  backend_type: \"redis\"\n  similarity_threshold: 0.7\n  max_entries: 1000\n  ttl_seconds: 3600\n\nprompt_guard:\n  enabled: True\n  threshold: 0.6\n  use_modernbert: true\n\ntools:\n  enabled: False\n  top_k: 3\n  similarity_threshold: 0.2\n", "intent": "Route queries to llama3, using embedding-based routing, with PII detection, for kubernetes deployment", "deployment_context": "kubernetes", "source": "template", "values": {"decision_name": "business_decision", "model_name": "llama3", "signal_type": "embedding", "category1": "general", "category2": "sales", "endpoint_address": "172.16.0.10", "endpoint_port": 11434, "endpoint_weight": 2, "cache_enabled": false, "cache_backend": "redis", "cache_threshold": 0.7, "guard_enabled": true, "guard_threshold": 0.6, "tools_enabled": false, "deployment_context": "kubernetes"}}
{"id": "template_77397", "config": "# Semantic Router Configuration\n# Generated from template\n\ndecisions:\n  - name: \"business_decision\"\n    modelRefs:\n      - model: \"llama3\"\n        use_reasoning: true\n    signals:\n      - type: \"keyword\"\n        categories:\n          - \"support\"\n          - \"finance\"\n\nmodel_config:\n  llama3:\n    reasoning_family: \"llama3\"\n    preferred_endpoints:\n      - \"endpoint_llama3\"\n\nvllm_endpoints:\n  - name: \"endpoint_llama3\"\n    address: \"172.16.0.10\"\n    port: 8080\n    weight: 3\n\nsemantic_cache:\n  enabled: False\n  backend_type: \"redis\"\n  similarity_threshold: 0.8\n  max_entries: 1000\n  ttl_seconds: 3600\n\nprompt_guard:\n  enabled: True\n  threshold: 0.7\n  use_modernbert: true\n\ntools:\n  enabled: True\n  top_k: 3\n  similarity_threshold: 0.2\n", "intent": "Route queries to llama3, using keyword-based routing, with PII detection, with tools auto-selection, for kubernetes deployment", "deployment_context": "kubernetes", "source": "template", "values": {"decision_name": "business_decision", "model_name": "llama3", "signal_type": "keyword", "category1": "support", "category2": "finance", "endpoint_address": "172.16.0.10", "endpoint_port": 8080, "endpoint_weight": 3, "cache_enabled": false, "cache_backend": "redis", "cache_threshold": 0.8, "guard_enabled": true, "guard_threshold": 0.7, "tools_enabled": true, "deployment_context": "kubernetes"}}
{"id": "template_4872", "config": "# Semantic Router Configuration\n# Generated from template\n\ndecisions:\n  - name: \"business_decision\"\n    modelRefs:\n      - model: \"mistral\"\n        use_reasoning: true\n    signals:\n      - type: \"keyword\"\n        categories:\n          - \"support\"\n          - \"sales\"\n\nmodel_config:\n  mistral:\n    reasoning_family: \"mistral\"\n    preferred_endpoints:\n      - \"endpoint_mistral\"\n\nvllm_endpoints:\n  - name: \"endpoint_mistral\"\n    address: \"172.28.0.20\"\n    port: 8080\n    weight: 1\n\nsemantic_cache:\n  enabled: True\n  backend_type: \"redis\"\n  similarity_threshold: 0.7\n  max_entries: 1000\n  ttl_seconds: 3600\n\nprompt_guard:\n  enabled: True\n  threshold: 0.8\n  use_modernbert: true\n\ntools:\n  enabled: True\n  top_k: 3\n  similarity_threshold: 0.2\n", "intent": "Route queries to mistral, using keyword-based routing, with redis semantic cache, with PII detection, with tools auto-selection, for quickstart deployment", "deployment_context": "quickstart", "source": "template", "values": {"decision_name": "business_decision", "model_name": "mistral", "signal_type": "keyword", "category1": "support", "category2": "sales", "endpoint_address": "172.28.0.20", "endpoint_port": 8080, "endpoint_weight": 1, "cache_enabled": true, "cache_backend": "redis", "cache_threshold": 0.7, "guard_enabled": true, "guard_threshold": 0.8, "tools_enabled": true, "deployment_context": "quickstart"}}
{"id": "template_67461", "config": "# Semantic Router Configuration\n# Generated from template\n\ndecisions:\n  - name: \"support_decision\"\n    modelRefs:\n      - model: \"llama3\"\n        use_reasoning: true\n    signals:\n      - type: \"domain\"\n        categories:\n          - \"technical\"\n          - \"engineering\"\n\nmodel_config:\n  llama3:\n    reasoning_family: \"llama3\"\n    preferred_endpoints:\n      - \"endpoint_llama3\"\n\nvllm_endpoints:\n  - name: \"endpoint_llama3\"\n    address: \"172.16.0.10\"\n    port: 8002\n    weight: 1\n\nsemantic_cache:\n  enabled: True\n  backend_type: \"redis\"\n  similarity_threshold: 0.9\n  max_entries: 1000\n  ttl_seconds: 3600\n\nprompt_guard:\n  enabled: False\n  threshold: 0.7\n  use_modernbert: true\n\ntools:\n  enabled: True\n  top_k: 3\n  similarity_threshold: 0.2\n", "intent": "Route queries to llama3, using domain-based routing, with redis semantic cache, with tools auto-selection, for quickstart deployment", "deployment_context": "quickstart", "source": "template", "values": {"decision_name": "support_decision", "model_name": "llama3", "signal_type": "domain", "category1": "technical", "category2": "engineering", "endpoint_address": "172.16.0.10", "endpoint_port": 8002, "endpoint_weight": 1, "cache_enabled": true, "cache_backend": "redis", "cache_threshold": 0.9, "guard_enabled": false, "guard_threshold": 0.7, "tools_enabled": true, "deployment_context": "quickstart"}}
{"id": "template_8496", "config": "# Semantic Router Configuration\n# Generated from template\n\ndecisions:\n  - name: \"technical_decision\"\n    modelRefs:\n      - model: \"phi4\"\n        use_reasoning: true\n    signals:\n      - type: \"embedding\"\n        categories:\n          - \"business\"\n          - \"customer_service\"\n\nmodel_config:\n  phi4:\n    reasoning_family: \"phi4\"\n    preferred_endpoints:\n      - \"endpoint_phi4\"\n\nvllm_endpoints:\n  - name: \"endpoint_phi4\"\n    address: \"192.168.1.100\"\n    port: 8080\n    weight: 1\n\nsemantic_cache:\n  enabled: False\n  backend_type: \"milvus\"\n  similarity_threshold: 0.9\n  max_entries: 1000\n  ttl_seconds: 3600\n\nprompt_guard:\n  enabled: True\n  threshold: 0.6\n  use_modernbert: true\n\ntools:\n  enabled: False\n  top_k: 3\n  similarity_threshold: 0.2\n", "intent": "Route queries to phi4, using embedding-based routing, with PII detection, for quickstart deployment", "deployment_context": "quickstart", "source": "template", "values": {"decision_name": "technical_decision", "model_name": "phi4", "signal_type": "embedding", "category1": "business", "category2": "customer_service", "endpoint_address": "192.168.1.100", "endpoint_port": 8080, "endpoint_weight": 1, "cache_enabled": false, "cache_backend": "milvus", "cache_threshold": 0.9, "guard_enabled": true, "guard_threshold": 0.6, "tools_enabled": false, "deployment_context": "quickstart"}}
{"id": "template_89659", "config": "# Semantic Router Configuration\n# Generated from template\n\ndecisions:\n  - name: \"support_decision\"\n    modelRefs:\n      - model: \"qwen3\"\n        use_reasoning: true\n    signals:\n      - type: \"keyword\"\n        categories:\n          - \"technical\"\n          - \"finance\"\n\nmodel_config:\n  qwen3:\n    reasoning_family: \"qwen3\"\n    preferred_endpoints:\n      - \"endpoint_qwen3\"\n\nvllm_endpoints:\n  - name: \"endpoint_qwen3\"\n    address: \"172.28.0.20\"\n    port: 8002\n    weight: 2\n\nsemantic_cache:\n  enabled: False\n  backend_type: \"milvus\"\n  similarity_threshold: 0.7\n  max_entries: 1000\n  ttl_seconds: 3600\n\nprompt_guard:\n  enabled: True\n  threshold: 0.8\n  use_modernbert: true\n\ntools:\n  enabled: True\n  top_k: 3\n  similarity_threshold: 0.2\n", "intent": "Route queries to qwen3, using keyword-based routing, with PII detection, with tools auto-selection, for ai-gateway deployment", "deployment_context": "ai-gateway", "source": "template", "values": {"decision_name": "support_decision", "model_name": "qwen3", "signal_type": "keyword", "category1": "technical", "category2": "finance", "endpoint_address": "172.28.0.20", "endpoint_port": 8002, "endpoint_weight": 2, "cache_enabled": false, "cache_backend": "milvus", "cache_threshold": 0.7, "guard_enabled": true, "guard_threshold": 0.8, "tools_enabled": true, "deployment_context": "ai-gateway"}}
{"id": "template_37464", "config": "# Semantic Router Configuration\n# Generated from template\n\ndecisions:\n  - name: \"general_decision\"\n    modelRefs:\n      - model: \"qwen3\"\n        use_reasoning: true\n    signals:\n      - type: \"domain\"\n        categories:\n          - \"business\"\n          - \"engineering\"\n\nmodel_config:\n  qwen3:\n    reasoning_family: \"qwen3\"\n    preferred_endpoints:\n      - \"endpoint_qwen3\"\n\nvllm_endpoints:\n  - name: \"endpoint_qwen3\"\n    address: \"192.168.1.100\"\n    port: 8000\n    weight: 3\n\nsemantic_cache:\n  enabled: False\n  backend_type: \"milvus\"\n  similarity_threshold: 0.8\n  max_entries: 1000\n  ttl_seconds: 3600\n\nprompt_guard:\n  enabled: True\n  threshold: 0.8\n  use_modernbert: true\n\ntools:\n  enabled: False\n  top_k: 3\n  similarity_threshold: 0.2\n", "intent": "Route queries to qwen3, using domain-based routing, with PII detection, for kubernetes deployment", "deployment_context": "kubernetes", "source": "template", "values": {"decision_name": "general_decision", "model_name": "qwen3", "signal_type": "domain", "category1": "business", "category2": "engineering", "endpoint_address": "192.168.1.100", "endpoint_port": 8000, "endpoint_weight": 3, "cache_enabled": false, "cache_backend": "milvus", "cache_threshold": 0.8, "guard_enabled": true, "guard_threshold": 0.8, "tools_enabled": false, "deployment_context": "kubernetes"}}
{"id": "template_67746", "config": "# Semantic Router Configuration\n# Generated from template\n\ndecisions:\n  - name: \"technical_decision\"\n    modelRefs:\n      - model: \"qwen3\"\n        use_reasoning: true\n    signals:\n      - type: \"domain\"\n        categories:\n          - \"business\"\n          - \"sales\"\n\nmodel_config:\n  qwen3:\n    reasoning_family: \"qwen3\"\n    preferred_endpoints:\n      - \"endpoint_qwen3\"\n\nvllm_endpoints:\n  - name: \"endpoint_qwen3\"\n    address: \"10.0.0.50\"\n    port: 8000\n    weight: 1\n\nsemantic_cache:\n  enabled: False\n  backend_type: \"memory\"\n  similarity_threshold: 0.7\n  max_entries: 1000\n  ttl_seconds: 3600\n\nprompt_guard:\n  enabled: False\n  threshold: 0.6\n  use_modernbert: true\n\ntools:\n  enabled: True\n  top_k: 3\n  similarity_threshold: 0.2\n", "intent": "Route queries to qwen3, using domain-based routing, with tools auto-selection, for kubernetes deployment", "deployment_context": "kubernetes", "source": "template", "values": {"decision_name": "technical_decision", "model_name": "qwen3", "signal_type": "domain", "category1": "business", "category2": "sales", "endpoint_address": "10.0.0.50", "endpoint_port": 8000, "endpoint_weight": 1, "cache_enabled": false, "cache_backend": "memory", "cache_threshold": 0.7, "guard_enabled": false, "guard_threshold": 0.6, "tools_enabled": true, "deployment_context": "kubernetes"}}
{"id": "template_83295", "config": "# Semantic Router Configuration\n# Generated from template\n\ndecisions:\n  - name: \"technical_decision\"\n    modelRefs:\n      - model: \"phi4\"\n        use_reasoning: true\n    signals:\n      - type: \"keyword\"\n        categories:\n          - \"business\"\n          - \"customer_service\"\n\nmodel_config:\n  phi4:\n    reasoning_family: \"phi4\"\n    preferred_endpoints:\n      - \"endpoint_phi4\"\n\nvllm_endpoints:\n  - name: \"endpoint_phi4\"\n    address: \"172.28.0.20\"\n    port: 8000\n    weight: 1\n\nsemantic_cache:\n  enabled: False\n  backend_type: \"milvus\"\n  similarity_threshold: 0.7\n  max_entries: 1000\n  ttl_seconds: 3600\n\nprompt_guard:\n  enabled: False\n  threshold: 0.6\n  use_modernbert: true\n\ntools:\n  enabled: True\n  top_k: 3\n  similarity_threshold: 0.2\n", "intent": "Route queries to phi4, using keyword-based routing, with tools auto-selection, for quickstart deployment", "deployment_context": "quickstart", "source": "template", "values": {"decision_name": "technical_decision", "model_name": "phi4", "signal_type": "keyword", "category1": "business", "category2": "customer_service", "endpoint_address": "172.28.0.20", "endpoint_port": 8000, "endpoint_weight": 1, "cache_enabled": false, "cache_backend": "milvus", "cache_threshold": 0.7, "guard_enabled": false, "guard_threshold": 0.6, "tools_enabled": true, "deployment_context": "quickstart"}}
{"id": "template_23040", "config": "# Semantic Router Configuration\n# Generated from template\n\ndecisions:\n  - name: \"technical_decision\"\n    modelRefs:\n      - model: \"llama3\"\n        use_reasoning: true\n    signals:\n      - type: \"domain\"\n        categories:\n          - \"support\"\n          - \"finance\"\n\nmodel_config:\n  llama3:\n    reasoning_family: \"llama3\"\n    preferred_endpoints:\n      - \"endpoint_llama3\"\n\nvllm_endpoints:\n  - name: \"endpoint_llama3\"\n    address: \"192.168.1.100\"\n    port: 8080\n    weight: 2\n\nsemantic_cache:\n  enabled: False\n  backend_type: \"redis\"\n  similarity_threshold: 0.7\n  max_entries: 1000\n  ttl_seconds: 3600\n\nprompt_guard:\n  enabled: False\n  threshold: 0.8\n  use_modernbert: true\n\ntools:\n  enabled: True\n  top_k: 3\n  similarity_threshold: 0.2\n", "intent": "Route queries to llama3, using domain-based routing, with tools auto-selection, for kubernetes deployment", "deployment_context": "kubernetes", "source": "template", "values": {"decision_name": "technical_decision", "model_name": "llama3", "signal_type": "domain", "category1": "support", "category2": "finance", "endpoint_address": "192.168.1.100", "endpoint_port": 8080, "endpoint_weight": 2, "cache_enabled": false, "cache_backend": "redis", "cache_threshold": 0.7, "guard_enabled": false, "guard_threshold": 0.8, "tools_enabled": true, "deployment_context": "kubernetes"}}
{"id": "template_233", "config": "# Semantic Router Configuration\n# Generated from template\n\ndecisions:\n  - name: \"technical_decision\"\n    modelRefs:\n      - model: \"qwen3\"\n        use_reasoning: true\n    signals:\n      - type: \"keyword\"\n        categories:\n          - \"technical\"\n          - \"finance\"\n\nmodel_config:\n  qwen3:\n    reasoning_family: \"qwen3\"\n    preferred_endpoints:\n      - \"endpoint_qwen3\"\n\nvllm_endpoints:\n  - name: \"endpoint_qwen3\"\n    address: \"192.168.1.100\"\n    port: 8000\n    weight: 3\n\nsemantic_cache:\n  enabled: False\n  backend_type: \"redis\"\n  similarity_threshold: 0.8\n  max_entries: 1000\n  ttl_seconds: 3600\n\nprompt_guard:\n  enabled: False\n  threshold: 0.6\n  use_modernbert: true\n\ntools:\n  enabled: True\n  top_k: 3\n  similarity_threshold: 0.2\n", "intent": "Route queries to qwen3, using keyword-based routing, with tools auto-selection, for kubernetes deployment", "deployment_context": "kubernetes", "source": "template", "values": {"decision_name": "technical_decision", "model_name": "qwen3", "signal_type": "keyword", "category1": "technical", "category2": "finance", "endpoint_address": "192.168.1.100", "endpoint_port": 8000, "endpoint_weight": 3, "cache_enabled": false, "cache_backend": "redis", "cache_threshold": 0.8, "guard_enabled": false, "guard_threshold": 0.6, "tools_enabled": true, "deployment_context": "kubernetes"}}
{"id": "template_91183", "config": "# Semantic Router Configuration\n# Generated from template\n\ndecisions:\n  - name: \"business_decision\"\n    modelRefs:\n      - model: \"llama3\"\n        use_reasoning: true\n    signals:\n      - type: \"keyword\"\n        categories:\n          - \"general\"\n          - \"engineering\"\n\nmodel_config:\n  llama3:\n    reasoning_family: \"llama3\"\n    preferred_endpoints:\n      - \"endpoint_llama3\"\n\nvllm_endpoints:\n  - name: \"endpoint_llama3\"\n    address: \"172.28.0.20\"\n    port: 8080\n    weight: 2\n\nsemantic_cache:\n  enabled: True\n  backend_type: \"milvus\"\n  similarity_threshold: 0.7\n  max_entries: 1000\n  ttl_seconds: 3600\n\nprompt_guard:\n  enabled: False\n  threshold: 0.8\n  use_modernbert: true\n\ntools:\n  enabled: True\n  top_k: 3\n  similarity_threshold: 0.2\n", "intent": "Route queries to llama3, using keyword-based routing, with milvus semantic cache, with tools auto-selection, for istio deployment", "deployment_context": "istio", "source": "template", "values": {"decision_name": "business_decision", "model_name": "llama3", "signal_type": "keyword", "category1": "general", "category2": "engineering", "endpoint_address": "172.28.0.20", "endpoint_port": 8080, "endpoint_weight": 2, "cache_enabled": true, "cache_backend": "milvus", "cache_threshold": 0.7, "guard_enabled": false, "guard_threshold": 0.8, "tools_enabled": true, "deployment_context": "istio"}}
{"id": "template_52863", "config": "# Semantic Router Configuration\n# Generated from template\n\ndecisions:\n  - name: \"business_decision\"\n    modelRefs:\n      - model: \"phi4\"\n        use_reasoning: true\n    signals:\n      - type: \"domain\"\n        categories:\n          - \"technical\"\n          - \"customer_service\"\n\nmodel_config:\n  phi4:\n    reasoning_family: \"phi4\"\n    preferred_endpoints:\n      - \"endpoint_phi4\"\n\nvllm_endpoints:\n  - name: \"endpoint_phi4\"\n    address: \"172.28.0.20\"\n    port: 11434\n    weight: 1\n\nsemantic_cache:\n  enabled: True\n  backend_type: \"memory\"\n  similarity_threshold: 0.7\n  max_entries: 1000\n  ttl_seconds: 3600\n\nprompt_guard:\n  enabled: False\n  threshold: 0.8\n  use_modernbert: true\n\ntools:\n  enabled: True\n  top_k: 3\n  similarity_threshold: 0.2\n", "intent": "Route queries to phi4, using domain-based routing, with memory semantic cache, with tools auto-selection, for ai-gateway deployment", "deployment_context": "ai-gateway", "source": "template", "values": {"decision_name": "business_decision", "model_name": "phi4", "signal_type": "domain", "category1": "technical", "category2": "customer_service", "endpoint_address": "172.28.0.20", "endpoint_port": 11434, "endpoint_weight": 1, "cache_enabled": true, "cache_backend": "memory", "cache_threshold": 0.7, "guard_enabled": false, "guard_threshold": 0.8, "tools_enabled": true, "deployment_context": "ai-gateway"}}
{"id": "template_48134", "config": "# Semantic Router Configuration\n# Generated from template\n\ndecisions:\n  - name: \"general_decision\"\n    modelRefs:\n      - model: \"phi4\"\n        use_reasoning: true\n    signals:\n      - type: \"keyword\"\n        categories:\n          - \"business\"\n          - \"sales\"\n\nmodel_config:\n  phi4:\n    reasoning_family: \"phi4\"\n    preferred_endpoints:\n      - \"endpoint_phi4\"\n\nvllm_endpoints:\n  - name: \"endpoint_phi4\"\n    address: \"172.16.0.10\"\n    port: 8080\n    weight: 3\n\nsemantic_cache:\n  enabled: False\n  backend_type: \"milvus\"\n  similarity_threshold: 0.7\n  max_entries: 1000\n  ttl_seconds: 3600\n\nprompt_guard:\n  enabled: True\n  threshold: 0.6\n  use_modernbert: true\n\ntools:\n  enabled: True\n  top_k: 3\n  similarity_threshold: 0.2\n", "intent": "Route queries to phi4, using keyword-based routing, with PII detection, with tools auto-selection, for ai-gateway deployment", "deployment_context": "ai-gateway", "source": "template", "values": {"decision_name": "general_decision", "model_name": "phi4", "signal_type": "keyword", "category1": "business", "category2": "sales", "endpoint_address": "172.16.0.10", "endpoint_port": 8080, "endpoint_weight": 3, "cache_enabled": false, "cache_backend": "milvus", "cache_threshold": 0.7, "guard_enabled": true, "guard_threshold": 0.6, "tools_enabled": true, "deployment_context": "ai-gateway"}}
{"id": "template_34060", "config": "# Semantic Router Configuration\n# Generated from template\n\ndecisions:\n  - name: \"business_decision\"\n    modelRefs:\n      - model: \"mistral\"\n        use_reasoning: true\n    signals:\n      - type: \"domain\"\n        categories:\n          - \"support\"\n          - \"customer_service\"\n\nmodel_config:\n  mistral:\n    reasoning_family: \"mistral\"\n    preferred_endpoints:\n      - \"endpoint_mistral\"\n\nvllm_endpoints:\n  - name: \"endpoint_mistral\"\n    address: \"172.28.0.20\"\n    port: 8000\n    weight: 3\n\nsemantic_cache:\n  enabled: True\n  backend_type: \"milvus\"\n  similarity_threshold: 0.8\n  max_entries: 1000\n  ttl_seconds: 3600\n\nprompt_guard:\n  enabled: False\n  threshold: 0.7\n  use_modernbert: true\n\ntools:\n  enabled: False\n  top_k: 3\n  similarity_threshold: 0.2\n", "intent": "Route queries to mistral, using domain-based routing, with milvus semantic cache, for ai-gateway deployment", "deployment_context": "ai-gateway", "source": "template", "values": {"decision_name": "business_decision", "model_name": "mistral", "signal_type": "domain", "category1": "support", "category2": "customer_service", "endpoint_address": "172.28.0.20", "endpoint_port": 8000, "endpoint_weight": 3, "cache_enabled": true, "cache_backend": "milvus", "cache_threshold": 0.8, "guard_enabled": false, "guard_threshold": 0.7, "tools_enabled": false, "deployment_context": "ai-gateway"}}
{"id": "template_40720", "config": "# Semantic Router Configuration\n# Generated from template\n\ndecisions:\n  - name: \"technical_decision\"\n    modelRefs:\n      - model: \"qwen3\"\n        use_reasoning: true\n    signals:\n      - type: \"domain\"\n        categories:\n          - \"general\"\n          - \"engineering\"\n\nmodel_config:\n  qwen3:\n    reasoning_family: \"qwen3\"\n    preferred_endpoints:\n      - \"endpoint_qwen3\"\n\nvllm_endpoints:\n  - name: \"endpoint_qwen3\"\n    address: \"172.28.0.20\"\n    port: 8002\n    weight: 3\n\nsemantic_cache:\n  enabled: False\n  backend_type: \"milvus\"\n  similarity_threshold: 0.7\n  max_entries: 1000\n  ttl_seconds: 3600\n\nprompt_guard:\n  enabled: True\n  threshold: 0.6\n  use_modernbert: true\n\ntools:\n  enabled: True\n  top_k: 3\n  similarity_threshold: 0.2\n", "intent": "Route queries to qwen3, using domain-based routing, with PII detection, with tools auto-selection, for quickstart deployment", "deployment_context": "quickstart", "source": "template", "values": {"decision_name": "technical_decision", "model_name": "qwen3", "signal_type": "domain", "category1": "general", "category2": "engineering", "endpoint_address": "172.28.0.20", "endpoint_port": 8002, "endpoint_weight": 3, "cache_enabled": false, "cache_backend": "milvus", "cache_threshold": 0.7, "guard_enabled": true, "guard_threshold": 0.6, "tools_enabled": true, "deployment_context": "quickstart"}}
{"id": "template_74763", "config": "# Semantic Router Configuration\n# Generated from template\n\ndecisions:\n  - name: \"business_decision\"\n    modelRefs:\n      - model: \"phi4\"\n        use_reasoning: true\n    signals:\n      - type: \"domain\"\n        categories:\n          - \"business\"\n          - \"sales\"\n\nmodel_config:\n  phi4:\n    reasoning_family: \"phi4\"\n    preferred_endpoints:\n      - \"endpoint_phi4\"\n\nvllm_endpoints:\n  - name: \"endpoint_phi4\"\n    address: \"192.168.1.100\"\n    port: 8002\n    weight: 2\n\nsemantic_cache:\n  enabled: True\n  backend_type: \"milvus\"\n  similarity_threshold: 0.7\n  max_entries: 1000\n  ttl_seconds: 3600\n\nprompt_guard:\n  enabled: False\n  threshold: 0.7\n  use_modernbert: true\n\ntools:\n  enabled: False\n  top_k: 3\n  similarity_threshold: 0.2\n", "intent": "Route queries to phi4, using domain-based routing, with milvus semantic cache, for kubernetes deployment", "deployment_context": "kubernetes", "source": "template", "values": {"decision_name": "business_decision", "model_name": "phi4", "signal_type": "domain", "category1": "business", "category2": "sales", "endpoint_address": "192.168.1.100", "endpoint_port": 8002, "endpoint_weight": 2, "cache_enabled": true, "cache_backend": "milvus", "cache_threshold": 0.7, "guard_enabled": false, "guard_threshold": 0.7, "tools_enabled": false, "deployment_context": "kubernetes"}}
{"id": "template_53138", "config": "# Semantic Router Configuration\n# Generated from template\n\ndecisions:\n  - name: \"business_decision\"\n    modelRefs:\n      - model: \"mistral\"\n        use_reasoning: true\n    signals:\n      - type: \"domain\"\n        categories:\n          - \"technical\"\n          - \"engineering\"\n\nmodel_config:\n  mistral:\n    reasoning_family: \"mistral\"\n    preferred_endpoints:\n      - \"endpoint_mistral\"\n\nvllm_endpoints:\n  - name: \"endpoint_mistral\"\n    address: \"172.28.0.20\"\n    port: 8002\n    weight: 3\n\nsemantic_cache:\n  enabled: True\n  backend_type: \"milvus\"\n  similarity_threshold: 0.8\n  max_entries: 1000\n  ttl_seconds: 3600\n\nprompt_guard:\n  enabled: False\n  threshold: 0.7\n  use_modernbert: true\n\ntools:\n  enabled: True\n  top_k: 3\n  similarity_threshold: 0.2\n", "intent": "Route queries to mistral, using domain-based routing, with milvus semantic cache, with tools auto-selection, for istio deployment", "deployment_context": "istio", "source": "template", "values": {"decision_name": "business_decision", "model_name": "mistral", "signal_type": "domain", "category1": "technical", "category2": "engineering", "endpoint_address": "172.28.0.20", "endpoint_port": 8002, "endpoint_weight": 3, "cache_enabled": true, "cache_backend": "milvus", "cache_threshold": 0.8, "guard_enabled": false, "guard_threshold": 0.7, "tools_enabled": true, "deployment_context": "istio"}}
{"id": "template_18588", "config": "# Semantic Router Configuration\n# Generated from template\n\ndecisions:\n  - name: \"general_decision\"\n    modelRefs:\n      - model: \"llama3\"\n        use_reasoning: true\n    signals:\n      - type: \"keyword\"\n        categories:\n          - \"support\"\n          - \"customer_service\"\n\nmodel_config:\n  llama3:\n    reasoning_family: \"llama3\"\n    preferred_endpoints:\n      - \"endpoint_llama3\"\n\nvllm_endpoints:\n  - name: \"endpoint_llama3\"\n    address: \"192.168.1.100\"\n    port: 8000\n    weight: 2\n\nsemantic_cache:\n  enabled: True\n  backend_type: \"redis\"\n  similarity_threshold: 0.9\n  max_entries: 1000\n  ttl_seconds: 3600\n\nprompt_guard:\n  enabled: True\n  threshold: 0.7\n  use_modernbert: true\n\ntools:\n  enabled: False\n  top_k: 3\n  similarity_threshold: 0.2\n", "intent": "Route queries to llama3, using keyword-based routing, with redis semantic cache, with PII detection, for ai-gateway deployment", "deployment_context": "ai-gateway", "source": "template", "values": {"decision_name": "general_decision", "model_name": "llama3", "signal_type": "keyword", "category1": "support", "category2": "customer_service", "endpoint_address": "192.168.1.100", "endpoint_port": 8000, "endpoint_weight": 2, "cache_enabled": true, "cache_backend": "redis", "cache_threshold": 0.9, "guard_enabled": true, "guard_threshold": 0.7, "tools_enabled": false, "deployment_context": "ai-gateway"}}
{"id": "template_86135", "config": "# Semantic Router Configuration\n# Generated from template\n\ndecisions:\n  - name: \"general_decision\"\n    modelRefs:\n      - model: \"mistral\"\n        use_reasoning: true\n    signals:\n      - type: \"domain\"\n        categories:\n          - \"technical\"\n          - \"finance\"\n\nmodel_config:\n  mistral:\n    reasoning_family: \"mistral\"\n    preferred_endpoints:\n      - \"endpoint_mistral\"\n\nvllm_endpoints:\n  - name: \"endpoint_mistral\"\n    address: \"192.168.1.100\"\n    port: 11434\n    weight: 3\n\nsemantic_cache:\n  enabled: True\n  backend_type: \"redis\"\n  similarity_threshold: 0.9\n  max_entries: 1000\n  ttl_seconds: 3600\n\nprompt_guard:\n  enabled: True\n  threshold: 0.8\n  use_modernbert: true\n\ntools:\n  enabled: False\n  top_k: 3\n  similarity_threshold: 0.2\n", "intent": "Route queries to mistral, using domain-based routing, with redis semantic cache, with PII detection, for quickstart deployment", "deployment_context": "quickstart", "source": "template", "values": {"decision_name": "general_decision", "model_name": "mistral", "signal_type": "domain", "category1": "technical", "category2": "finance", "endpoint_address": "192.168.1.100", "endpoint_port": 11434, "endpoint_weight": 3, "cache_enabled": true, "cache_backend": "redis", "cache_threshold": 0.9, "guard_enabled": true, "guard_threshold": 0.8, "tools_enabled": false, "deployment_context": "quickstart"}}
{"id": "template_38241", "config": "# Semantic Router Configuration\n# Generated from template\n\ndecisions:\n  - name: \"general_decision\"\n    modelRefs:\n      - model: \"qwen3\"\n        use_reasoning: true\n    signals:\n      - type: \"embedding\"\n        categories:\n          - \"support\"\n          - \"sales\"\n\nmodel_config:\n  qwen3:\n    reasoning_family: \"qwen3\"\n    preferred_endpoints:\n      - \"endpoint_qwen3\"\n\nvllm_endpoints:\n  - name: \"endpoint_qwen3\"\n    address: \"172.16.0.10\"\n    port: 8080\n    weight: 3\n\nsemantic_cache:\n  enabled: False\n  backend_type: \"redis\"\n  similarity_threshold: 0.8\n  max_entries: 1000\n  ttl_seconds: 3600\n\nprompt_guard:\n  enabled: True\n  threshold: 0.7\n  use_modernbert: true\n\ntools:\n  enabled: False\n  top_k: 3\n  similarity_threshold: 0.2\n", "intent": "Route queries to qwen3, using embedding-based routing, with PII detection, for kubernetes deployment", "deployment_context": "kubernetes", "source": "template", "values": {"decision_name": "general_decision", "model_name": "qwen3", "signal_type": "embedding", "category1": "support", "category2": "sales", "endpoint_address": "172.16.0.10", "endpoint_port": 8080, "endpoint_weight": 3, "cache_enabled": false, "cache_backend": "redis", "cache_threshold": 0.8, "guard_enabled": true, "guard_threshold": 0.7, "tools_enabled": false, "deployment_context": "kubernetes"}}
{"id": "template_68157", "config": "# Semantic Router Configuration\n# Generated from template\n\ndecisions:\n  - name: \"support_decision\"\n    modelRefs:\n      - model: \"mistral\"\n        use_reasoning: true\n    signals:\n      - type: \"keyword\"\n        categories:\n          - \"general\"\n          - \"customer_service\"\n\nmodel_config:\n  mistral:\n    reasoning_family: \"mistral\"\n    preferred_endpoints:\n      - \"endpoint_mistral\"\n\nvllm_endpoints:\n  - name: \"endpoint_mistral\"\n    address: \"10.0.0.50\"\n    port: 8000\n    weight: 2\n\nsemantic_cache:\n  enabled: True\n  backend_type: \"milvus\"\n  similarity_threshold: 0.9\n  max_entries: 1000\n  ttl_seconds: 3600\n\nprompt_guard:\n  enabled: True\n  threshold: 0.8\n  use_modernbert: true\n\ntools:\n  enabled: False\n  top_k: 3\n  similarity_threshold: 0.2\n", "intent": "Route queries to mistral, using keyword-based routing, with milvus semantic cache, with PII detection, for ai-gateway deployment", "deployment_context": "ai-gateway", "source": "template", "values": {"decision_name": "support_decision", "model_name": "mistral", "signal_type": "keyword", "category1": "general", "category2": "customer_service", "endpoint_address": "10.0.0.50", "endpoint_port": 8000, "endpoint_weight": 2, "cache_enabled": true, "cache_backend": "milvus", "cache_threshold": 0.9, "guard_enabled": true, "guard_threshold": 0.8, "tools_enabled": false, "deployment_context": "ai-gateway"}}
{"id": "template_49040", "config": "# Semantic Router Configuration\n# Generated from template\n\ndecisions:\n  - name: \"technical_decision\"\n    modelRefs:\n      - model: \"qwen3\"\n        use_reasoning: true\n    signals:\n      - type: \"keyword\"\n        categories:\n          - \"business\"\n          - \"customer_service\"\n\nmodel_config:\n  qwen3:\n    reasoning_family: \"qwen3\"\n    preferred_endpoints:\n      - \"endpoint_qwen3\"\n\nvllm_endpoints:\n  - name: \"endpoint_qwen3\"\n    address: \"172.28.0.20\"\n    port: 8080\n    weight: 2\n\nsemantic_cache:\n  enabled: True\n  backend_type: \"redis\"\n  similarity_threshold: 0.9\n  max_entries: 1000\n  ttl_seconds: 3600\n\nprompt_guard:\n  enabled: False\n  threshold: 0.6\n  use_modernbert: true\n\ntools:\n  enabled: False\n  top_k: 3\n  similarity_threshold: 0.2\n", "intent": "Route queries to qwen3, using keyword-based routing, with redis semantic cache, for quickstart deployment", "deployment_context": "quickstart", "source": "template", "values": {"decision_name": "technical_decision", "model_name": "qwen3", "signal_type": "keyword", "category1": "business", "category2": "customer_service", "endpoint_address": "172.28.0.20", "endpoint_port": 8080, "endpoint_weight": 2, "cache_enabled": true, "cache_backend": "redis", "cache_threshold": 0.9, "guard_enabled": false, "guard_threshold": 0.6, "tools_enabled": false, "deployment_context": "quickstart"}}
{"id": "template_29473", "config": "# Semantic Router Configuration\n# Generated from template\n\ndecisions:\n  - name: \"support_decision\"\n    modelRefs:\n      - model: \"phi4\"\n        use_reasoning: true\n    signals:\n      - type: \"embedding\"\n        categories:\n          - \"business\"\n          - \"finance\"\n\nmodel_config:\n  phi4:\n    reasoning_family: \"phi4\"\n    preferred_endpoints:\n      - \"endpoint_phi4\"\n\nvllm_endpoints:\n  - name: \"endpoint_phi4\"\n    address: \"10.0.0.50\"\n    port: 8002\n    weight: 3\n\nsemantic_cache:\n  enabled: False\n  backend_type: \"redis\"\n  similarity_threshold: 0.8\n  max_entries: 1000\n  ttl_seconds: 3600\n\nprompt_guard:\n  enabled: True\n  threshold: 0.7\n  use_modernbert: true\n\ntools:\n  enabled: True\n  top_k: 3\n  similarity_threshold: 0.2\n", "intent": "Route queries to phi4, using embedding-based routing, with PII detection, with tools auto-selection, for kubernetes deployment", "deployment_context": "kubernetes", "source": "template", "values": {"decision_name": "support_decision", "model_name": "phi4", "signal_type": "embedding", "category1": "business", "category2": "finance", "endpoint_address": "10.0.0.50", "endpoint_port": 8002, "endpoint_weight": 3, "cache_enabled": false, "cache_backend": "redis", "cache_threshold": 0.8, "guard_enabled": true, "guard_threshold": 0.7, "tools_enabled": true, "deployment_context": "kubernetes"}}
{"id": "template_80301", "config": "# Semantic Router Configuration\n# Generated from template\n\ndecisions:\n  - name: \"general_decision\"\n    modelRefs:\n      - model: \"phi4\"\n        use_reasoning: true\n    signals:\n      - type: \"domain\"\n        categories:\n          - \"business\"\n          - \"customer_service\"\n\nmodel_config:\n  phi4:\n    reasoning_family: \"phi4\"\n    preferred_endpoints:\n      - \"endpoint_phi4\"\n\nvllm_endpoints:\n  - name: \"endpoint_phi4\"\n    address: \"10.0.0.50\"\n    port: 8080\n    weight: 2\n\nsemantic_cache:\n  enabled: True\n  backend_type: \"milvus\"\n  similarity_threshold: 0.7\n  max_entries: 1000\n  ttl_seconds: 3600\n\nprompt_guard:\n  enabled: False\n  threshold: 0.7\n  use_modernbert: true\n\ntools:\n  enabled: True\n  top_k: 3\n  similarity_threshold: 0.2\n", "intent": "Route queries to phi4, using domain-based routing, with milvus semantic cache, with tools auto-selection, for istio deployment", "deployment_context": "istio", "source": "template", "values": {"decision_name": "general_decision", "model_name": "phi4", "signal_type": "domain", "category1": "business", "category2": "customer_service", "endpoint_address": "10.0.0.50", "endpoint_port": 8080, "endpoint_weight": 2, "cache_enabled": true, "cache_backend": "milvus", "cache_threshold": 0.7, "guard_enabled": false, "guard_threshold": 0.7, "tools_enabled": true, "deployment_context": "istio"}}
{"id": "template_35727", "config": "# Semantic Router Configuration\n# Generated from template\n\ndecisions:\n  - name: \"technical_decision\"\n    modelRefs:\n      - model: \"mistral\"\n        use_reasoning: true\n    signals:\n      - type: \"embedding\"\n        categories:\n          - \"support\"\n          - \"sales\"\n\nmodel_config:\n  mistral:\n    reasoning_family: \"mistral\"\n    preferred_endpoints:\n      - \"endpoint_mistral\"\n\nvllm_endpoints:\n  - name: \"endpoint_mistral\"\n    address: \"10.0.0.50\"\n    port: 8002\n    weight: 1\n\nsemantic_cache:\n  enabled: False\n  backend_type: \"redis\"\n  similarity_threshold: 0.7\n  max_entries: 1000\n  ttl_seconds: 3600\n\nprompt_guard:\n  enabled: False\n  threshold: 0.7\n  use_modernbert: true\n\ntools:\n  enabled: True\n  top_k: 3\n  similarity_threshold: 0.2\n", "intent": "Route queries to mistral, using embedding-based routing, with tools auto-selection, for kubernetes deployment", "deployment_context": "kubernetes", "source": "template", "values": {"decision_name": "technical_decision", "model_name": "mistral", "signal_type": "embedding", "category1": "support", "category2": "sales", "endpoint_address": "10.0.0.50", "endpoint_port": 8002, "endpoint_weight": 1, "cache_enabled": false, "cache_backend": "redis", "cache_threshold": 0.7, "guard_enabled": false, "guard_threshold": 0.7, "tools_enabled": true, "deployment_context": "kubernetes"}}
{"id": "template_27651", "config": "# Semantic Router Configuration\n# Generated from template\n\ndecisions:\n  - name: \"general_decision\"\n    modelRefs:\n      - model: \"llama3\"\n        use_reasoning: true\n    signals:\n      - type: \"domain\"\n        categories:\n          - \"support\"\n          - \"customer_service\"\n\nmodel_config:\n  llama3:\n    reasoning_family: \"llama3\"\n    preferred_endpoints:\n      - \"endpoint_llama3\"\n\nvllm_endpoints:\n  - name: \"endpoint_llama3\"\n    address: \"172.28.0.20\"\n    port: 11434\n    weight: 2\n\nsemantic_cache:\n  enabled: False\n  backend_type: \"memory\"\n  similarity_threshold: 0.8\n  max_entries: 1000\n  ttl_seconds: 3600\n\nprompt_guard:\n  enabled: False\n  threshold: 0.6\n  use_modernbert: true\n\ntools:\n  enabled: True\n  top_k: 3\n  similarity_threshold: 0.2\n", "intent": "Route queries to llama3, using domain-based routing, with tools auto-selection, for ai-gateway deployment", "deployment_context": "ai-gateway", "source": "template", "values": {"decision_name": "general_decision", "model_name": "llama3", "signal_type": "domain", "category1": "support", "category2": "customer_service", "endpoint_address": "172.28.0.20", "endpoint_port": 11434, "endpoint_weight": 2, "cache_enabled": false, "cache_backend": "memory", "cache_threshold": 0.8, "guard_enabled": false, "guard_threshold": 0.6, "tools_enabled": true, "deployment_context": "ai-gateway"}}
{"id": "template_18337", "config": "# Semantic Router Configuration\n# Generated from template\n\ndecisions:\n  - name: \"business_decision\"\n    modelRefs:\n      - model: \"qwen3\"\n        use_reasoning: true\n    signals:\n      - type: \"embedding\"\n        categories:\n          - \"general\"\n          - \"customer_service\"\n\nmodel_config:\n  qwen3:\n    reasoning_family: \"qwen3\"\n    preferred_endpoints:\n      - \"endpoint_qwen3\"\n\nvllm_endpoints:\n  - name: \"endpoint_qwen3\"\n    address: \"172.16.0.10\"\n    port: 8002\n    weight: 2\n\nsemantic_cache:\n  enabled: True\n  backend_type: \"milvus\"\n  similarity_threshold: 0.8\n  max_entries: 1000\n  ttl_seconds: 3600\n\nprompt_guard:\n  enabled: True\n  threshold: 0.7\n  use_modernbert: true\n\ntools:\n  enabled: True\n  top_k: 3\n  similarity_threshold: 0.2\n", "intent": "Route queries to qwen3, using embedding-based routing, with milvus semantic cache, with PII detection, with tools auto-selection, for ai-gateway deployment", "deployment_context": "ai-gateway", "source": "template", "values": {"decision_name": "business_decision", "model_name": "qwen3", "signal_type": "embedding", "category1": "general", "category2": "customer_service", "endpoint_address": "172.16.0.10", "endpoint_port": 8002, "endpoint_weight": 2, "cache_enabled": true, "cache_backend": "milvus", "cache_threshold": 0.8, "guard_enabled": true, "guard_threshold": 0.7, "tools_enabled": true, "deployment_context": "ai-gateway"}}
{"id": "template_38635", "config": "# Semantic Router Configuration\n# Generated from template\n\ndecisions:\n  - name: \"business_decision\"\n    modelRefs:\n      - model: \"mistral\"\n        use_reasoning: true\n    signals:\n      - type: \"domain\"\n        categories:\n          - \"support\"\n          - \"engineering\"\n\nmodel_config:\n  mistral:\n    reasoning_family: \"mistral\"\n    preferred_endpoints:\n      - \"endpoint_mistral\"\n\nvllm_endpoints:\n  - name: \"endpoint_mistral\"\n    address: \"172.16.0.10\"\n    port: 11434\n    weight: 3\n\nsemantic_cache:\n  enabled: True\n  backend_type: \"milvus\"\n  similarity_threshold: 0.9\n  max_entries: 1000\n  ttl_seconds: 3600\n\nprompt_guard:\n  enabled: True\n  threshold: 0.8\n  use_modernbert: true\n\ntools:\n  enabled: True\n  top_k: 3\n  similarity_threshold: 0.2\n", "intent": "Route queries to mistral, using domain-based routing, with milvus semantic cache, with PII detection, with tools auto-selection, for quickstart deployment", "deployment_context": "quickstart", "source": "template", "values": {"decision_name": "business_decision", "model_name": "mistral", "signal_type": "domain", "category1": "support", "category2": "engineering", "endpoint_address": "172.16.0.10", "endpoint_port": 11434, "endpoint_weight": 3, "cache_enabled": true, "cache_backend": "milvus", "cache_threshold": 0.9, "guard_enabled": true, "guard_threshold": 0.8, "tools_enabled": true, "deployment_context": "quickstart"}}
{"id": "template_76872", "config": "# Semantic Router Configuration\n# Generated from template\n\ndecisions:\n  - name: \"business_decision\"\n    modelRefs:\n      - model: \"llama3\"\n        use_reasoning: true\n    signals:\n      - type: \"domain\"\n        categories:\n          - \"technical\"\n          - \"sales\"\n\nmodel_config:\n  llama3:\n    reasoning_family: \"llama3\"\n    preferred_endpoints:\n      - \"endpoint_llama3\"\n\nvllm_endpoints:\n  - name: \"endpoint_llama3\"\n    address: \"192.168.1.100\"\n    port: 8080\n    weight: 2\n\nsemantic_cache:\n  enabled: True\n  backend_type: \"milvus\"\n  similarity_threshold: 0.8\n  max_entries: 1000\n  ttl_seconds: 3600\n\nprompt_guard:\n  enabled: False\n  threshold: 0.7\n  use_modernbert: true\n\ntools:\n  enabled: False\n  top_k: 3\n  similarity_threshold: 0.2\n", "intent": "Route queries to llama3, using domain-based routing, with milvus semantic cache, for kubernetes deployment", "deployment_context": "kubernetes", "source": "template", "values": {"decision_name": "business_decision", "model_name": "llama3", "signal_type": "domain", "category1": "technical", "category2": "sales", "endpoint_address": "192.168.1.100", "endpoint_port": 8080, "endpoint_weight": 2, "cache_enabled": true, "cache_backend": "milvus", "cache_threshold": 0.8, "guard_enabled": false, "guard_threshold": 0.7, "tools_enabled": false, "deployment_context": "kubernetes"}}
{"id": "template_96696", "config": "# Semantic Router Configuration\n# Generated from template\n\ndecisions:\n  - name: \"technical_decision\"\n    modelRefs:\n      - model: \"llama3\"\n        use_reasoning: true\n    signals:\n      - type: \"domain\"\n        categories:\n          - \"business\"\n          - \"customer_service\"\n\nmodel_config:\n  llama3:\n    reasoning_family: \"llama3\"\n    preferred_endpoints:\n      - \"endpoint_llama3\"\n\nvllm_endpoints:\n  - name: \"endpoint_llama3\"\n    address: \"172.28.0.20\"\n    port: 8002\n    weight: 3\n\nsemantic_cache:\n  enabled: False\n  backend_type: \"redis\"\n  similarity_threshold: 0.8\n  max_entries: 1000\n  ttl_seconds: 3600\n\nprompt_guard:\n  enabled: True\n  threshold: 0.7\n  use_modernbert: true\n\ntools:\n  enabled: True\n  top_k: 3\n  similarity_threshold: 0.2\n", "intent": "Route queries to llama3, using domain-based routing, with PII detection, with tools auto-selection, for quickstart deployment", "deployment_context": "quickstart", "source": "template", "values": {"decision_name": "technical_decision", "model_name": "llama3", "signal_type": "domain", "category1": "business", "category2": "customer_service", "endpoint_address": "172.28.0.20", "endpoint_port": 8002, "endpoint_weight": 3, "cache_enabled": false, "cache_backend": "redis", "cache_threshold": 0.8, "guard_enabled": true, "guard_threshold": 0.7, "tools_enabled": true, "deployment_context": "quickstart"}}
{"id": "template_49739", "config": "# Semantic Router Configuration\n# Generated from template\n\ndecisions:\n  - name: \"general_decision\"\n    modelRefs:\n      - model: \"mistral\"\n        use_reasoning: true\n    signals:\n      - type: \"keyword\"\n        categories:\n          - \"technical\"\n          - \"finance\"\n\nmodel_config:\n  mistral:\n    reasoning_family: \"mistral\"\n    preferred_endpoints:\n      - \"endpoint_mistral\"\n\nvllm_endpoints:\n  - name: \"endpoint_mistral\"\n    address: \"172.28.0.20\"\n    port: 8000\n    weight: 1\n\nsemantic_cache:\n  enabled: False\n  backend_type: \"memory\"\n  similarity_threshold: 0.7\n  max_entries: 1000\n  ttl_seconds: 3600\n\nprompt_guard:\n  enabled: True\n  threshold: 0.8\n  use_modernbert: true\n\ntools:\n  enabled: False\n  top_k: 3\n  similarity_threshold: 0.2\n", "intent": "Route queries to mistral, using keyword-based routing, with PII detection, for kubernetes deployment", "deployment_context": "kubernetes", "source": "template", "values": {"decision_name": "general_decision", "model_name": "mistral", "signal_type": "keyword", "category1": "technical", "category2": "finance", "endpoint_address": "172.28.0.20", "endpoint_port": 8000, "endpoint_weight": 1, "cache_enabled": false, "cache_backend": "memory", "cache_threshold": 0.7, "guard_enabled": true, "guard_threshold": 0.8, "tools_enabled": false, "deployment_context": "kubernetes"}}
{"id": "template_5076", "config": "# Semantic Router Configuration\n# Generated from template\n\ndecisions:\n  - name: \"general_decision\"\n    modelRefs:\n      - model: \"phi4\"\n        use_reasoning: true\n    signals:\n      - type: \"keyword\"\n        categories:\n          - \"support\"\n          - \"engineering\"\n\nmodel_config:\n  phi4:\n    reasoning_family: \"phi4\"\n    preferred_endpoints:\n      - \"endpoint_phi4\"\n\nvllm_endpoints:\n  - name: \"endpoint_phi4\"\n    address: \"172.28.0.20\"\n    port: 8002\n    weight: 2\n\nsemantic_cache:\n  enabled: False\n  backend_type: \"memory\"\n  similarity_threshold: 0.8\n  max_entries: 1000\n  ttl_seconds: 3600\n\nprompt_guard:\n  enabled: False\n  threshold: 0.8\n  use_modernbert: true\n\ntools:\n  enabled: True\n  top_k: 3\n  similarity_threshold: 0.2\n", "intent": "Route queries to phi4, using keyword-based routing, with tools auto-selection, for quickstart deployment", "deployment_context": "quickstart", "source": "template", "values": {"decision_name": "general_decision", "model_name": "phi4", "signal_type": "keyword", "category1": "support", "category2": "engineering", "endpoint_address": "172.28.0.20", "endpoint_port": 8002, "endpoint_weight": 2, "cache_enabled": false, "cache_backend": "memory", "cache_threshold": 0.8, "guard_enabled": false, "guard_threshold": 0.8, "tools_enabled": true, "deployment_context": "quickstart"}}
{"id": "template_212", "config": "# Semantic Router Configuration\n# Generated from template\n\ndecisions:\n  - name: \"general_decision\"\n    modelRefs:\n      - model: \"mistral\"\n        use_reasoning: true\n    signals:\n      - type: \"keyword\"\n        categories:\n          - \"support\"\n          - \"finance\"\n\nmodel_config:\n  mistral:\n    reasoning_family: \"mistral\"\n    preferred_endpoints:\n      - \"endpoint_mistral\"\n\nvllm_endpoints:\n  - name: \"endpoint_mistral\"\n    address: \"172.28.0.20\"\n    port: 11434\n    weight: 1\n\nsemantic_cache:\n  enabled: False\n  backend_type: \"memory\"\n  similarity_threshold: 0.7\n  max_entries: 1000\n  ttl_seconds: 3600\n\nprompt_guard:\n  enabled: True\n  threshold: 0.6\n  use_modernbert: true\n\ntools:\n  enabled: True\n  top_k: 3\n  similarity_threshold: 0.2\n", "intent": "Route queries to mistral, using keyword-based routing, with PII detection, with tools auto-selection, for kubernetes deployment", "deployment_context": "kubernetes", "source": "template", "values": {"decision_name": "general_decision", "model_name": "mistral", "signal_type": "keyword", "category1": "support", "category2": "finance", "endpoint_address": "172.28.0.20", "endpoint_port": 11434, "endpoint_weight": 1, "cache_enabled": false, "cache_backend": "memory", "cache_threshold": 0.7, "guard_enabled": true, "guard_threshold": 0.6, "tools_enabled": true, "deployment_context": "kubernetes"}}
{"id": "template_11694", "config": "# Semantic Router Configuration\n# Generated from template\n\ndecisions:\n  - name: \"technical_decision\"\n    modelRefs:\n      - model: \"phi4\"\n        use_reasoning: true\n    signals:\n      - type: \"keyword\"\n        categories:\n          - \"support\"\n          - \"finance\"\n\nmodel_config:\n  phi4:\n    reasoning_family: \"phi4\"\n    preferred_endpoints:\n      - \"endpoint_phi4\"\n\nvllm_endpoints:\n  - name: \"endpoint_phi4\"\n    address: \"192.168.1.100\"\n    port: 8080\n    weight: 3\n\nsemantic_cache:\n  enabled: False\n  backend_type: \"memory\"\n  similarity_threshold: 0.7\n  max_entries: 1000\n  ttl_seconds: 3600\n\nprompt_guard:\n  enabled: True\n  threshold: 0.6\n  use_modernbert: true\n\ntools:\n  enabled: True\n  top_k: 3\n  similarity_threshold: 0.2\n", "intent": "Route queries to phi4, using keyword-based routing, with PII detection, with tools auto-selection, for ai-gateway deployment", "deployment_context": "ai-gateway", "source": "template", "values": {"decision_name": "technical_decision", "model_name": "phi4", "signal_type": "keyword", "category1": "support", "category2": "finance", "endpoint_address": "192.168.1.100", "endpoint_port": 8080, "endpoint_weight": 3, "cache_enabled": false, "cache_backend": "memory", "cache_threshold": 0.7, "guard_enabled": true, "guard_threshold": 0.6, "tools_enabled": true, "deployment_context": "ai-gateway"}}
{"id": "template_40606", "config": "# Semantic Router Configuration\n# Generated from template\n\ndecisions:\n  - name: \"general_decision\"\n    modelRefs:\n      - model: \"mistral\"\n        use_reasoning: true\n    signals:\n      - type: \"domain\"\n        categories:\n          - \"technical\"\n          - \"finance\"\n\nmodel_config:\n  mistral:\n    reasoning_family: \"mistral\"\n    preferred_endpoints:\n      - \"endpoint_mistral\"\n\nvllm_endpoints:\n  - name: \"endpoint_mistral\"\n    address: \"172.28.0.20\"\n    port: 8000\n    weight: 2\n\nsemantic_cache:\n  enabled: False\n  backend_type: \"milvus\"\n  similarity_threshold: 0.9\n  max_entries: 1000\n  ttl_seconds: 3600\n\nprompt_guard:\n  enabled: False\n  threshold: 0.8\n  use_modernbert: true\n\ntools:\n  enabled: False\n  top_k: 3\n  similarity_threshold: 0.2\n", "intent": "Route queries to mistral, using domain-based routing, for quickstart deployment", "deployment_context": "quickstart", "source": "template", "values": {"decision_name": "general_decision", "model_name": "mistral", "signal_type": "domain", "category1": "technical", "category2": "finance", "endpoint_address": "172.28.0.20", "endpoint_port": 8000, "endpoint_weight": 2, "cache_enabled": false, "cache_backend": "milvus", "cache_threshold": 0.9, "guard_enabled": false, "guard_threshold": 0.8, "tools_enabled": false, "deployment_context": "quickstart"}}
{"id": "template_2807", "config": "# Semantic Router Configuration\n# Generated from template\n\ndecisions:\n  - name: \"business_decision\"\n    modelRefs:\n      - model: \"phi4\"\n        use_reasoning: true\n    signals:\n      - type: \"keyword\"\n        categories:\n          - \"support\"\n          - \"sales\"\n\nmodel_config:\n  phi4:\n    reasoning_family: \"phi4\"\n    preferred_endpoints:\n      - \"endpoint_phi4\"\n\nvllm_endpoints:\n  - name: \"endpoint_phi4\"\n    address: \"172.16.0.10\"\n    port: 8080\n    weight: 1\n\nsemantic_cache:\n  enabled: True\n  backend_type: \"memory\"\n  similarity_threshold: 0.8\n  max_entries: 1000\n  ttl_seconds: 3600\n\nprompt_guard:\n  enabled: False\n  threshold: 0.6\n  use_modernbert: true\n\ntools:\n  enabled: False\n  top_k: 3\n  similarity_threshold: 0.2\n", "intent": "Route queries to phi4, using keyword-based routing, with memory semantic cache, for ai-gateway deployment", "deployment_context": "ai-gateway", "source": "template", "values": {"decision_name": "business_decision", "model_name": "phi4", "signal_type": "keyword", "category1": "support", "category2": "sales", "endpoint_address": "172.16.0.10", "endpoint_port": 8080, "endpoint_weight": 1, "cache_enabled": true, "cache_backend": "memory", "cache_threshold": 0.8, "guard_enabled": false, "guard_threshold": 0.6, "tools_enabled": false, "deployment_context": "ai-gateway"}}
{"id": "template_36425", "config": "# Semantic Router Configuration\n# Generated from template\n\ndecisions:\n  - name: \"technical_decision\"\n    modelRefs:\n      - model: \"qwen3\"\n        use_reasoning: true\n    signals:\n      - type: \"keyword\"\n        categories:\n          - \"support\"\n          - \"engineering\"\n\nmodel_config:\n  qwen3:\n    reasoning_family: \"qwen3\"\n    preferred_endpoints:\n      - \"endpoint_qwen3\"\n\nvllm_endpoints:\n  - name: \"endpoint_qwen3\"\n    address: \"172.16.0.10\"\n    port: 8000\n    weight: 2\n\nsemantic_cache:\n  enabled: False\n  backend_type: \"milvus\"\n  similarity_threshold: 0.9\n  max_entries: 1000\n  ttl_seconds: 3600\n\nprompt_guard:\n  enabled: True\n  threshold: 0.6\n  use_modernbert: true\n\ntools:\n  enabled: False\n  top_k: 3\n  similarity_threshold: 0.2\n", "intent": "Route queries to qwen3, using keyword-based routing, with PII detection, for istio deployment", "deployment_context": "istio", "source": "template", "values": {"decision_name": "technical_decision", "model_name": "qwen3", "signal_type": "keyword", "category1": "support", "category2": "engineering", "endpoint_address": "172.16.0.10", "endpoint_port": 8000, "endpoint_weight": 2, "cache_enabled": false, "cache_backend": "milvus", "cache_threshold": 0.9, "guard_enabled": true, "guard_threshold": 0.6, "tools_enabled": false, "deployment_context": "istio"}}
{"id": "template_58995", "config": "# Semantic Router Configuration\n# Generated from template\n\ndecisions:\n  - name: \"general_decision\"\n    modelRefs:\n      - model: \"phi4\"\n        use_reasoning: true\n    signals:\n      - type: \"keyword\"\n        categories:\n          - \"technical\"\n          - \"sales\"\n\nmodel_config:\n  phi4:\n    reasoning_family: \"phi4\"\n    preferred_endpoints:\n      - \"endpoint_phi4\"\n\nvllm_endpoints:\n  - name: \"endpoint_phi4\"\n    address: \"172.28.0.20\"\n    port: 11434\n    weight: 1\n\nsemantic_cache:\n  enabled: False\n  backend_type: \"milvus\"\n  similarity_threshold: 0.7\n  max_entries: 1000\n  ttl_seconds: 3600\n\nprompt_guard:\n  enabled: False\n  threshold: 0.7\n  use_modernbert: true\n\ntools:\n  enabled: True\n  top_k: 3\n  similarity_threshold: 0.2\n", "intent": "Route queries to phi4, using keyword-based routing, with tools auto-selection, for istio deployment", "deployment_context": "istio", "source": "template", "values": {"decision_name": "general_decision", "model_name": "phi4", "signal_type": "keyword", "category1": "technical", "category2": "sales", "endpoint_address": "172.28.0.20", "endpoint_port": 11434, "endpoint_weight": 1, "cache_enabled": false, "cache_backend": "milvus", "cache_threshold": 0.7, "guard_enabled": false, "guard_threshold": 0.7, "tools_enabled": true, "deployment_context": "istio"}}
{"id": "template_55704", "config": "# Semantic Router Configuration\n# Generated from template\n\ndecisions:\n  - name: \"support_decision\"\n    modelRefs:\n      - model: \"phi4\"\n        use_reasoning: true\n    signals:\n      - type: \"embedding\"\n        categories:\n          - \"support\"\n          - \"sales\"\n\nmodel_config:\n  phi4:\n    reasoning_family: \"phi4\"\n    preferred_endpoints:\n      - \"endpoint_phi4\"\n\nvllm_endpoints:\n  - name: \"endpoint_phi4\"\n    address: \"172.16.0.10\"\n    port: 8080\n    weight: 3\n\nsemantic_cache:\n  enabled: False\n  backend_type: \"milvus\"\n  similarity_threshold: 0.7\n  max_entries: 1000\n  ttl_seconds: 3600\n\nprompt_guard:\n  enabled: True\n  threshold: 0.8\n  use_modernbert: true\n\ntools:\n  enabled: False\n  top_k: 3\n  similarity_threshold: 0.2\n", "intent": "Route queries to phi4, using embedding-based routing, with PII detection, for ai-gateway deployment", "deployment_context": "ai-gateway", "source": "template", "values": {"decision_name": "support_decision", "model_name": "phi4", "signal_type": "embedding", "category1": "support", "category2": "sales", "endpoint_address": "172.16.0.10", "endpoint_port": 8080, "endpoint_weight": 3, "cache_enabled": false, "cache_backend": "milvus", "cache_threshold": 0.7, "guard_enabled": true, "guard_threshold": 0.8, "tools_enabled": false, "deployment_context": "ai-gateway"}}
{"id": "template_35198", "config": "# Semantic Router Configuration\n# Generated from template\n\ndecisions:\n  - name: \"business_decision\"\n    modelRefs:\n      - model: \"qwen3\"\n        use_reasoning: true\n    signals:\n      - type: \"keyword\"\n        categories:\n          - \"general\"\n          - \"sales\"\n\nmodel_config:\n  qwen3:\n    reasoning_family: \"qwen3\"\n    preferred_endpoints:\n      - \"endpoint_qwen3\"\n\nvllm_endpoints:\n  - name: \"endpoint_qwen3\"\n    address: \"172.16.0.10\"\n    port: 8080\n    weight: 1\n\nsemantic_cache:\n  enabled: True\n  backend_type: \"redis\"\n  similarity_threshold: 0.7\n  max_entries: 1000\n  ttl_seconds: 3600\n\nprompt_guard:\n  enabled: False\n  threshold: 0.6\n  use_modernbert: true\n\ntools:\n  enabled: True\n  top_k: 3\n  similarity_threshold: 0.2\n", "intent": "Route queries to qwen3, using keyword-based routing, with redis semantic cache, with tools auto-selection, for istio deployment", "deployment_context": "istio", "source": "template", "values": {"decision_name": "business_decision", "model_name": "qwen3", "signal_type": "keyword", "category1": "general", "category2": "sales", "endpoint_address": "172.16.0.10", "endpoint_port": 8080, "endpoint_weight": 1, "cache_enabled": true, "cache_backend": "redis", "cache_threshold": 0.7, "guard_enabled": false, "guard_threshold": 0.6, "tools_enabled": true, "deployment_context": "istio"}}
{"id": "template_23626", "config": "# Semantic Router Configuration\n# Generated from template\n\ndecisions:\n  - name: \"technical_decision\"\n    modelRefs:\n      - model: \"phi4\"\n        use_reasoning: true\n    signals:\n      - type: \"embedding\"\n        categories:\n          - \"business\"\n          - \"sales\"\n\nmodel_config:\n  phi4:\n    reasoning_family: \"phi4\"\n    preferred_endpoints:\n      - \"endpoint_phi4\"\n\nvllm_endpoints:\n  - name: \"endpoint_phi4\"\n    address: \"172.16.0.10\"\n    port: 8080\n    weight: 1\n\nsemantic_cache:\n  enabled: False\n  backend_type: \"milvus\"\n  similarity_threshold: 0.7\n  max_entries: 1000\n  ttl_seconds: 3600\n\nprompt_guard:\n  enabled: False\n  threshold: 0.6\n  use_modernbert: true\n\ntools:\n  enabled: True\n  top_k: 3\n  similarity_threshold: 0.2\n", "intent": "Route queries to phi4, using embedding-based routing, with tools auto-selection, for kubernetes deployment", "deployment_context": "kubernetes", "source": "template", "values": {"decision_name": "technical_decision", "model_name": "phi4", "signal_type": "embedding", "category1": "business", "category2": "sales", "endpoint_address": "172.16.0.10", "endpoint_port": 8080, "endpoint_weight": 1, "cache_enabled": false, "cache_backend": "milvus", "cache_threshold": 0.7, "guard_enabled": false, "guard_threshold": 0.6, "tools_enabled": true, "deployment_context": "kubernetes"}}
{"id": "template_47110", "config": "# Semantic Router Configuration\n# Generated from template\n\ndecisions:\n  - name: \"technical_decision\"\n    modelRefs:\n      - model: \"llama3\"\n        use_reasoning: true\n    signals:\n      - type: \"keyword\"\n        categories:\n          - \"technical\"\n          - \"sales\"\n\nmodel_config:\n  llama3:\n    reasoning_family: \"llama3\"\n    preferred_endpoints:\n      - \"endpoint_llama3\"\n\nvllm_endpoints:\n  - name: \"endpoint_llama3\"\n    address: \"172.16.0.10\"\n    port: 8002\n    weight: 1\n\nsemantic_cache:\n  enabled: True\n  backend_type: \"milvus\"\n  similarity_threshold: 0.9\n  max_entries: 1000\n  ttl_seconds: 3600\n\nprompt_guard:\n  enabled: True\n  threshold: 0.6\n  use_modernbert: true\n\ntools:\n  enabled: False\n  top_k: 3\n  similarity_threshold: 0.2\n", "intent": "Route queries to llama3, using keyword-based routing, with milvus semantic cache, with PII detection, for quickstart deployment", "deployment_context": "quickstart", "source": "template", "values": {"decision_name": "technical_decision", "model_name": "llama3", "signal_type": "keyword", "category1": "technical", "category2": "sales", "endpoint_address": "172.16.0.10", "endpoint_port": 8002, "endpoint_weight": 1, "cache_enabled": true, "cache_backend": "milvus", "cache_threshold": 0.9, "guard_enabled": true, "guard_threshold": 0.6, "tools_enabled": false, "deployment_context": "quickstart"}}
{"id": "template_8460", "config": "# Semantic Router Configuration\n# Generated from template\n\ndecisions:\n  - name: \"technical_decision\"\n    modelRefs:\n      - model: \"mistral\"\n        use_reasoning: true\n    signals:\n      - type: \"domain\"\n        categories:\n          - \"general\"\n          - \"finance\"\n\nmodel_config:\n  mistral:\n    reasoning_family: \"mistral\"\n    preferred_endpoints:\n      - \"endpoint_mistral\"\n\nvllm_endpoints:\n  - name: \"endpoint_mistral\"\n    address: \"192.168.1.100\"\n    port: 8000\n    weight: 3\n\nsemantic_cache:\n  enabled: True\n  backend_type: \"redis\"\n  similarity_threshold: 0.7\n  max_entries: 1000\n  ttl_seconds: 3600\n\nprompt_guard:\n  enabled: False\n  threshold: 0.6\n  use_modernbert: true\n\ntools:\n  enabled: False\n  top_k: 3\n  similarity_threshold: 0.2\n", "intent": "Route queries to mistral, using domain-based routing, with redis semantic cache, for quickstart deployment", "deployment_context": "quickstart", "source": "template", "values": {"decision_name": "technical_decision", "model_name": "mistral", "signal_type": "domain", "category1": "general", "category2": "finance", "endpoint_address": "192.168.1.100", "endpoint_port": 8000, "endpoint_weight": 3, "cache_enabled": true, "cache_backend": "redis", "cache_threshold": 0.7, "guard_enabled": false, "guard_threshold": 0.6, "tools_enabled": false, "deployment_context": "quickstart"}}
{"id": "template_1722", "config": "# Semantic Router Configuration\n# Generated from template\n\ndecisions:\n  - name: \"technical_decision\"\n    modelRefs:\n      - model: \"mistral\"\n        use_reasoning: true\n    signals:\n      - type: \"domain\"\n        categories:\n          - \"business\"\n          - \"finance\"\n\nmodel_config:\n  mistral:\n    reasoning_family: \"mistral\"\n    preferred_endpoints:\n      - \"endpoint_mistral\"\n\nvllm_endpoints:\n  - name: \"endpoint_mistral\"\n    address: \"172.28.0.20\"\n    port: 8000\n    weight: 3\n\nsemantic_cache:\n  enabled: True\n  backend_type: \"milvus\"\n  similarity_threshold: 0.9\n  max_entries: 1000\n  ttl_seconds: 3600\n\nprompt_guard:\n  enabled: True\n  threshold: 0.7\n  use_modernbert: true\n\ntools:\n  enabled: True\n  top_k: 3\n  similarity_threshold: 0.2\n", "intent": "Route queries to mistral, using domain-based routing, with milvus semantic cache, with PII detection, with tools auto-selection, for istio deployment", "deployment_context": "istio", "source": "template", "values": {"decision_name": "technical_decision", "model_name": "mistral", "signal_type": "domain", "category1": "business", "category2": "finance", "endpoint_address": "172.28.0.20", "endpoint_port": 8000, "endpoint_weight": 3, "cache_enabled": true, "cache_backend": "milvus", "cache_threshold": 0.9, "guard_enabled": true, "guard_threshold": 0.7, "tools_enabled": true, "deployment_context": "istio"}}
{"id": "template_55599", "config": "# Semantic Router Configuration\n# Generated from template\n\ndecisions:\n  - name: \"business_decision\"\n    modelRefs:\n      - model: \"mistral\"\n        use_reasoning: true\n    signals:\n      - type: \"embedding\"\n        categories:\n          - \"support\"\n          - \"engineering\"\n\nmodel_config:\n  mistral:\n    reasoning_family: \"mistral\"\n    preferred_endpoints:\n      - \"endpoint_mistral\"\n\nvllm_endpoints:\n  - name: \"endpoint_mistral\"\n    address: \"172.16.0.10\"\n    port: 8002\n    weight: 3\n\nsemantic_cache:\n  enabled: True\n  backend_type: \"redis\"\n  similarity_threshold: 0.9\n  max_entries: 1000\n  ttl_seconds: 3600\n\nprompt_guard:\n  enabled: True\n  threshold: 0.6\n  use_modernbert: true\n\ntools:\n  enabled: True\n  top_k: 3\n  similarity_threshold: 0.2\n", "intent": "Route queries to mistral, using embedding-based routing, with redis semantic cache, with PII detection, with tools auto-selection, for quickstart deployment", "deployment_context": "quickstart", "source": "template", "values": {"decision_name": "business_decision", "model_name": "mistral", "signal_type": "embedding", "category1": "support", "category2": "engineering", "endpoint_address": "172.16.0.10", "endpoint_port": 8002, "endpoint_weight": 3, "cache_enabled": true, "cache_backend": "redis", "cache_threshold": 0.9, "guard_enabled": true, "guard_threshold": 0.6, "tools_enabled": true, "deployment_context": "quickstart"}}
{"id": "template_52053", "config": "# Semantic Router Configuration\n# Generated from template\n\ndecisions:\n  - name: \"general_decision\"\n    modelRefs:\n      - model: \"qwen3\"\n        use_reasoning: true\n    signals:\n      - type: \"keyword\"\n        categories:\n          - \"business\"\n          - \"sales\"\n\nmodel_config:\n  qwen3:\n    reasoning_family: \"qwen3\"\n    preferred_endpoints:\n      - \"endpoint_qwen3\"\n\nvllm_endpoints:\n  - name: \"endpoint_qwen3\"\n    address: \"10.0.0.50\"\n    port: 8002\n    weight: 3\n\nsemantic_cache:\n  enabled: True\n  backend_type: \"milvus\"\n  similarity_threshold: 0.9\n  max_entries: 1000\n  ttl_seconds: 3600\n\nprompt_guard:\n  enabled: True\n  threshold: 0.8\n  use_modernbert: true\n\ntools:\n  enabled: True\n  top_k: 3\n  similarity_threshold: 0.2\n", "intent": "Route queries to qwen3, using keyword-based routing, with milvus semantic cache, with PII detection, with tools auto-selection, for quickstart deployment", "deployment_context": "quickstart", "source": "template", "values": {"decision_name": "general_decision", "model_name": "qwen3", "signal_type": "keyword", "category1": "business", "category2": "sales", "endpoint_address": "10.0.0.50", "endpoint_port": 8002, "endpoint_weight": 3, "cache_enabled": true, "cache_backend": "milvus", "cache_threshold": 0.9, "guard_enabled": true, "guard_threshold": 0.8, "tools_enabled": true, "deployment_context": "quickstart"}}
{"id": "template_91027", "config": "# Semantic Router Configuration\n# Generated from template\n\ndecisions:\n  - name: \"business_decision\"\n    modelRefs:\n      - model: \"llama3\"\n        use_reasoning: true\n    signals:\n      - type: \"embedding\"\n        categories:\n          - \"general\"\n          - \"sales\"\n\nmodel_config:\n  llama3:\n    reasoning_family: \"llama3\"\n    preferred_endpoints:\n      - \"endpoint_llama3\"\n\nvllm_endpoints:\n  - name: \"endpoint_llama3\"\n    address: \"10.0.0.50\"\n    port: 8002\n    weight: 2\n\nsemantic_cache:\n  enabled: True\n  backend_type: \"milvus\"\n  similarity_threshold: 0.7\n  max_entries: 1000\n  ttl_seconds: 3600\n\nprompt_guard:\n  enabled: True\n  threshold: 0.6\n  use_modernbert: true\n\ntools:\n  enabled: True\n  top_k: 3\n  similarity_threshold: 0.2\n", "intent": "Route queries to llama3, using embedding-based routing, with milvus semantic cache, with PII detection, with tools auto-selection, for kubernetes deployment", "deployment_context": "kubernetes", "source": "template", "values": {"decision_name": "business_decision", "model_name": "llama3", "signal_type": "embedding", "category1": "general", "category2": "sales", "endpoint_address": "10.0.0.50", "endpoint_port": 8002, "endpoint_weight": 2, "cache_enabled": true, "cache_backend": "milvus", "cache_threshold": 0.7, "guard_enabled": true, "guard_threshold": 0.6, "tools_enabled": true, "deployment_context": "kubernetes"}}
{"id": "template_89895", "config": "# Semantic Router Configuration\n# Generated from template\n\ndecisions:\n  - name: \"business_decision\"\n    modelRefs:\n      - model: \"llama3\"\n        use_reasoning: true\n    signals:\n      - type: \"domain\"\n        categories:\n          - \"support\"\n          - \"customer_service\"\n\nmodel_config:\n  llama3:\n    reasoning_family: \"llama3\"\n    preferred_endpoints:\n      - \"endpoint_llama3\"\n\nvllm_endpoints:\n  - name: \"endpoint_llama3\"\n    address: \"172.28.0.20\"\n    port: 11434\n    weight: 1\n\nsemantic_cache:\n  enabled: False\n  backend_type: \"memory\"\n  similarity_threshold: 0.8\n  max_entries: 1000\n  ttl_seconds: 3600\n\nprompt_guard:\n  enabled: True\n  threshold: 0.6\n  use_modernbert: true\n\ntools:\n  enabled: True\n  top_k: 3\n  similarity_threshold: 0.2\n", "intent": "Route queries to llama3, using domain-based routing, with PII detection, with tools auto-selection, for istio deployment", "deployment_context": "istio", "source": "template", "values": {"decision_name": "business_decision", "model_name": "llama3", "signal_type": "domain", "category1": "support", "category2": "customer_service", "endpoint_address": "172.28.0.20", "endpoint_port": 11434, "endpoint_weight": 1, "cache_enabled": false, "cache_backend": "memory", "cache_threshold": 0.8, "guard_enabled": true, "guard_threshold": 0.6, "tools_enabled": true, "deployment_context": "istio"}}
{"id": "template_47512", "config": "# Semantic Router Configuration\n# Generated from template\n\ndecisions:\n  - name: \"business_decision\"\n    modelRefs:\n      - model: \"phi4\"\n        use_reasoning: true\n    signals:\n      - type: \"embedding\"\n        categories:\n          - \"business\"\n          - \"sales\"\n\nmodel_config:\n  phi4:\n    reasoning_family: \"phi4\"\n    preferred_endpoints:\n      - \"endpoint_phi4\"\n\nvllm_endpoints:\n  - name: \"endpoint_phi4\"\n    address: \"10.0.0.50\"\n    port: 8002\n    weight: 3\n\nsemantic_cache:\n  enabled: False\n  backend_type: \"redis\"\n  similarity_threshold: 0.8\n  max_entries: 1000\n  ttl_seconds: 3600\n\nprompt_guard:\n  enabled: True\n  threshold: 0.7\n  use_modernbert: true\n\ntools:\n  enabled: True\n  top_k: 3\n  similarity_threshold: 0.2\n", "intent": "Route queries to phi4, using embedding-based routing, with PII detection, with tools auto-selection, for istio deployment", "deployment_context": "istio", "source": "template", "values": {"decision_name": "business_decision", "model_name": "phi4", "signal_type": "embedding", "category1": "business", "category2": "sales", "endpoint_address": "10.0.0.50", "endpoint_port": 8002, "endpoint_weight": 3, "cache_enabled": false, "cache_backend": "redis", "cache_threshold": 0.8, "guard_enabled": true, "guard_threshold": 0.7, "tools_enabled": true, "deployment_context": "istio"}}
{"id": "template_90440", "config": "# Semantic Router Configuration\n# Generated from template\n\ndecisions:\n  - name: \"support_decision\"\n    modelRefs:\n      - model: \"mistral\"\n        use_reasoning: true\n    signals:\n      - type: \"embedding\"\n        categories:\n          - \"business\"\n          - \"engineering\"\n\nmodel_config:\n  mistral:\n    reasoning_family: \"mistral\"\n    preferred_endpoints:\n      - \"endpoint_mistral\"\n\nvllm_endpoints:\n  - name: \"endpoint_mistral\"\n    address: \"172.28.0.20\"\n    port: 8000\n    weight: 2\n\nsemantic_cache:\n  enabled: True\n  backend_type: \"milvus\"\n  similarity_threshold: 0.9\n  max_entries: 1000\n  ttl_seconds: 3600\n\nprompt_guard:\n  enabled: False\n  threshold: 0.7\n  use_modernbert: true\n\ntools:\n  enabled: True\n  top_k: 3\n  similarity_threshold: 0.2\n", "intent": "Route queries to mistral, using embedding-based routing, with milvus semantic cache, with tools auto-selection, for quickstart deployment", "deployment_context": "quickstart", "source": "template", "values": {"decision_name": "support_decision", "model_name": "mistral", "signal_type": "embedding", "category1": "business", "category2": "engineering", "endpoint_address": "172.28.0.20", "endpoint_port": 8000, "endpoint_weight": 2, "cache_enabled": true, "cache_backend": "milvus", "cache_threshold": 0.9, "guard_enabled": false, "guard_threshold": 0.7, "tools_enabled": true, "deployment_context": "quickstart"}}
{"id": "template_93117", "config": "# Semantic Router Configuration\n# Generated from template\n\ndecisions:\n  - name: \"technical_decision\"\n    modelRefs:\n      - model: \"mistral\"\n        use_reasoning: true\n    signals:\n      - type: \"keyword\"\n        categories:\n          - \"technical\"\n          - \"engineering\"\n\nmodel_config:\n  mistral:\n    reasoning_family: \"mistral\"\n    preferred_endpoints:\n      - \"endpoint_mistral\"\n\nvllm_endpoints:\n  - name: \"endpoint_mistral\"\n    address: \"172.16.0.10\"\n    port: 8002\n    weight: 3\n\nsemantic_cache:\n  enabled: False\n  backend_type: \"memory\"\n  similarity_threshold: 0.7\n  max_entries: 1000\n  ttl_seconds: 3600\n\nprompt_guard:\n  enabled: True\n  threshold: 0.6\n  use_modernbert: true\n\ntools:\n  enabled: True\n  top_k: 3\n  similarity_threshold: 0.2\n", "intent": "Route queries to mistral, using keyword-based routing, with PII detection, with tools auto-selection, for quickstart deployment", "deployment_context": "quickstart", "source": "template", "values": {"decision_name": "technical_decision", "model_name": "mistral", "signal_type": "keyword", "category1": "technical", "category2": "engineering", "endpoint_address": "172.16.0.10", "endpoint_port": 8002, "endpoint_weight": 3, "cache_enabled": false, "cache_backend": "memory", "cache_threshold": 0.7, "guard_enabled": true, "guard_threshold": 0.6, "tools_enabled": true, "deployment_context": "quickstart"}}
{"id": "template_11415", "config": "# Semantic Router Configuration\n# Generated from template\n\ndecisions:\n  - name: \"support_decision\"\n    modelRefs:\n      - model: \"qwen3\"\n        use_reasoning: true\n    signals:\n      - type: \"keyword\"\n        categories:\n          - \"business\"\n          - \"engineering\"\n\nmodel_config:\n  qwen3:\n    reasoning_family: \"qwen3\"\n    preferred_endpoints:\n      - \"endpoint_qwen3\"\n\nvllm_endpoints:\n  - name: \"endpoint_qwen3\"\n    address: \"172.16.0.10\"\n    port: 11434\n    weight: 2\n\nsemantic_cache:\n  enabled: False\n  backend_type: \"milvus\"\n  similarity_threshold: 0.9\n  max_entries: 1000\n  ttl_seconds: 3600\n\nprompt_guard:\n  enabled: False\n  threshold: 0.8\n  use_modernbert: true\n\ntools:\n  enabled: False\n  top_k: 3\n  similarity_threshold: 0.2\n", "intent": "Route queries to qwen3, using keyword-based routing, for istio deployment", "deployment_context": "istio", "source": "template", "values": {"decision_name": "support_decision", "model_name": "qwen3", "signal_type": "keyword", "category1": "business", "category2": "engineering", "endpoint_address": "172.16.0.10", "endpoint_port": 11434, "endpoint_weight": 2, "cache_enabled": false, "cache_backend": "milvus", "cache_threshold": 0.9, "guard_enabled": false, "guard_threshold": 0.8, "tools_enabled": false, "deployment_context": "istio"}}
{"id": "template_37032", "config": "# Semantic Router Configuration\n# Generated from template\n\ndecisions:\n  - name: \"technical_decision\"\n    modelRefs:\n      - model: \"mistral\"\n        use_reasoning: true\n    signals:\n      - type: \"embedding\"\n        categories:\n          - \"support\"\n          - \"finance\"\n\nmodel_config:\n  mistral:\n    reasoning_family: \"mistral\"\n    preferred_endpoints:\n      - \"endpoint_mistral\"\n\nvllm_endpoints:\n  - name: \"endpoint_mistral\"\n    address: \"192.168.1.100\"\n    port: 11434\n    weight: 3\n\nsemantic_cache:\n  enabled: False\n  backend_type: \"memory\"\n  similarity_threshold: 0.9\n  max_entries: 1000\n  ttl_seconds: 3600\n\nprompt_guard:\n  enabled: False\n  threshold: 0.7\n  use_modernbert: true\n\ntools:\n  enabled: False\n  top_k: 3\n  similarity_threshold: 0.2\n", "intent": "Route queries to mistral, using embedding-based routing, for kubernetes deployment", "deployment_context": "kubernetes", "source": "template", "values": {"decision_name": "technical_decision", "model_name": "mistral", "signal_type": "embedding", "category1": "support", "category2": "finance", "endpoint_address": "192.168.1.100", "endpoint_port": 11434, "endpoint_weight": 3, "cache_enabled": false, "cache_backend": "memory", "cache_threshold": 0.9, "guard_enabled": false, "guard_threshold": 0.7, "tools_enabled": false, "deployment_context": "kubernetes"}}
{"id": "template_99700", "config": "# Semantic Router Configuration\n# Generated from template\n\ndecisions:\n  - name: \"technical_decision\"\n    modelRefs:\n      - model: \"llama3\"\n        use_reasoning: true\n    signals:\n      - type: \"keyword\"\n        categories:\n          - \"technical\"\n          - \"engineering\"\n\nmodel_config:\n  llama3:\n    reasoning_family: \"llama3\"\n    preferred_endpoints:\n      - \"endpoint_llama3\"\n\nvllm_endpoints:\n  - name: \"endpoint_llama3\"\n    address: \"10.0.0.50\"\n    port: 8080\n    weight: 2\n\nsemantic_cache:\n  enabled: False\n  backend_type: \"redis\"\n  similarity_threshold: 0.8\n  max_entries: 1000\n  ttl_seconds: 3600\n\nprompt_guard:\n  enabled: True\n  threshold: 0.7\n  use_modernbert: true\n\ntools:\n  enabled: False\n  top_k: 3\n  similarity_threshold: 0.2\n", "intent": "Route queries to llama3, using keyword-based routing, with PII detection, for kubernetes deployment", "deployment_context": "kubernetes", "source": "template", "values": {"decision_name": "technical_decision", "model_name": "llama3", "signal_type": "keyword", "category1": "technical", "category2": "engineering", "endpoint_address": "10.0.0.50", "endpoint_port": 8080, "endpoint_weight": 2, "cache_enabled": false, "cache_backend": "redis", "cache_threshold": 0.8, "guard_enabled": true, "guard_threshold": 0.7, "tools_enabled": false, "deployment_context": "kubernetes"}}
{"id": "template_25915", "config": "# Semantic Router Configuration\n# Generated from template\n\ndecisions:\n  - name: \"technical_decision\"\n    modelRefs:\n      - model: \"qwen3\"\n        use_reasoning: true\n    signals:\n      - type: \"keyword\"\n        categories:\n          - \"support\"\n          - \"engineering\"\n\nmodel_config:\n  qwen3:\n    reasoning_family: \"qwen3\"\n    preferred_endpoints:\n      - \"endpoint_qwen3\"\n\nvllm_endpoints:\n  - name: \"endpoint_qwen3\"\n    address: \"192.168.1.100\"\n    port: 8002\n    weight: 2\n\nsemantic_cache:\n  enabled: False\n  backend_type: \"milvus\"\n  similarity_threshold: 0.7\n  max_entries: 1000\n  ttl_seconds: 3600\n\nprompt_guard:\n  enabled: True\n  threshold: 0.8\n  use_modernbert: true\n\ntools:\n  enabled: False\n  top_k: 3\n  similarity_threshold: 0.2\n", "intent": "Route queries to qwen3, using keyword-based routing, with PII detection, for kubernetes deployment", "deployment_context": "kubernetes", "source": "template", "values": {"decision_name": "technical_decision", "model_name": "qwen3", "signal_type": "keyword", "category1": "support", "category2": "engineering", "endpoint_address": "192.168.1.100", "endpoint_port": 8002, "endpoint_weight": 2, "cache_enabled": false, "cache_backend": "milvus", "cache_threshold": 0.7, "guard_enabled": true, "guard_threshold": 0.8, "tools_enabled": false, "deployment_context": "kubernetes"}}
{"id": "template_52601", "config": "# Semantic Router Configuration\n# Generated from template\n\ndecisions:\n  - name: \"general_decision\"\n    modelRefs:\n      - model: \"llama3\"\n        use_reasoning: true\n    signals:\n      - type: \"embedding\"\n        categories:\n          - \"general\"\n          - \"finance\"\n\nmodel_config:\n  llama3:\n    reasoning_family: \"llama3\"\n    preferred_endpoints:\n      - \"endpoint_llama3\"\n\nvllm_endpoints:\n  - name: \"endpoint_llama3\"\n    address: \"192.168.1.100\"\n    port: 8080\n    weight: 3\n\nsemantic_cache:\n  enabled: True\n  backend_type: \"memory\"\n  similarity_threshold: 0.7\n  max_entries: 1000\n  ttl_seconds: 3600\n\nprompt_guard:\n  enabled: True\n  threshold: 0.7\n  use_modernbert: true\n\ntools:\n  enabled: False\n  top_k: 3\n  similarity_threshold: 0.2\n", "intent": "Route queries to llama3, using embedding-based routing, with memory semantic cache, with PII detection, for kubernetes deployment", "deployment_context": "kubernetes", "source": "template", "values": {"decision_name": "general_decision", "model_name": "llama3", "signal_type": "embedding", "category1": "general", "category2": "finance", "endpoint_address": "192.168.1.100", "endpoint_port": 8080, "endpoint_weight": 3, "cache_enabled": true, "cache_backend": "memory", "cache_threshold": 0.7, "guard_enabled": true, "guard_threshold": 0.7, "tools_enabled": false, "deployment_context": "kubernetes"}}
{"id": "template_20976", "config": "# Semantic Router Configuration\n# Generated from template\n\ndecisions:\n  - name: \"business_decision\"\n    modelRefs:\n      - model: \"phi4\"\n        use_reasoning: true\n    signals:\n      - type: \"embedding\"\n        categories:\n          - \"support\"\n          - \"finance\"\n\nmodel_config:\n  phi4:\n    reasoning_family: \"phi4\"\n    preferred_endpoints:\n      - \"endpoint_phi4\"\n\nvllm_endpoints:\n  - name: \"endpoint_phi4\"\n    address: \"172.28.0.20\"\n    port: 8080\n    weight: 3\n\nsemantic_cache:\n  enabled: True\n  backend_type: \"memory\"\n  similarity_threshold: 0.8\n  max_entries: 1000\n  ttl_seconds: 3600\n\nprompt_guard:\n  enabled: True\n  threshold: 0.6\n  use_modernbert: true\n\ntools:\n  enabled: True\n  top_k: 3\n  similarity_threshold: 0.2\n", "intent": "Route queries to phi4, using embedding-based routing, with memory semantic cache, with PII detection, with tools auto-selection, for istio deployment", "deployment_context": "istio", "source": "template", "values": {"decision_name": "business_decision", "model_name": "phi4", "signal_type": "embedding", "category1": "support", "category2": "finance", "endpoint_address": "172.28.0.20", "endpoint_port": 8080, "endpoint_weight": 3, "cache_enabled": true, "cache_backend": "memory", "cache_threshold": 0.8, "guard_enabled": true, "guard_threshold": 0.6, "tools_enabled": true, "deployment_context": "istio"}}
{"id": "template_25511", "config": "# Semantic Router Configuration\n# Generated from template\n\ndecisions:\n  - name: \"support_decision\"\n    modelRefs:\n      - model: \"phi4\"\n        use_reasoning: true\n    signals:\n      - type: \"keyword\"\n        categories:\n          - \"general\"\n          - \"sales\"\n\nmodel_config:\n  phi4:\n    reasoning_family: \"phi4\"\n    preferred_endpoints:\n      - \"endpoint_phi4\"\n\nvllm_endpoints:\n  - name: \"endpoint_phi4\"\n    address: \"172.16.0.10\"\n    port: 8002\n    weight: 2\n\nsemantic_cache:\n  enabled: False\n  backend_type: \"redis\"\n  similarity_threshold: 0.9\n  max_entries: 1000\n  ttl_seconds: 3600\n\nprompt_guard:\n  enabled: True\n  threshold: 0.7\n  use_modernbert: true\n\ntools:\n  enabled: True\n  top_k: 3\n  similarity_threshold: 0.2\n", "intent": "Route queries to phi4, using keyword-based routing, with PII detection, with tools auto-selection, for kubernetes deployment", "deployment_context": "kubernetes", "source": "template", "values": {"decision_name": "support_decision", "model_name": "phi4", "signal_type": "keyword", "category1": "general", "category2": "sales", "endpoint_address": "172.16.0.10", "endpoint_port": 8002, "endpoint_weight": 2, "cache_enabled": false, "cache_backend": "redis", "cache_threshold": 0.9, "guard_enabled": true, "guard_threshold": 0.7, "tools_enabled": true, "deployment_context": "kubernetes"}}
{"id": "template_27822", "config": "# Semantic Router Configuration\n# Generated from template\n\ndecisions:\n  - name: \"general_decision\"\n    modelRefs:\n      - model: \"mistral\"\n        use_reasoning: true\n    signals:\n      - type: \"keyword\"\n        categories:\n          - \"general\"\n          - \"finance\"\n\nmodel_config:\n  mistral:\n    reasoning_family: \"mistral\"\n    preferred_endpoints:\n      - \"endpoint_mistral\"\n\nvllm_endpoints:\n  - name: \"endpoint_mistral\"\n    address: \"10.0.0.50\"\n    port: 8000\n    weight: 3\n\nsemantic_cache:\n  enabled: True\n  backend_type: \"milvus\"\n  similarity_threshold: 0.7\n  max_entries: 1000\n  ttl_seconds: 3600\n\nprompt_guard:\n  enabled: False\n  threshold: 0.6\n  use_modernbert: true\n\ntools:\n  enabled: False\n  top_k: 3\n  similarity_threshold: 0.2\n", "intent": "Route queries to mistral, using keyword-based routing, with milvus semantic cache, for kubernetes deployment", "deployment_context": "kubernetes", "source": "template", "values": {"decision_name": "general_decision", "model_name": "mistral", "signal_type": "keyword", "category1": "general", "category2": "finance", "endpoint_address": "10.0.0.50", "endpoint_port": 8000, "endpoint_weight": 3, "cache_enabled": true, "cache_backend": "milvus", "cache_threshold": 0.7, "guard_enabled": false, "guard_threshold": 0.6, "tools_enabled": false, "deployment_context": "kubernetes"}}
{"id": "template_52543", "config": "# Semantic Router Configuration\n# Generated from template\n\ndecisions:\n  - name: \"technical_decision\"\n    modelRefs:\n      - model: \"phi4\"\n        use_reasoning: true\n    signals:\n      - type: \"domain\"\n        categories:\n          - \"general\"\n          - \"engineering\"\n\nmodel_config:\n  phi4:\n    reasoning_family: \"phi4\"\n    preferred_endpoints:\n      - \"endpoint_phi4\"\n\nvllm_endpoints:\n  - name: \"endpoint_phi4\"\n    address: \"10.0.0.50\"\n    port: 8002\n    weight: 3\n\nsemantic_cache:\n  enabled: True\n  backend_type: \"milvus\"\n  similarity_threshold: 0.9\n  max_entries: 1000\n  ttl_seconds: 3600\n\nprompt_guard:\n  enabled: True\n  threshold: 0.8\n  use_modernbert: true\n\ntools:\n  enabled: False\n  top_k: 3\n  similarity_threshold: 0.2\n", "intent": "Route queries to phi4, using domain-based routing, with milvus semantic cache, with PII detection, for ai-gateway deployment", "deployment_context": "ai-gateway", "source": "template", "values": {"decision_name": "technical_decision", "model_name": "phi4", "signal_type": "domain", "category1": "general", "category2": "engineering", "endpoint_address": "10.0.0.50", "endpoint_port": 8002, "endpoint_weight": 3, "cache_enabled": true, "cache_backend": "milvus", "cache_threshold": 0.9, "guard_enabled": true, "guard_threshold": 0.8, "tools_enabled": false, "deployment_context": "ai-gateway"}}
{"id": "template_18754", "config": "# Semantic Router Configuration\n# Generated from template\n\ndecisions:\n  - name: \"support_decision\"\n    modelRefs:\n      - model: \"llama3\"\n        use_reasoning: true\n    signals:\n      - type: \"embedding\"\n        categories:\n          - \"general\"\n          - \"finance\"\n\nmodel_config:\n  llama3:\n    reasoning_family: \"llama3\"\n    preferred_endpoints:\n      - \"endpoint_llama3\"\n\nvllm_endpoints:\n  - name: \"endpoint_llama3\"\n    address: \"10.0.0.50\"\n    port: 8000\n    weight: 1\n\nsemantic_cache:\n  enabled: False\n  backend_type: \"milvus\"\n  similarity_threshold: 0.9\n  max_entries: 1000\n  ttl_seconds: 3600\n\nprompt_guard:\n  enabled: True\n  threshold: 0.8\n  use_modernbert: true\n\ntools:\n  enabled: True\n  top_k: 3\n  similarity_threshold: 0.2\n", "intent": "Route queries to llama3, using embedding-based routing, with PII detection, with tools auto-selection, for quickstart deployment", "deployment_context": "quickstart", "source": "template", "values": {"decision_name": "support_decision", "model_name": "llama3", "signal_type": "embedding", "category1": "general", "category2": "finance", "endpoint_address": "10.0.0.50", "endpoint_port": 8000, "endpoint_weight": 1, "cache_enabled": false, "cache_backend": "milvus", "cache_threshold": 0.9, "guard_enabled": true, "guard_threshold": 0.8, "tools_enabled": true, "deployment_context": "quickstart"}}
{"id": "template_11893", "config": "# Semantic Router Configuration\n# Generated from template\n\ndecisions:\n  - name: \"business_decision\"\n    modelRefs:\n      - model: \"qwen3\"\n        use_reasoning: true\n    signals:\n      - type: \"keyword\"\n        categories:\n          - \"general\"\n          - \"sales\"\n\nmodel_config:\n  qwen3:\n    reasoning_family: \"qwen3\"\n    preferred_endpoints:\n      - \"endpoint_qwen3\"\n\nvllm_endpoints:\n  - name: \"endpoint_qwen3\"\n    address: \"10.0.0.50\"\n    port: 8080\n    weight: 1\n\nsemantic_cache:\n  enabled: True\n  backend_type: \"milvus\"\n  similarity_threshold: 0.7\n  max_entries: 1000\n  ttl_seconds: 3600\n\nprompt_guard:\n  enabled: True\n  threshold: 0.8\n  use_modernbert: true\n\ntools:\n  enabled: True\n  top_k: 3\n  similarity_threshold: 0.2\n", "intent": "Route queries to qwen3, using keyword-based routing, with milvus semantic cache, with PII detection, with tools auto-selection, for istio deployment", "deployment_context": "istio", "source": "template", "values": {"decision_name": "business_decision", "model_name": "qwen3", "signal_type": "keyword", "category1": "general", "category2": "sales", "endpoint_address": "10.0.0.50", "endpoint_port": 8080, "endpoint_weight": 1, "cache_enabled": true, "cache_backend": "milvus", "cache_threshold": 0.7, "guard_enabled": true, "guard_threshold": 0.8, "tools_enabled": true, "deployment_context": "istio"}}
{"id": "template_63522", "config": "# Semantic Router Configuration\n# Generated from template\n\ndecisions:\n  - name: \"technical_decision\"\n    modelRefs:\n      - model: \"mistral\"\n        use_reasoning: true\n    signals:\n      - type: \"embedding\"\n        categories:\n          - \"support\"\n          - \"engineering\"\n\nmodel_config:\n  mistral:\n    reasoning_family: \"mistral\"\n    preferred_endpoints:\n      - \"endpoint_mistral\"\n\nvllm_endpoints:\n  - name: \"endpoint_mistral\"\n    address: \"192.168.1.100\"\n    port: 11434\n    weight: 2\n\nsemantic_cache:\n  enabled: True\n  backend_type: \"memory\"\n  similarity_threshold: 0.9\n  max_entries: 1000\n  ttl_seconds: 3600\n\nprompt_guard:\n  enabled: False\n  threshold: 0.8\n  use_modernbert: true\n\ntools:\n  enabled: False\n  top_k: 3\n  similarity_threshold: 0.2\n", "intent": "Route queries to mistral, using embedding-based routing, with memory semantic cache, for ai-gateway deployment", "deployment_context": "ai-gateway", "source": "template", "values": {"decision_name": "technical_decision", "model_name": "mistral", "signal_type": "embedding", "category1": "support", "category2": "engineering", "endpoint_address": "192.168.1.100", "endpoint_port": 11434, "endpoint_weight": 2, "cache_enabled": true, "cache_backend": "memory", "cache_threshold": 0.9, "guard_enabled": false, "guard_threshold": 0.8, "tools_enabled": false, "deployment_context": "ai-gateway"}}
{"id": "template_46177", "config": "# Semantic Router Configuration\n# Generated from template\n\ndecisions:\n  - name: \"technical_decision\"\n    modelRefs:\n      - model: \"llama3\"\n        use_reasoning: true\n    signals:\n      - type: \"domain\"\n        categories:\n          - \"support\"\n          - \"finance\"\n\nmodel_config:\n  llama3:\n    reasoning_family: \"llama3\"\n    preferred_endpoints:\n      - \"endpoint_llama3\"\n\nvllm_endpoints:\n  - name: \"endpoint_llama3\"\n    address: \"192.168.1.100\"\n    port: 8080\n    weight: 3\n\nsemantic_cache:\n  enabled: True\n  backend_type: \"redis\"\n  similarity_threshold: 0.8\n  max_entries: 1000\n  ttl_seconds: 3600\n\nprompt_guard:\n  enabled: False\n  threshold: 0.6\n  use_modernbert: true\n\ntools:\n  enabled: True\n  top_k: 3\n  similarity_threshold: 0.2\n", "intent": "Route queries to llama3, using domain-based routing, with redis semantic cache, with tools auto-selection, for istio deployment", "deployment_context": "istio", "source": "template", "values": {"decision_name": "technical_decision", "model_name": "llama3", "signal_type": "domain", "category1": "support", "category2": "finance", "endpoint_address": "192.168.1.100", "endpoint_port": 8080, "endpoint_weight": 3, "cache_enabled": true, "cache_backend": "redis", "cache_threshold": 0.8, "guard_enabled": false, "guard_threshold": 0.6, "tools_enabled": true, "deployment_context": "istio"}}
{"id": "template_80088", "config": "# Semantic Router Configuration\n# Generated from template\n\ndecisions:\n  - name: \"support_decision\"\n    modelRefs:\n      - model: \"qwen3\"\n        use_reasoning: true\n    signals:\n      - type: \"embedding\"\n        categories:\n          - \"business\"\n          - \"finance\"\n\nmodel_config:\n  qwen3:\n    reasoning_family: \"qwen3\"\n    preferred_endpoints:\n      - \"endpoint_qwen3\"\n\nvllm_endpoints:\n  - name: \"endpoint_qwen3\"\n    address: \"192.168.1.100\"\n    port: 8002\n    weight: 3\n\nsemantic_cache:\n  enabled: True\n  backend_type: \"milvus\"\n  similarity_threshold: 0.9\n  max_entries: 1000\n  ttl_seconds: 3600\n\nprompt_guard:\n  enabled: False\n  threshold: 0.8\n  use_modernbert: true\n\ntools:\n  enabled: True\n  top_k: 3\n  similarity_threshold: 0.2\n", "intent": "Route queries to qwen3, using embedding-based routing, with milvus semantic cache, with tools auto-selection, for quickstart deployment", "deployment_context": "quickstart", "source": "template", "values": {"decision_name": "support_decision", "model_name": "qwen3", "signal_type": "embedding", "category1": "business", "category2": "finance", "endpoint_address": "192.168.1.100", "endpoint_port": 8002, "endpoint_weight": 3, "cache_enabled": true, "cache_backend": "milvus", "cache_threshold": 0.9, "guard_enabled": false, "guard_threshold": 0.8, "tools_enabled": true, "deployment_context": "quickstart"}}
{"id": "template_46266", "config": "# Semantic Router Configuration\n# Generated from template\n\ndecisions:\n  - name: \"general_decision\"\n    modelRefs:\n      - model: \"mistral\"\n        use_reasoning: true\n    signals:\n      - type: \"embedding\"\n        categories:\n          - \"technical\"\n          - \"customer_service\"\n\nmodel_config:\n  mistral:\n    reasoning_family: \"mistral\"\n    preferred_endpoints:\n      - \"endpoint_mistral\"\n\nvllm_endpoints:\n  - name: \"endpoint_mistral\"\n    address: \"172.16.0.10\"\n    port: 11434\n    weight: 2\n\nsemantic_cache:\n  enabled: False\n  backend_type: \"milvus\"\n  similarity_threshold: 0.9\n  max_entries: 1000\n  ttl_seconds: 3600\n\nprompt_guard:\n  enabled: True\n  threshold: 0.7\n  use_modernbert: true\n\ntools:\n  enabled: True\n  top_k: 3\n  similarity_threshold: 0.2\n", "intent": "Route queries to mistral, using embedding-based routing, with PII detection, with tools auto-selection, for ai-gateway deployment", "deployment_context": "ai-gateway", "source": "template", "values": {"decision_name": "general_decision", "model_name": "mistral", "signal_type": "embedding", "category1": "technical", "category2": "customer_service", "endpoint_address": "172.16.0.10", "endpoint_port": 11434, "endpoint_weight": 2, "cache_enabled": false, "cache_backend": "milvus", "cache_threshold": 0.9, "guard_enabled": true, "guard_threshold": 0.7, "tools_enabled": true, "deployment_context": "ai-gateway"}}
{"id": "template_46566", "config": "# Semantic Router Configuration\n# Generated from template\n\ndecisions:\n  - name: \"business_decision\"\n    modelRefs:\n      - model: \"phi4\"\n        use_reasoning: true\n    signals:\n      - type: \"keyword\"\n        categories:\n          - \"technical\"\n          - \"engineering\"\n\nmodel_config:\n  phi4:\n    reasoning_family: \"phi4\"\n    preferred_endpoints:\n      - \"endpoint_phi4\"\n\nvllm_endpoints:\n  - name: \"endpoint_phi4\"\n    address: \"192.168.1.100\"\n    port: 8080\n    weight: 3\n\nsemantic_cache:\n  enabled: True\n  backend_type: \"milvus\"\n  similarity_threshold: 0.8\n  max_entries: 1000\n  ttl_seconds: 3600\n\nprompt_guard:\n  enabled: True\n  threshold: 0.7\n  use_modernbert: true\n\ntools:\n  enabled: False\n  top_k: 3\n  similarity_threshold: 0.2\n", "intent": "Route queries to phi4, using keyword-based routing, with milvus semantic cache, with PII detection, for quickstart deployment", "deployment_context": "quickstart", "source": "template", "values": {"decision_name": "business_decision", "model_name": "phi4", "signal_type": "keyword", "category1": "technical", "category2": "engineering", "endpoint_address": "192.168.1.100", "endpoint_port": 8080, "endpoint_weight": 3, "cache_enabled": true, "cache_backend": "milvus", "cache_threshold": 0.8, "guard_enabled": true, "guard_threshold": 0.7, "tools_enabled": false, "deployment_context": "quickstart"}}
{"id": "template_61942", "config": "# Semantic Router Configuration\n# Generated from template\n\ndecisions:\n  - name: \"general_decision\"\n    modelRefs:\n      - model: \"phi4\"\n        use_reasoning: true\n    signals:\n      - type: \"embedding\"\n        categories:\n          - \"technical\"\n          - \"customer_service\"\n\nmodel_config:\n  phi4:\n    reasoning_family: \"phi4\"\n    preferred_endpoints:\n      - \"endpoint_phi4\"\n\nvllm_endpoints:\n  - name: \"endpoint_phi4\"\n    address: \"10.0.0.50\"\n    port: 8080\n    weight: 3\n\nsemantic_cache:\n  enabled: False\n  backend_type: \"memory\"\n  similarity_threshold: 0.8\n  max_entries: 1000\n  ttl_seconds: 3600\n\nprompt_guard:\n  enabled: True\n  threshold: 0.8\n  use_modernbert: true\n\ntools:\n  enabled: False\n  top_k: 3\n  similarity_threshold: 0.2\n", "intent": "Route queries to phi4, using embedding-based routing, with PII detection, for ai-gateway deployment", "deployment_context": "ai-gateway", "source": "template", "values": {"decision_name": "general_decision", "model_name": "phi4", "signal_type": "embedding", "category1": "technical", "category2": "customer_service", "endpoint_address": "10.0.0.50", "endpoint_port": 8080, "endpoint_weight": 3, "cache_enabled": false, "cache_backend": "memory", "cache_threshold": 0.8, "guard_enabled": true, "guard_threshold": 0.8, "tools_enabled": false, "deployment_context": "ai-gateway"}}
{"id": "template_57221", "config": "# Semantic Router Configuration\n# Generated from template\n\ndecisions:\n  - name: \"general_decision\"\n    modelRefs:\n      - model: \"llama3\"\n        use_reasoning: true\n    signals:\n      - type: \"embedding\"\n        categories:\n          - \"business\"\n          - \"engineering\"\n\nmodel_config:\n  llama3:\n    reasoning_family: \"llama3\"\n    preferred_endpoints:\n      - \"endpoint_llama3\"\n\nvllm_endpoints:\n  - name: \"endpoint_llama3\"\n    address: \"172.16.0.10\"\n    port: 8000\n    weight: 2\n\nsemantic_cache:\n  enabled: False\n  backend_type: \"redis\"\n  similarity_threshold: 0.8\n  max_entries: 1000\n  ttl_seconds: 3600\n\nprompt_guard:\n  enabled: True\n  threshold: 0.8\n  use_modernbert: true\n\ntools:\n  enabled: False\n  top_k: 3\n  similarity_threshold: 0.2\n", "intent": "Route queries to llama3, using embedding-based routing, with PII detection, for quickstart deployment", "deployment_context": "quickstart", "source": "template", "values": {"decision_name": "general_decision", "model_name": "llama3", "signal_type": "embedding", "category1": "business", "category2": "engineering", "endpoint_address": "172.16.0.10", "endpoint_port": 8000, "endpoint_weight": 2, "cache_enabled": false, "cache_backend": "redis", "cache_threshold": 0.8, "guard_enabled": true, "guard_threshold": 0.8, "tools_enabled": false, "deployment_context": "quickstart"}}
{"id": "template_47277", "config": "# Semantic Router Configuration\n# Generated from template\n\ndecisions:\n  - name: \"technical_decision\"\n    modelRefs:\n      - model: \"phi4\"\n        use_reasoning: true\n    signals:\n      - type: \"embedding\"\n        categories:\n          - \"business\"\n          - \"engineering\"\n\nmodel_config:\n  phi4:\n    reasoning_family: \"phi4\"\n    preferred_endpoints:\n      - \"endpoint_phi4\"\n\nvllm_endpoints:\n  - name: \"endpoint_phi4\"\n    address: \"172.28.0.20\"\n    port: 11434\n    weight: 2\n\nsemantic_cache:\n  enabled: True\n  backend_type: \"milvus\"\n  similarity_threshold: 0.7\n  max_entries: 1000\n  ttl_seconds: 3600\n\nprompt_guard:\n  enabled: False\n  threshold: 0.6\n  use_modernbert: true\n\ntools:\n  enabled: True\n  top_k: 3\n  similarity_threshold: 0.2\n", "intent": "Route queries to phi4, using embedding-based routing, with milvus semantic cache, with tools auto-selection, for ai-gateway deployment", "deployment_context": "ai-gateway", "source": "template", "values": {"decision_name": "technical_decision", "model_name": "phi4", "signal_type": "embedding", "category1": "business", "category2": "engineering", "endpoint_address": "172.28.0.20", "endpoint_port": 11434, "endpoint_weight": 2, "cache_enabled": true, "cache_backend": "milvus", "cache_threshold": 0.7, "guard_enabled": false, "guard_threshold": 0.6, "tools_enabled": true, "deployment_context": "ai-gateway"}}
{"id": "template_44698", "config": "# Semantic Router Configuration\n# Generated from template\n\ndecisions:\n  - name: \"business_decision\"\n    modelRefs:\n      - model: \"phi4\"\n        use_reasoning: true\n    signals:\n      - type: \"embedding\"\n        categories:\n          - \"business\"\n          - \"customer_service\"\n\nmodel_config:\n  phi4:\n    reasoning_family: \"phi4\"\n    preferred_endpoints:\n      - \"endpoint_phi4\"\n\nvllm_endpoints:\n  - name: \"endpoint_phi4\"\n    address: \"10.0.0.50\"\n    port: 8002\n    weight: 3\n\nsemantic_cache:\n  enabled: True\n  backend_type: \"memory\"\n  similarity_threshold: 0.8\n  max_entries: 1000\n  ttl_seconds: 3600\n\nprompt_guard:\n  enabled: True\n  threshold: 0.6\n  use_modernbert: true\n\ntools:\n  enabled: False\n  top_k: 3\n  similarity_threshold: 0.2\n", "intent": "Route queries to phi4, using embedding-based routing, with memory semantic cache, with PII detection, for quickstart deployment", "deployment_context": "quickstart", "source": "template", "values": {"decision_name": "business_decision", "model_name": "phi4", "signal_type": "embedding", "category1": "business", "category2": "customer_service", "endpoint_address": "10.0.0.50", "endpoint_port": 8002, "endpoint_weight": 3, "cache_enabled": true, "cache_backend": "memory", "cache_threshold": 0.8, "guard_enabled": true, "guard_threshold": 0.6, "tools_enabled": false, "deployment_context": "quickstart"}}
{"id": "template_5991", "config": "# Semantic Router Configuration\n# Generated from template\n\ndecisions:\n  - name: \"technical_decision\"\n    modelRefs:\n      - model: \"llama3\"\n        use_reasoning: true\n    signals:\n      - type: \"domain\"\n        categories:\n          - \"general\"\n          - \"engineering\"\n\nmodel_config:\n  llama3:\n    reasoning_family: \"llama3\"\n    preferred_endpoints:\n      - \"endpoint_llama3\"\n\nvllm_endpoints:\n  - name: \"endpoint_llama3\"\n    address: \"192.168.1.100\"\n    port: 11434\n    weight: 3\n\nsemantic_cache:\n  enabled: False\n  backend_type: \"redis\"\n  similarity_threshold: 0.7\n  max_entries: 1000\n  ttl_seconds: 3600\n\nprompt_guard:\n  enabled: True\n  threshold: 0.7\n  use_modernbert: true\n\ntools:\n  enabled: True\n  top_k: 3\n  similarity_threshold: 0.2\n", "intent": "Route queries to llama3, using domain-based routing, with PII detection, with tools auto-selection, for istio deployment", "deployment_context": "istio", "source": "template", "values": {"decision_name": "technical_decision", "model_name": "llama3", "signal_type": "domain", "category1": "general", "category2": "engineering", "endpoint_address": "192.168.1.100", "endpoint_port": 11434, "endpoint_weight": 3, "cache_enabled": false, "cache_backend": "redis", "cache_threshold": 0.7, "guard_enabled": true, "guard_threshold": 0.7, "tools_enabled": true, "deployment_context": "istio"}}
{"id": "template_19599", "config": "# Semantic Router Configuration\n# Generated from template\n\ndecisions:\n  - name: \"support_decision\"\n    modelRefs:\n      - model: \"phi4\"\n        use_reasoning: true\n    signals:\n      - type: \"domain\"\n        categories:\n          - \"business\"\n          - \"sales\"\n\nmodel_config:\n  phi4:\n    reasoning_family: \"phi4\"\n    preferred_endpoints:\n      - \"endpoint_phi4\"\n\nvllm_endpoints:\n  - name: \"endpoint_phi4\"\n    address: \"192.168.1.100\"\n    port: 8002\n    weight: 1\n\nsemantic_cache:\n  enabled: False\n  backend_type: \"memory\"\n  similarity_threshold: 0.9\n  max_entries: 1000\n  ttl_seconds: 3600\n\nprompt_guard:\n  enabled: False\n  threshold: 0.8\n  use_modernbert: true\n\ntools:\n  enabled: False\n  top_k: 3\n  similarity_threshold: 0.2\n", "intent": "Route queries to phi4, using domain-based routing, for kubernetes deployment", "deployment_context": "kubernetes", "source": "template", "values": {"decision_name": "support_decision", "model_name": "phi4", "signal_type": "domain", "category1": "business", "category2": "sales", "endpoint_address": "192.168.1.100", "endpoint_port": 8002, "endpoint_weight": 1, "cache_enabled": false, "cache_backend": "memory", "cache_threshold": 0.9, "guard_enabled": false, "guard_threshold": 0.8, "tools_enabled": false, "deployment_context": "kubernetes"}}
{"id": "template_20560", "config": "# Semantic Router Configuration\n# Generated from template\n\ndecisions:\n  - name: \"general_decision\"\n    modelRefs:\n      - model: \"mistral\"\n        use_reasoning: true\n    signals:\n      - type: \"domain\"\n        categories:\n          - \"general\"\n          - \"sales\"\n\nmodel_config:\n  mistral:\n    reasoning_family: \"mistral\"\n    preferred_endpoints:\n      - \"endpoint_mistral\"\n\nvllm_endpoints:\n  - name: \"endpoint_mistral\"\n    address: \"172.28.0.20\"\n    port: 11434\n    weight: 1\n\nsemantic_cache:\n  enabled: False\n  backend_type: \"memory\"\n  similarity_threshold: 0.8\n  max_entries: 1000\n  ttl_seconds: 3600\n\nprompt_guard:\n  enabled: False\n  threshold: 0.8\n  use_modernbert: true\n\ntools:\n  enabled: True\n  top_k: 3\n  similarity_threshold: 0.2\n", "intent": "Route queries to mistral, using domain-based routing, with tools auto-selection, for kubernetes deployment", "deployment_context": "kubernetes", "source": "template", "values": {"decision_name": "general_decision", "model_name": "mistral", "signal_type": "domain", "category1": "general", "category2": "sales", "endpoint_address": "172.28.0.20", "endpoint_port": 11434, "endpoint_weight": 1, "cache_enabled": false, "cache_backend": "memory", "cache_threshold": 0.8, "guard_enabled": false, "guard_threshold": 0.8, "tools_enabled": true, "deployment_context": "kubernetes"}}
{"id": "template_64190", "config": "# Semantic Router Configuration\n# Generated from template\n\ndecisions:\n  - name: \"general_decision\"\n    modelRefs:\n      - model: \"mistral\"\n        use_reasoning: true\n    signals:\n      - type: \"keyword\"\n        categories:\n          - \"technical\"\n          - \"engineering\"\n\nmodel_config:\n  mistral:\n    reasoning_family: \"mistral\"\n    preferred_endpoints:\n      - \"endpoint_mistral\"\n\nvllm_endpoints:\n  - name: \"endpoint_mistral\"\n    address: \"10.0.0.50\"\n    port: 8002\n    weight: 1\n\nsemantic_cache:\n  enabled: False\n  backend_type: \"milvus\"\n  similarity_threshold: 0.7\n  max_entries: 1000\n  ttl_seconds: 3600\n\nprompt_guard:\n  enabled: False\n  threshold: 0.7\n  use_modernbert: true\n\ntools:\n  enabled: True\n  top_k: 3\n  similarity_threshold: 0.2\n", "intent": "Route queries to mistral, using keyword-based routing, with tools auto-selection, for kubernetes deployment", "deployment_context": "kubernetes", "source": "template", "values": {"decision_name": "general_decision", "model_name": "mistral", "signal_type": "keyword", "category1": "technical", "category2": "engineering", "endpoint_address": "10.0.0.50", "endpoint_port": 8002, "endpoint_weight": 1, "cache_enabled": false, "cache_backend": "milvus", "cache_threshold": 0.7, "guard_enabled": false, "guard_threshold": 0.7, "tools_enabled": true, "deployment_context": "kubernetes"}}
{"id": "template_16398", "config": "# Semantic Router Configuration\n# Generated from template\n\ndecisions:\n  - name: \"technical_decision\"\n    modelRefs:\n      - model: \"phi4\"\n        use_reasoning: true\n    signals:\n      - type: \"keyword\"\n        categories:\n          - \"support\"\n          - \"customer_service\"\n\nmodel_config:\n  phi4:\n    reasoning_family: \"phi4\"\n    preferred_endpoints:\n      - \"endpoint_phi4\"\n\nvllm_endpoints:\n  - name: \"endpoint_phi4\"\n    address: \"10.0.0.50\"\n    port: 8000\n    weight: 3\n\nsemantic_cache:\n  enabled: False\n  backend_type: \"milvus\"\n  similarity_threshold: 0.7\n  max_entries: 1000\n  ttl_seconds: 3600\n\nprompt_guard:\n  enabled: False\n  threshold: 0.7\n  use_modernbert: true\n\ntools:\n  enabled: True\n  top_k: 3\n  similarity_threshold: 0.2\n", "intent": "Route queries to phi4, using keyword-based routing, with tools auto-selection, for kubernetes deployment", "deployment_context": "kubernetes", "source": "template", "values": {"decision_name": "technical_decision", "model_name": "phi4", "signal_type": "keyword", "category1": "support", "category2": "customer_service", "endpoint_address": "10.0.0.50", "endpoint_port": 8000, "endpoint_weight": 3, "cache_enabled": false, "cache_backend": "milvus", "cache_threshold": 0.7, "guard_enabled": false, "guard_threshold": 0.7, "tools_enabled": true, "deployment_context": "kubernetes"}}
{"id": "template_16367", "config": "# Semantic Router Configuration\n# Generated from template\n\ndecisions:\n  - name: \"general_decision\"\n    modelRefs:\n      - model: \"qwen3\"\n        use_reasoning: true\n    signals:\n      - type: \"embedding\"\n        categories:\n          - \"support\"\n          - \"customer_service\"\n\nmodel_config:\n  qwen3:\n    reasoning_family: \"qwen3\"\n    preferred_endpoints:\n      - \"endpoint_qwen3\"\n\nvllm_endpoints:\n  - name: \"endpoint_qwen3\"\n    address: \"10.0.0.50\"\n    port: 8000\n    weight: 1\n\nsemantic_cache:\n  enabled: False\n  backend_type: \"milvus\"\n  similarity_threshold: 0.7\n  max_entries: 1000\n  ttl_seconds: 3600\n\nprompt_guard:\n  enabled: False\n  threshold: 0.7\n  use_modernbert: true\n\ntools:\n  enabled: False\n  top_k: 3\n  similarity_threshold: 0.2\n", "intent": "Route queries to qwen3, using embedding-based routing, for ai-gateway deployment", "deployment_context": "ai-gateway", "source": "template", "values": {"decision_name": "general_decision", "model_name": "qwen3", "signal_type": "embedding", "category1": "support", "category2": "customer_service", "endpoint_address": "10.0.0.50", "endpoint_port": 8000, "endpoint_weight": 1, "cache_enabled": false, "cache_backend": "milvus", "cache_threshold": 0.7, "guard_enabled": false, "guard_threshold": 0.7, "tools_enabled": false, "deployment_context": "ai-gateway"}}
{"id": "template_16990", "config": "# Semantic Router Configuration\n# Generated from template\n\ndecisions:\n  - name: \"general_decision\"\n    modelRefs:\n      - model: \"phi4\"\n        use_reasoning: true\n    signals:\n      - type: \"embedding\"\n        categories:\n          - \"business\"\n          - \"finance\"\n\nmodel_config:\n  phi4:\n    reasoning_family: \"phi4\"\n    preferred_endpoints:\n      - \"endpoint_phi4\"\n\nvllm_endpoints:\n  - name: \"endpoint_phi4\"\n    address: \"10.0.0.50\"\n    port: 11434\n    weight: 2\n\nsemantic_cache:\n  enabled: True\n  backend_type: \"redis\"\n  similarity_threshold: 0.9\n  max_entries: 1000\n  ttl_seconds: 3600\n\nprompt_guard:\n  enabled: False\n  threshold: 0.8\n  use_modernbert: true\n\ntools:\n  enabled: False\n  top_k: 3\n  similarity_threshold: 0.2\n", "intent": "Route queries to phi4, using embedding-based routing, with redis semantic cache, for istio deployment", "deployment_context": "istio", "source": "template", "values": {"decision_name": "general_decision", "model_name": "phi4", "signal_type": "embedding", "category1": "business", "category2": "finance", "endpoint_address": "10.0.0.50", "endpoint_port": 11434, "endpoint_weight": 2, "cache_enabled": true, "cache_backend": "redis", "cache_threshold": 0.9, "guard_enabled": false, "guard_threshold": 0.8, "tools_enabled": false, "deployment_context": "istio"}}
{"id": "template_27081", "config": "# Semantic Router Configuration\n# Generated from template\n\ndecisions:\n  - name: \"business_decision\"\n    modelRefs:\n      - model: \"phi4\"\n        use_reasoning: true\n    signals:\n      - type: \"domain\"\n        categories:\n          - \"technical\"\n          - \"sales\"\n\nmodel_config:\n  phi4:\n    reasoning_family: \"phi4\"\n    preferred_endpoints:\n      - \"endpoint_phi4\"\n\nvllm_endpoints:\n  - name: \"endpoint_phi4\"\n    address: \"172.28.0.20\"\n    port: 8000\n    weight: 3\n\nsemantic_cache:\n  enabled: True\n  backend_type: \"milvus\"\n  similarity_threshold: 0.7\n  max_entries: 1000\n  ttl_seconds: 3600\n\nprompt_guard:\n  enabled: False\n  threshold: 0.8\n  use_modernbert: true\n\ntools:\n  enabled: False\n  top_k: 3\n  similarity_threshold: 0.2\n", "intent": "Route queries to phi4, using domain-based routing, with milvus semantic cache, for quickstart deployment", "deployment_context": "quickstart", "source": "template", "values": {"decision_name": "business_decision", "model_name": "phi4", "signal_type": "domain", "category1": "technical", "category2": "sales", "endpoint_address": "172.28.0.20", "endpoint_port": 8000, "endpoint_weight": 3, "cache_enabled": true, "cache_backend": "milvus", "cache_threshold": 0.7, "guard_enabled": false, "guard_threshold": 0.8, "tools_enabled": false, "deployment_context": "quickstart"}}
{"id": "template_77549", "config": "# Semantic Router Configuration\n# Generated from template\n\ndecisions:\n  - name: \"technical_decision\"\n    modelRefs:\n      - model: \"phi4\"\n        use_reasoning: true\n    signals:\n      - type: \"domain\"\n        categories:\n          - \"support\"\n          - \"finance\"\n\nmodel_config:\n  phi4:\n    reasoning_family: \"phi4\"\n    preferred_endpoints:\n      - \"endpoint_phi4\"\n\nvllm_endpoints:\n  - name: \"endpoint_phi4\"\n    address: \"172.28.0.20\"\n    port: 8000\n    weight: 2\n\nsemantic_cache:\n  enabled: False\n  backend_type: \"redis\"\n  similarity_threshold: 0.8\n  max_entries: 1000\n  ttl_seconds: 3600\n\nprompt_guard:\n  enabled: False\n  threshold: 0.7\n  use_modernbert: true\n\ntools:\n  enabled: False\n  top_k: 3\n  similarity_threshold: 0.2\n", "intent": "Route queries to phi4, using domain-based routing, for kubernetes deployment", "deployment_context": "kubernetes", "source": "template", "values": {"decision_name": "technical_decision", "model_name": "phi4", "signal_type": "domain", "category1": "support", "category2": "finance", "endpoint_address": "172.28.0.20", "endpoint_port": 8000, "endpoint_weight": 2, "cache_enabled": false, "cache_backend": "redis", "cache_threshold": 0.8, "guard_enabled": false, "guard_threshold": 0.7, "tools_enabled": false, "deployment_context": "kubernetes"}}
{"id": "template_22891", "config": "# Semantic Router Configuration\n# Generated from template\n\ndecisions:\n  - name: \"business_decision\"\n    modelRefs:\n      - model: \"mistral\"\n        use_reasoning: true\n    signals:\n      - type: \"keyword\"\n        categories:\n          - \"general\"\n          - \"finance\"\n\nmodel_config:\n  mistral:\n    reasoning_family: \"mistral\"\n    preferred_endpoints:\n      - \"endpoint_mistral\"\n\nvllm_endpoints:\n  - name: \"endpoint_mistral\"\n    address: \"172.28.0.20\"\n    port: 8002\n    weight: 2\n\nsemantic_cache:\n  enabled: False\n  backend_type: \"milvus\"\n  similarity_threshold: 0.8\n  max_entries: 1000\n  ttl_seconds: 3600\n\nprompt_guard:\n  enabled: True\n  threshold: 0.7\n  use_modernbert: true\n\ntools:\n  enabled: False\n  top_k: 3\n  similarity_threshold: 0.2\n", "intent": "Route queries to mistral, using keyword-based routing, with PII detection, for kubernetes deployment", "deployment_context": "kubernetes", "source": "template", "values": {"decision_name": "business_decision", "model_name": "mistral", "signal_type": "keyword", "category1": "general", "category2": "finance", "endpoint_address": "172.28.0.20", "endpoint_port": 8002, "endpoint_weight": 2, "cache_enabled": false, "cache_backend": "milvus", "cache_threshold": 0.8, "guard_enabled": true, "guard_threshold": 0.7, "tools_enabled": false, "deployment_context": "kubernetes"}}
{"id": "template_61423", "config": "# Semantic Router Configuration\n# Generated from template\n\ndecisions:\n  - name: \"technical_decision\"\n    modelRefs:\n      - model: \"phi4\"\n        use_reasoning: true\n    signals:\n      - type: \"embedding\"\n        categories:\n          - \"technical\"\n          - \"finance\"\n\nmodel_config:\n  phi4:\n    reasoning_family: \"phi4\"\n    preferred_endpoints:\n      - \"endpoint_phi4\"\n\nvllm_endpoints:\n  - name: \"endpoint_phi4\"\n    address: \"172.16.0.10\"\n    port: 11434\n    weight: 2\n\nsemantic_cache:\n  enabled: True\n  backend_type: \"redis\"\n  similarity_threshold: 0.9\n  max_entries: 1000\n  ttl_seconds: 3600\n\nprompt_guard:\n  enabled: False\n  threshold: 0.7\n  use_modernbert: true\n\ntools:\n  enabled: False\n  top_k: 3\n  similarity_threshold: 0.2\n", "intent": "Route queries to phi4, using embedding-based routing, with redis semantic cache, for kubernetes deployment", "deployment_context": "kubernetes", "source": "template", "values": {"decision_name": "technical_decision", "model_name": "phi4", "signal_type": "embedding", "category1": "technical", "category2": "finance", "endpoint_address": "172.16.0.10", "endpoint_port": 11434, "endpoint_weight": 2, "cache_enabled": true, "cache_backend": "redis", "cache_threshold": 0.9, "guard_enabled": false, "guard_threshold": 0.7, "tools_enabled": false, "deployment_context": "kubernetes"}}
{"id": "template_98527", "config": "# Semantic Router Configuration\n# Generated from template\n\ndecisions:\n  - name: \"business_decision\"\n    modelRefs:\n      - model: \"mistral\"\n        use_reasoning: true\n    signals:\n      - type: \"embedding\"\n        categories:\n          - \"technical\"\n          - \"finance\"\n\nmodel_config:\n  mistral:\n    reasoning_family: \"mistral\"\n    preferred_endpoints:\n      - \"endpoint_mistral\"\n\nvllm_endpoints:\n  - name: \"endpoint_mistral\"\n    address: \"172.28.0.20\"\n    port: 8002\n    weight: 3\n\nsemantic_cache:\n  enabled: False\n  backend_type: \"memory\"\n  similarity_threshold: 0.9\n  max_entries: 1000\n  ttl_seconds: 3600\n\nprompt_guard:\n  enabled: False\n  threshold: 0.6\n  use_modernbert: true\n\ntools:\n  enabled: True\n  top_k: 3\n  similarity_threshold: 0.2\n", "intent": "Route queries to mistral, using embedding-based routing, with tools auto-selection, for quickstart deployment", "deployment_context": "quickstart", "source": "template", "values": {"decision_name": "business_decision", "model_name": "mistral", "signal_type": "embedding", "category1": "technical", "category2": "finance", "endpoint_address": "172.28.0.20", "endpoint_port": 8002, "endpoint_weight": 3, "cache_enabled": false, "cache_backend": "memory", "cache_threshold": 0.9, "guard_enabled": false, "guard_threshold": 0.6, "tools_enabled": true, "deployment_context": "quickstart"}}
{"id": "template_19737", "config": "# Semantic Router Configuration\n# Generated from template\n\ndecisions:\n  - name: \"general_decision\"\n    modelRefs:\n      - model: \"phi4\"\n        use_reasoning: true\n    signals:\n      - type: \"keyword\"\n        categories:\n          - \"support\"\n          - \"sales\"\n\nmodel_config:\n  phi4:\n    reasoning_family: \"phi4\"\n    preferred_endpoints:\n      - \"endpoint_phi4\"\n\nvllm_endpoints:\n  - name: \"endpoint_phi4\"\n    address: \"172.16.0.10\"\n    port: 11434\n    weight: 3\n\nsemantic_cache:\n  enabled: True\n  backend_type: \"memory\"\n  similarity_threshold: 0.7\n  max_entries: 1000\n  ttl_seconds: 3600\n\nprompt_guard:\n  enabled: False\n  threshold: 0.6\n  use_modernbert: true\n\ntools:\n  enabled: True\n  top_k: 3\n  similarity_threshold: 0.2\n", "intent": "Route queries to phi4, using keyword-based routing, with memory semantic cache, with tools auto-selection, for ai-gateway deployment", "deployment_context": "ai-gateway", "source": "template", "values": {"decision_name": "general_decision", "model_name": "phi4", "signal_type": "keyword", "category1": "support", "category2": "sales", "endpoint_address": "172.16.0.10", "endpoint_port": 11434, "endpoint_weight": 3, "cache_enabled": true, "cache_backend": "memory", "cache_threshold": 0.7, "guard_enabled": false, "guard_threshold": 0.6, "tools_enabled": true, "deployment_context": "ai-gateway"}}
{"id": "template_78981", "config": "# Semantic Router Configuration\n# Generated from template\n\ndecisions:\n  - name: \"support_decision\"\n    modelRefs:\n      - model: \"qwen3\"\n        use_reasoning: true\n    signals:\n      - type: \"embedding\"\n        categories:\n          - \"support\"\n          - \"finance\"\n\nmodel_config:\n  qwen3:\n    reasoning_family: \"qwen3\"\n    preferred_endpoints:\n      - \"endpoint_qwen3\"\n\nvllm_endpoints:\n  - name: \"endpoint_qwen3\"\n    address: \"172.28.0.20\"\n    port: 8080\n    weight: 1\n\nsemantic_cache:\n  enabled: True\n  backend_type: \"memory\"\n  similarity_threshold: 0.9\n  max_entries: 1000\n  ttl_seconds: 3600\n\nprompt_guard:\n  enabled: False\n  threshold: 0.7\n  use_modernbert: true\n\ntools:\n  enabled: False\n  top_k: 3\n  similarity_threshold: 0.2\n", "intent": "Route queries to qwen3, using embedding-based routing, with memory semantic cache, for quickstart deployment", "deployment_context": "quickstart", "source": "template", "values": {"decision_name": "support_decision", "model_name": "qwen3", "signal_type": "embedding", "category1": "support", "category2": "finance", "endpoint_address": "172.28.0.20", "endpoint_port": 8080, "endpoint_weight": 1, "cache_enabled": true, "cache_backend": "memory", "cache_threshold": 0.9, "guard_enabled": false, "guard_threshold": 0.7, "tools_enabled": false, "deployment_context": "quickstart"}}
{"id": "template_50067", "config": "# Semantic Router Configuration\n# Generated from template\n\ndecisions:\n  - name: \"general_decision\"\n    modelRefs:\n      - model: \"phi4\"\n        use_reasoning: true\n    signals:\n      - type: \"embedding\"\n        categories:\n          - \"technical\"\n          - \"sales\"\n\nmodel_config:\n  phi4:\n    reasoning_family: \"phi4\"\n    preferred_endpoints:\n      - \"endpoint_phi4\"\n\nvllm_endpoints:\n  - name: \"endpoint_phi4\"\n    address: \"192.168.1.100\"\n    port: 11434\n    weight: 2\n\nsemantic_cache:\n  enabled: False\n  backend_type: \"memory\"\n  similarity_threshold: 0.9\n  max_entries: 1000\n  ttl_seconds: 3600\n\nprompt_guard:\n  enabled: False\n  threshold: 0.8\n  use_modernbert: true\n\ntools:\n  enabled: True\n  top_k: 3\n  similarity_threshold: 0.2\n", "intent": "Route queries to phi4, using embedding-based routing, with tools auto-selection, for quickstart deployment", "deployment_context": "quickstart", "source": "template", "values": {"decision_name": "general_decision", "model_name": "phi4", "signal_type": "embedding", "category1": "technical", "category2": "sales", "endpoint_address": "192.168.1.100", "endpoint_port": 11434, "endpoint_weight": 2, "cache_enabled": false, "cache_backend": "memory", "cache_threshold": 0.9, "guard_enabled": false, "guard_threshold": 0.8, "tools_enabled": true, "deployment_context": "quickstart"}}
{"id": "template_2477", "config": "# Semantic Router Configuration\n# Generated from template\n\ndecisions:\n  - name: \"support_decision\"\n    modelRefs:\n      - model: \"llama3\"\n        use_reasoning: true\n    signals:\n      - type: \"domain\"\n        categories:\n          - \"business\"\n          - \"customer_service\"\n\nmodel_config:\n  llama3:\n    reasoning_family: \"llama3\"\n    preferred_endpoints:\n      - \"endpoint_llama3\"\n\nvllm_endpoints:\n  - name: \"endpoint_llama3\"\n    address: \"10.0.0.50\"\n    port: 8002\n    weight: 2\n\nsemantic_cache:\n  enabled: False\n  backend_type: \"redis\"\n  similarity_threshold: 0.7\n  max_entries: 1000\n  ttl_seconds: 3600\n\nprompt_guard:\n  enabled: True\n  threshold: 0.7\n  use_modernbert: true\n\ntools:\n  enabled: False\n  top_k: 3\n  similarity_threshold: 0.2\n", "intent": "Route queries to llama3, using domain-based routing, with PII detection, for ai-gateway deployment", "deployment_context": "ai-gateway", "source": "template", "values": {"decision_name": "support_decision", "model_name": "llama3", "signal_type": "domain", "category1": "business", "category2": "customer_service", "endpoint_address": "10.0.0.50", "endpoint_port": 8002, "endpoint_weight": 2, "cache_enabled": false, "cache_backend": "redis", "cache_threshold": 0.7, "guard_enabled": true, "guard_threshold": 0.7, "tools_enabled": false, "deployment_context": "ai-gateway"}}
{"id": "template_70908", "config": "# Semantic Router Configuration\n# Generated from template\n\ndecisions:\n  - name: \"technical_decision\"\n    modelRefs:\n      - model: \"llama3\"\n        use_reasoning: true\n    signals:\n      - type: \"embedding\"\n        categories:\n          - \"support\"\n          - \"finance\"\n\nmodel_config:\n  llama3:\n    reasoning_family: \"llama3\"\n    preferred_endpoints:\n      - \"endpoint_llama3\"\n\nvllm_endpoints:\n  - name: \"endpoint_llama3\"\n    address: \"172.16.0.10\"\n    port: 8000\n    weight: 1\n\nsemantic_cache:\n  enabled: False\n  backend_type: \"redis\"\n  similarity_threshold: 0.9\n  max_entries: 1000\n  ttl_seconds: 3600\n\nprompt_guard:\n  enabled: False\n  threshold: 0.8\n  use_modernbert: true\n\ntools:\n  enabled: True\n  top_k: 3\n  similarity_threshold: 0.2\n", "intent": "Route queries to llama3, using embedding-based routing, with tools auto-selection, for ai-gateway deployment", "deployment_context": "ai-gateway", "source": "template", "values": {"decision_name": "technical_decision", "model_name": "llama3", "signal_type": "embedding", "category1": "support", "category2": "finance", "endpoint_address": "172.16.0.10", "endpoint_port": 8000, "endpoint_weight": 1, "cache_enabled": false, "cache_backend": "redis", "cache_threshold": 0.9, "guard_enabled": false, "guard_threshold": 0.8, "tools_enabled": true, "deployment_context": "ai-gateway"}}
{"id": "template_69103", "config": "# Semantic Router Configuration\n# Generated from template\n\ndecisions:\n  - name: \"technical_decision\"\n    modelRefs:\n      - model: \"mistral\"\n        use_reasoning: true\n    signals:\n      - type: \"keyword\"\n        categories:\n          - \"business\"\n          - \"finance\"\n\nmodel_config:\n  mistral:\n    reasoning_family: \"mistral\"\n    preferred_endpoints:\n      - \"endpoint_mistral\"\n\nvllm_endpoints:\n  - name: \"endpoint_mistral\"\n    address: \"172.16.0.10\"\n    port: 11434\n    weight: 1\n\nsemantic_cache:\n  enabled: True\n  backend_type: \"redis\"\n  similarity_threshold: 0.7\n  max_entries: 1000\n  ttl_seconds: 3600\n\nprompt_guard:\n  enabled: True\n  threshold: 0.6\n  use_modernbert: true\n\ntools:\n  enabled: False\n  top_k: 3\n  similarity_threshold: 0.2\n", "intent": "Route queries to mistral, using keyword-based routing, with redis semantic cache, with PII detection, for ai-gateway deployment", "deployment_context": "ai-gateway", "source": "template", "values": {"decision_name": "technical_decision", "model_name": "mistral", "signal_type": "keyword", "category1": "business", "category2": "finance", "endpoint_address": "172.16.0.10", "endpoint_port": 11434, "endpoint_weight": 1, "cache_enabled": true, "cache_backend": "redis", "cache_threshold": 0.7, "guard_enabled": true, "guard_threshold": 0.6, "tools_enabled": false, "deployment_context": "ai-gateway"}}
{"id": "template_20591", "config": "# Semantic Router Configuration\n# Generated from template\n\ndecisions:\n  - name: \"general_decision\"\n    modelRefs:\n      - model: \"mistral\"\n        use_reasoning: true\n    signals:\n      - type: \"keyword\"\n        categories:\n          - \"support\"\n          - \"sales\"\n\nmodel_config:\n  mistral:\n    reasoning_family: \"mistral\"\n    preferred_endpoints:\n      - \"endpoint_mistral\"\n\nvllm_endpoints:\n  - name: \"endpoint_mistral\"\n    address: \"10.0.0.50\"\n    port: 8080\n    weight: 1\n\nsemantic_cache:\n  enabled: False\n  backend_type: \"redis\"\n  similarity_threshold: 0.8\n  max_entries: 1000\n  ttl_seconds: 3600\n\nprompt_guard:\n  enabled: False\n  threshold: 0.6\n  use_modernbert: true\n\ntools:\n  enabled: True\n  top_k: 3\n  similarity_threshold: 0.2\n", "intent": "Route queries to mistral, using keyword-based routing, with tools auto-selection, for ai-gateway deployment", "deployment_context": "ai-gateway", "source": "template", "values": {"decision_name": "general_decision", "model_name": "mistral", "signal_type": "keyword", "category1": "support", "category2": "sales", "endpoint_address": "10.0.0.50", "endpoint_port": 8080, "endpoint_weight": 1, "cache_enabled": false, "cache_backend": "redis", "cache_threshold": 0.8, "guard_enabled": false, "guard_threshold": 0.6, "tools_enabled": true, "deployment_context": "ai-gateway"}}
{"id": "template_55047", "config": "# Semantic Router Configuration\n# Generated from template\n\ndecisions:\n  - name: \"technical_decision\"\n    modelRefs:\n      - model: \"llama3\"\n        use_reasoning: true\n    signals:\n      - type: \"keyword\"\n        categories:\n          - \"business\"\n          - \"finance\"\n\nmodel_config:\n  llama3:\n    reasoning_family: \"llama3\"\n    preferred_endpoints:\n      - \"endpoint_llama3\"\n\nvllm_endpoints:\n  - name: \"endpoint_llama3\"\n    address: \"10.0.0.50\"\n    port: 8002\n    weight: 1\n\nsemantic_cache:\n  enabled: False\n  backend_type: \"milvus\"\n  similarity_threshold: 0.8\n  max_entries: 1000\n  ttl_seconds: 3600\n\nprompt_guard:\n  enabled: True\n  threshold: 0.7\n  use_modernbert: true\n\ntools:\n  enabled: False\n  top_k: 3\n  similarity_threshold: 0.2\n", "intent": "Route queries to llama3, using keyword-based routing, with PII detection, for ai-gateway deployment", "deployment_context": "ai-gateway", "source": "template", "values": {"decision_name": "technical_decision", "model_name": "llama3", "signal_type": "keyword", "category1": "business", "category2": "finance", "endpoint_address": "10.0.0.50", "endpoint_port": 8002, "endpoint_weight": 1, "cache_enabled": false, "cache_backend": "milvus", "cache_threshold": 0.8, "guard_enabled": true, "guard_threshold": 0.7, "tools_enabled": false, "deployment_context": "ai-gateway"}}
{"id": "template_1897", "config": "# Semantic Router Configuration\n# Generated from template\n\ndecisions:\n  - name: \"business_decision\"\n    modelRefs:\n      - model: \"phi4\"\n        use_reasoning: true\n    signals:\n      - type: \"domain\"\n        categories:\n          - \"general\"\n          - \"finance\"\n\nmodel_config:\n  phi4:\n    reasoning_family: \"phi4\"\n    preferred_endpoints:\n      - \"endpoint_phi4\"\n\nvllm_endpoints:\n  - name: \"endpoint_phi4\"\n    address: \"172.16.0.10\"\n    port: 8002\n    weight: 2\n\nsemantic_cache:\n  enabled: False\n  backend_type: \"milvus\"\n  similarity_threshold: 0.7\n  max_entries: 1000\n  ttl_seconds: 3600\n\nprompt_guard:\n  enabled: True\n  threshold: 0.6\n  use_modernbert: true\n\ntools:\n  enabled: True\n  top_k: 3\n  similarity_threshold: 0.2\n", "intent": "Route queries to phi4, using domain-based routing, with PII detection, with tools auto-selection, for istio deployment", "deployment_context": "istio", "source": "template", "values": {"decision_name": "business_decision", "model_name": "phi4", "signal_type": "domain", "category1": "general", "category2": "finance", "endpoint_address": "172.16.0.10", "endpoint_port": 8002, "endpoint_weight": 2, "cache_enabled": false, "cache_backend": "milvus", "cache_threshold": 0.7, "guard_enabled": true, "guard_threshold": 0.6, "tools_enabled": true, "deployment_context": "istio"}}
{"id": "template_69623", "config": "# Semantic Router Configuration\n# Generated from template\n\ndecisions:\n  - name: \"business_decision\"\n    modelRefs:\n      - model: \"llama3\"\n        use_reasoning: true\n    signals:\n      - type: \"embedding\"\n        categories:\n          - \"business\"\n          - \"finance\"\n\nmodel_config:\n  llama3:\n    reasoning_family: \"llama3\"\n    preferred_endpoints:\n      - \"endpoint_llama3\"\n\nvllm_endpoints:\n  - name: \"endpoint_llama3\"\n    address: \"172.28.0.20\"\n    port: 8080\n    weight: 2\n\nsemantic_cache:\n  enabled: False\n  backend_type: \"memory\"\n  similarity_threshold: 0.7\n  max_entries: 1000\n  ttl_seconds: 3600\n\nprompt_guard:\n  enabled: True\n  threshold: 0.8\n  use_modernbert: true\n\ntools:\n  enabled: True\n  top_k: 3\n  similarity_threshold: 0.2\n", "intent": "Route queries to llama3, using embedding-based routing, with PII detection, with tools auto-selection, for istio deployment", "deployment_context": "istio", "source": "template", "values": {"decision_name": "business_decision", "model_name": "llama3", "signal_type": "embedding", "category1": "business", "category2": "finance", "endpoint_address": "172.28.0.20", "endpoint_port": 8080, "endpoint_weight": 2, "cache_enabled": false, "cache_backend": "memory", "cache_threshold": 0.7, "guard_enabled": true, "guard_threshold": 0.8, "tools_enabled": true, "deployment_context": "istio"}}
{"id": "template_762", "config": "# Semantic Router Configuration\n# Generated from template\n\ndecisions:\n  - name: \"general_decision\"\n    modelRefs:\n      - model: \"mistral\"\n        use_reasoning: true\n    signals:\n      - type: \"keyword\"\n        categories:\n          - \"business\"\n          - \"sales\"\n\nmodel_config:\n  mistral:\n    reasoning_family: \"mistral\"\n    preferred_endpoints:\n      - \"endpoint_mistral\"\n\nvllm_endpoints:\n  - name: \"endpoint_mistral\"\n    address: \"172.16.0.10\"\n    port: 11434\n    weight: 1\n\nsemantic_cache:\n  enabled: False\n  backend_type: \"redis\"\n  similarity_threshold: 0.8\n  max_entries: 1000\n  ttl_seconds: 3600\n\nprompt_guard:\n  enabled: False\n  threshold: 0.8\n  use_modernbert: true\n\ntools:\n  enabled: True\n  top_k: 3\n  similarity_threshold: 0.2\n", "intent": "Route queries to mistral, using keyword-based routing, with tools auto-selection, for quickstart deployment", "deployment_context": "quickstart", "source": "template", "values": {"decision_name": "general_decision", "model_name": "mistral", "signal_type": "keyword", "category1": "business", "category2": "sales", "endpoint_address": "172.16.0.10", "endpoint_port": 11434, "endpoint_weight": 1, "cache_enabled": false, "cache_backend": "redis", "cache_threshold": 0.8, "guard_enabled": false, "guard_threshold": 0.8, "tools_enabled": true, "deployment_context": "quickstart"}}
{"id": "template_42394", "config": "# Semantic Router Configuration\n# Generated from template\n\ndecisions:\n  - name: \"technical_decision\"\n    modelRefs:\n      - model: \"mistral\"\n        use_reasoning: true\n    signals:\n      - type: \"domain\"\n        categories:\n          - \"support\"\n          - \"finance\"\n\nmodel_config:\n  mistral:\n    reasoning_family: \"mistral\"\n    preferred_endpoints:\n      - \"endpoint_mistral\"\n\nvllm_endpoints:\n  - name: \"endpoint_mistral\"\n    address: \"172.28.0.20\"\n    port: 8000\n    weight: 3\n\nsemantic_cache:\n  enabled: False\n  backend_type: \"milvus\"\n  similarity_threshold: 0.8\n  max_entries: 1000\n  ttl_seconds: 3600\n\nprompt_guard:\n  enabled: False\n  threshold: 0.8\n  use_modernbert: true\n\ntools:\n  enabled: False\n  top_k: 3\n  similarity_threshold: 0.2\n", "intent": "Route queries to mistral, using domain-based routing, for istio deployment", "deployment_context": "istio", "source": "template", "values": {"decision_name": "technical_decision", "model_name": "mistral", "signal_type": "domain", "category1": "support", "category2": "finance", "endpoint_address": "172.28.0.20", "endpoint_port": 8000, "endpoint_weight": 3, "cache_enabled": false, "cache_backend": "milvus", "cache_threshold": 0.8, "guard_enabled": false, "guard_threshold": 0.8, "tools_enabled": false, "deployment_context": "istio"}}
{"id": "template_27552", "config": "# Semantic Router Configuration\n# Generated from template\n\ndecisions:\n  - name: \"support_decision\"\n    modelRefs:\n      - model: \"phi4\"\n        use_reasoning: true\n    signals:\n      - type: \"keyword\"\n        categories:\n          - \"technical\"\n          - \"sales\"\n\nmodel_config:\n  phi4:\n    reasoning_family: \"phi4\"\n    preferred_endpoints:\n      - \"endpoint_phi4\"\n\nvllm_endpoints:\n  - name: \"endpoint_phi4\"\n    address: \"10.0.0.50\"\n    port: 8002\n    weight: 1\n\nsemantic_cache:\n  enabled: True\n  backend_type: \"memory\"\n  similarity_threshold: 0.9\n  max_entries: 1000\n  ttl_seconds: 3600\n\nprompt_guard:\n  enabled: False\n  threshold: 0.6\n  use_modernbert: true\n\ntools:\n  enabled: False\n  top_k: 3\n  similarity_threshold: 0.2\n", "intent": "Route queries to phi4, using keyword-based routing, with memory semantic cache, for istio deployment", "deployment_context": "istio", "source": "template", "values": {"decision_name": "support_decision", "model_name": "phi4", "signal_type": "keyword", "category1": "technical", "category2": "sales", "endpoint_address": "10.0.0.50", "endpoint_port": 8002, "endpoint_weight": 1, "cache_enabled": true, "cache_backend": "memory", "cache_threshold": 0.9, "guard_enabled": false, "guard_threshold": 0.6, "tools_enabled": false, "deployment_context": "istio"}}
{"id": "template_33879", "config": "# Semantic Router Configuration\n# Generated from template\n\ndecisions:\n  - name: \"technical_decision\"\n    modelRefs:\n      - model: \"mistral\"\n        use_reasoning: true\n    signals:\n      - type: \"domain\"\n        categories:\n          - \"general\"\n          - \"finance\"\n\nmodel_config:\n  mistral:\n    reasoning_family: \"mistral\"\n    preferred_endpoints:\n      - \"endpoint_mistral\"\n\nvllm_endpoints:\n  - name: \"endpoint_mistral\"\n    address: \"192.168.1.100\"\n    port: 8080\n    weight: 1\n\nsemantic_cache:\n  enabled: False\n  backend_type: \"memory\"\n  similarity_threshold: 0.9\n  max_entries: 1000\n  ttl_seconds: 3600\n\nprompt_guard:\n  enabled: False\n  threshold: 0.8\n  use_modernbert: true\n\ntools:\n  enabled: True\n  top_k: 3\n  similarity_threshold: 0.2\n", "intent": "Route queries to mistral, using domain-based routing, with tools auto-selection, for quickstart deployment", "deployment_context": "quickstart", "source": "template", "values": {"decision_name": "technical_decision", "model_name": "mistral", "signal_type": "domain", "category1": "general", "category2": "finance", "endpoint_address": "192.168.1.100", "endpoint_port": 8080, "endpoint_weight": 1, "cache_enabled": false, "cache_backend": "memory", "cache_threshold": 0.9, "guard_enabled": false, "guard_threshold": 0.8, "tools_enabled": true, "deployment_context": "quickstart"}}
{"id": "template_69188", "config": "# Semantic Router Configuration\n# Generated from template\n\ndecisions:\n  - name: \"technical_decision\"\n    modelRefs:\n      - model: \"mistral\"\n        use_reasoning: true\n    signals:\n      - type: \"embedding\"\n        categories:\n          - \"technical\"\n          - \"engineering\"\n\nmodel_config:\n  mistral:\n    reasoning_family: \"mistral\"\n    preferred_endpoints:\n      - \"endpoint_mistral\"\n\nvllm_endpoints:\n  - name: \"endpoint_mistral\"\n    address: \"192.168.1.100\"\n    port: 8080\n    weight: 1\n\nsemantic_cache:\n  enabled: True\n  backend_type: \"milvus\"\n  similarity_threshold: 0.9\n  max_entries: 1000\n  ttl_seconds: 3600\n\nprompt_guard:\n  enabled: True\n  threshold: 0.7\n  use_modernbert: true\n\ntools:\n  enabled: True\n  top_k: 3\n  similarity_threshold: 0.2\n", "intent": "Route queries to mistral, using embedding-based routing, with milvus semantic cache, with PII detection, with tools auto-selection, for istio deployment", "deployment_context": "istio", "source": "template", "values": {"decision_name": "technical_decision", "model_name": "mistral", "signal_type": "embedding", "category1": "technical", "category2": "engineering", "endpoint_address": "192.168.1.100", "endpoint_port": 8080, "endpoint_weight": 1, "cache_enabled": true, "cache_backend": "milvus", "cache_threshold": 0.9, "guard_enabled": true, "guard_threshold": 0.7, "tools_enabled": true, "deployment_context": "istio"}}
{"id": "template_72698", "config": "# Semantic Router Configuration\n# Generated from template\n\ndecisions:\n  - name: \"technical_decision\"\n    modelRefs:\n      - model: \"llama3\"\n        use_reasoning: true\n    signals:\n      - type: \"keyword\"\n        categories:\n          - \"support\"\n          - \"finance\"\n\nmodel_config:\n  llama3:\n    reasoning_family: \"llama3\"\n    preferred_endpoints:\n      - \"endpoint_llama3\"\n\nvllm_endpoints:\n  - name: \"endpoint_llama3\"\n    address: \"172.28.0.20\"\n    port: 8002\n    weight: 3\n\nsemantic_cache:\n  enabled: False\n  backend_type: \"memory\"\n  similarity_threshold: 0.9\n  max_entries: 1000\n  ttl_seconds: 3600\n\nprompt_guard:\n  enabled: False\n  threshold: 0.8\n  use_modernbert: true\n\ntools:\n  enabled: True\n  top_k: 3\n  similarity_threshold: 0.2\n", "intent": "Route queries to llama3, using keyword-based routing, with tools auto-selection, for istio deployment", "deployment_context": "istio", "source": "template", "values": {"decision_name": "technical_decision", "model_name": "llama3", "signal_type": "keyword", "category1": "support", "category2": "finance", "endpoint_address": "172.28.0.20", "endpoint_port": 8002, "endpoint_weight": 3, "cache_enabled": false, "cache_backend": "memory", "cache_threshold": 0.9, "guard_enabled": false, "guard_threshold": 0.8, "tools_enabled": true, "deployment_context": "istio"}}
{"id": "template_55457", "config": "# Semantic Router Configuration\n# Generated from template\n\ndecisions:\n  - name: \"technical_decision\"\n    modelRefs:\n      - model: \"llama3\"\n        use_reasoning: true\n    signals:\n      - type: \"keyword\"\n        categories:\n          - \"technical\"\n          - \"engineering\"\n\nmodel_config:\n  llama3:\n    reasoning_family: \"llama3\"\n    preferred_endpoints:\n      - \"endpoint_llama3\"\n\nvllm_endpoints:\n  - name: \"endpoint_llama3\"\n    address: \"10.0.0.50\"\n    port: 8080\n    weight: 2\n\nsemantic_cache:\n  enabled: True\n  backend_type: \"memory\"\n  similarity_threshold: 0.7\n  max_entries: 1000\n  ttl_seconds: 3600\n\nprompt_guard:\n  enabled: True\n  threshold: 0.8\n  use_modernbert: true\n\ntools:\n  enabled: True\n  top_k: 3\n  similarity_threshold: 0.2\n", "intent": "Route queries to llama3, using keyword-based routing, with memory semantic cache, with PII detection, with tools auto-selection, for istio deployment", "deployment_context": "istio", "source": "template", "values": {"decision_name": "technical_decision", "model_name": "llama3", "signal_type": "keyword", "category1": "technical", "category2": "engineering", "endpoint_address": "10.0.0.50", "endpoint_port": 8080, "endpoint_weight": 2, "cache_enabled": true, "cache_backend": "memory", "cache_threshold": 0.7, "guard_enabled": true, "guard_threshold": 0.8, "tools_enabled": true, "deployment_context": "istio"}}
{"id": "template_59057", "config": "# Semantic Router Configuration\n# Generated from template\n\ndecisions:\n  - name: \"technical_decision\"\n    modelRefs:\n      - model: \"phi4\"\n        use_reasoning: true\n    signals:\n      - type: \"keyword\"\n        categories:\n          - \"business\"\n          - \"engineering\"\n\nmodel_config:\n  phi4:\n    reasoning_family: \"phi4\"\n    preferred_endpoints:\n      - \"endpoint_phi4\"\n\nvllm_endpoints:\n  - name: \"endpoint_phi4\"\n    address: \"192.168.1.100\"\n    port: 8080\n    weight: 3\n\nsemantic_cache:\n  enabled: True\n  backend_type: \"milvus\"\n  similarity_threshold: 0.7\n  max_entries: 1000\n  ttl_seconds: 3600\n\nprompt_guard:\n  enabled: True\n  threshold: 0.6\n  use_modernbert: true\n\ntools:\n  enabled: False\n  top_k: 3\n  similarity_threshold: 0.2\n", "intent": "Route queries to phi4, using keyword-based routing, with milvus semantic cache, with PII detection, for kubernetes deployment", "deployment_context": "kubernetes", "source": "template", "values": {"decision_name": "technical_decision", "model_name": "phi4", "signal_type": "keyword", "category1": "business", "category2": "engineering", "endpoint_address": "192.168.1.100", "endpoint_port": 8080, "endpoint_weight": 3, "cache_enabled": true, "cache_backend": "milvus", "cache_threshold": 0.7, "guard_enabled": true, "guard_threshold": 0.6, "tools_enabled": false, "deployment_context": "kubernetes"}}
{"id": "template_21741", "config": "# Semantic Router Configuration\n# Generated from template\n\ndecisions:\n  - name: \"technical_decision\"\n    modelRefs:\n      - model: \"phi4\"\n        use_reasoning: true\n    signals:\n      - type: \"embedding\"\n        categories:\n          - \"technical\"\n          - \"customer_service\"\n\nmodel_config:\n  phi4:\n    reasoning_family: \"phi4\"\n    preferred_endpoints:\n      - \"endpoint_phi4\"\n\nvllm_endpoints:\n  - name: \"endpoint_phi4\"\n    address: \"192.168.1.100\"\n    port: 8080\n    weight: 1\n\nsemantic_cache:\n  enabled: False\n  backend_type: \"milvus\"\n  similarity_threshold: 0.7\n  max_entries: 1000\n  ttl_seconds: 3600\n\nprompt_guard:\n  enabled: True\n  threshold: 0.8\n  use_modernbert: true\n\ntools:\n  enabled: True\n  top_k: 3\n  similarity_threshold: 0.2\n", "intent": "Route queries to phi4, using embedding-based routing, with PII detection, with tools auto-selection, for quickstart deployment", "deployment_context": "quickstart", "source": "template", "values": {"decision_name": "technical_decision", "model_name": "phi4", "signal_type": "embedding", "category1": "technical", "category2": "customer_service", "endpoint_address": "192.168.1.100", "endpoint_port": 8080, "endpoint_weight": 1, "cache_enabled": false, "cache_backend": "milvus", "cache_threshold": 0.7, "guard_enabled": true, "guard_threshold": 0.8, "tools_enabled": true, "deployment_context": "quickstart"}}
{"id": "template_88486", "config": "# Semantic Router Configuration\n# Generated from template\n\ndecisions:\n  - name: \"business_decision\"\n    modelRefs:\n      - model: \"phi4\"\n        use_reasoning: true\n    signals:\n      - type: \"embedding\"\n        categories:\n          - \"technical\"\n          - \"customer_service\"\n\nmodel_config:\n  phi4:\n    reasoning_family: \"phi4\"\n    preferred_endpoints:\n      - \"endpoint_phi4\"\n\nvllm_endpoints:\n  - name: \"endpoint_phi4\"\n    address: \"192.168.1.100\"\n    port: 8000\n    weight: 1\n\nsemantic_cache:\n  enabled: True\n  backend_type: \"redis\"\n  similarity_threshold: 0.9\n  max_entries: 1000\n  ttl_seconds: 3600\n\nprompt_guard:\n  enabled: False\n  threshold: 0.8\n  use_modernbert: true\n\ntools:\n  enabled: False\n  top_k: 3\n  similarity_threshold: 0.2\n", "intent": "Route queries to phi4, using embedding-based routing, with redis semantic cache, for quickstart deployment", "deployment_context": "quickstart", "source": "template", "values": {"decision_name": "business_decision", "model_name": "phi4", "signal_type": "embedding", "category1": "technical", "category2": "customer_service", "endpoint_address": "192.168.1.100", "endpoint_port": 8000, "endpoint_weight": 1, "cache_enabled": true, "cache_backend": "redis", "cache_threshold": 0.9, "guard_enabled": false, "guard_threshold": 0.8, "tools_enabled": false, "deployment_context": "quickstart"}}
{"id": "template_80969", "config": "# Semantic Router Configuration\n# Generated from template\n\ndecisions:\n  - name: \"general_decision\"\n    modelRefs:\n      - model: \"llama3\"\n        use_reasoning: true\n    signals:\n      - type: \"embedding\"\n        categories:\n          - \"business\"\n          - \"engineering\"\n\nmodel_config:\n  llama3:\n    reasoning_family: \"llama3\"\n    preferred_endpoints:\n      - \"endpoint_llama3\"\n\nvllm_endpoints:\n  - name: \"endpoint_llama3\"\n    address: \"10.0.0.50\"\n    port: 8080\n    weight: 1\n\nsemantic_cache:\n  enabled: True\n  backend_type: \"milvus\"\n  similarity_threshold: 0.8\n  max_entries: 1000\n  ttl_seconds: 3600\n\nprompt_guard:\n  enabled: True\n  threshold: 0.7\n  use_modernbert: true\n\ntools:\n  enabled: True\n  top_k: 3\n  similarity_threshold: 0.2\n", "intent": "Route queries to llama3, using embedding-based routing, with milvus semantic cache, with PII detection, with tools auto-selection, for ai-gateway deployment", "deployment_context": "ai-gateway", "source": "template", "values": {"decision_name": "general_decision", "model_name": "llama3", "signal_type": "embedding", "category1": "business", "category2": "engineering", "endpoint_address": "10.0.0.50", "endpoint_port": 8080, "endpoint_weight": 1, "cache_enabled": true, "cache_backend": "milvus", "cache_threshold": 0.8, "guard_enabled": true, "guard_threshold": 0.7, "tools_enabled": true, "deployment_context": "ai-gateway"}}
{"id": "template_10133", "config": "# Semantic Router Configuration\n# Generated from template\n\ndecisions:\n  - name: \"general_decision\"\n    modelRefs:\n      - model: \"llama3\"\n        use_reasoning: true\n    signals:\n      - type: \"embedding\"\n        categories:\n          - \"technical\"\n          - \"customer_service\"\n\nmodel_config:\n  llama3:\n    reasoning_family: \"llama3\"\n    preferred_endpoints:\n      - \"endpoint_llama3\"\n\nvllm_endpoints:\n  - name: \"endpoint_llama3\"\n    address: \"192.168.1.100\"\n    port: 11434\n    weight: 3\n\nsemantic_cache:\n  enabled: True\n  backend_type: \"redis\"\n  similarity_threshold: 0.8\n  max_entries: 1000\n  ttl_seconds: 3600\n\nprompt_guard:\n  enabled: False\n  threshold: 0.6\n  use_modernbert: true\n\ntools:\n  enabled: True\n  top_k: 3\n  similarity_threshold: 0.2\n", "intent": "Route queries to llama3, using embedding-based routing, with redis semantic cache, with tools auto-selection, for kubernetes deployment", "deployment_context": "kubernetes", "source": "template", "values": {"decision_name": "general_decision", "model_name": "llama3", "signal_type": "embedding", "category1": "technical", "category2": "customer_service", "endpoint_address": "192.168.1.100", "endpoint_port": 11434, "endpoint_weight": 3, "cache_enabled": true, "cache_backend": "redis", "cache_threshold": 0.8, "guard_enabled": false, "guard_threshold": 0.6, "tools_enabled": true, "deployment_context": "kubernetes"}}
{"id": "template_35994", "config": "# Semantic Router Configuration\n# Generated from template\n\ndecisions:\n  - name: \"business_decision\"\n    modelRefs:\n      - model: \"qwen3\"\n        use_reasoning: true\n    signals:\n      - type: \"keyword\"\n        categories:\n          - \"technical\"\n          - \"engineering\"\n\nmodel_config:\n  qwen3:\n    reasoning_family: \"qwen3\"\n    preferred_endpoints:\n      - \"endpoint_qwen3\"\n\nvllm_endpoints:\n  - name: \"endpoint_qwen3\"\n    address: \"192.168.1.100\"\n    port: 8080\n    weight: 1\n\nsemantic_cache:\n  enabled: True\n  backend_type: \"milvus\"\n  similarity_threshold: 0.7\n  max_entries: 1000\n  ttl_seconds: 3600\n\nprompt_guard:\n  enabled: True\n  threshold: 0.7\n  use_modernbert: true\n\ntools:\n  enabled: False\n  top_k: 3\n  similarity_threshold: 0.2\n", "intent": "Route queries to qwen3, using keyword-based routing, with milvus semantic cache, with PII detection, for ai-gateway deployment", "deployment_context": "ai-gateway", "source": "template", "values": {"decision_name": "business_decision", "model_name": "qwen3", "signal_type": "keyword", "category1": "technical", "category2": "engineering", "endpoint_address": "192.168.1.100", "endpoint_port": 8080, "endpoint_weight": 1, "cache_enabled": true, "cache_backend": "milvus", "cache_threshold": 0.7, "guard_enabled": true, "guard_threshold": 0.7, "tools_enabled": false, "deployment_context": "ai-gateway"}}
{"id": "template_11937", "config": "# Semantic Router Configuration\n# Generated from template\n\ndecisions:\n  - name: \"general_decision\"\n    modelRefs:\n      - model: \"mistral\"\n        use_reasoning: true\n    signals:\n      - type: \"keyword\"\n        categories:\n          - \"general\"\n          - \"sales\"\n\nmodel_config:\n  mistral:\n    reasoning_family: \"mistral\"\n    preferred_endpoints:\n      - \"endpoint_mistral\"\n\nvllm_endpoints:\n  - name: \"endpoint_mistral\"\n    address: \"172.28.0.20\"\n    port: 8080\n    weight: 3\n\nsemantic_cache:\n  enabled: False\n  backend_type: \"redis\"\n  similarity_threshold: 0.9\n  max_entries: 1000\n  ttl_seconds: 3600\n\nprompt_guard:\n  enabled: True\n  threshold: 0.7\n  use_modernbert: true\n\ntools:\n  enabled: False\n  top_k: 3\n  similarity_threshold: 0.2\n", "intent": "Route queries to mistral, using keyword-based routing, with PII detection, for istio deployment", "deployment_context": "istio", "source": "template", "values": {"decision_name": "general_decision", "model_name": "mistral", "signal_type": "keyword", "category1": "general", "category2": "sales", "endpoint_address": "172.28.0.20", "endpoint_port": 8080, "endpoint_weight": 3, "cache_enabled": false, "cache_backend": "redis", "cache_threshold": 0.9, "guard_enabled": true, "guard_threshold": 0.7, "tools_enabled": false, "deployment_context": "istio"}}
{"id": "template_5547", "config": "# Semantic Router Configuration\n# Generated from template\n\ndecisions:\n  - name: \"technical_decision\"\n    modelRefs:\n      - model: \"qwen3\"\n        use_reasoning: true\n    signals:\n      - type: \"keyword\"\n        categories:\n          - \"support\"\n          - \"sales\"\n\nmodel_config:\n  qwen3:\n    reasoning_family: \"qwen3\"\n    preferred_endpoints:\n      - \"endpoint_qwen3\"\n\nvllm_endpoints:\n  - name: \"endpoint_qwen3\"\n    address: \"172.16.0.10\"\n    port: 8000\n    weight: 2\n\nsemantic_cache:\n  enabled: True\n  backend_type: \"memory\"\n  similarity_threshold: 0.7\n  max_entries: 1000\n  ttl_seconds: 3600\n\nprompt_guard:\n  enabled: False\n  threshold: 0.7\n  use_modernbert: true\n\ntools:\n  enabled: False\n  top_k: 3\n  similarity_threshold: 0.2\n", "intent": "Route queries to qwen3, using keyword-based routing, with memory semantic cache, for ai-gateway deployment", "deployment_context": "ai-gateway", "source": "template", "values": {"decision_name": "technical_decision", "model_name": "qwen3", "signal_type": "keyword", "category1": "support", "category2": "sales", "endpoint_address": "172.16.0.10", "endpoint_port": 8000, "endpoint_weight": 2, "cache_enabled": true, "cache_backend": "memory", "cache_threshold": 0.7, "guard_enabled": false, "guard_threshold": 0.7, "tools_enabled": false, "deployment_context": "ai-gateway"}}
{"id": "template_10476", "config": "# Semantic Router Configuration\n# Generated from template\n\ndecisions:\n  - name: \"general_decision\"\n    modelRefs:\n      - model: \"llama3\"\n        use_reasoning: true\n    signals:\n      - type: \"domain\"\n        categories:\n          - \"business\"\n          - \"sales\"\n\nmodel_config:\n  llama3:\n    reasoning_family: \"llama3\"\n    preferred_endpoints:\n      - \"endpoint_llama3\"\n\nvllm_endpoints:\n  - name: \"endpoint_llama3\"\n    address: \"192.168.1.100\"\n    port: 8080\n    weight: 3\n\nsemantic_cache:\n  enabled: True\n  backend_type: \"memory\"\n  similarity_threshold: 0.7\n  max_entries: 1000\n  ttl_seconds: 3600\n\nprompt_guard:\n  enabled: True\n  threshold: 0.6\n  use_modernbert: true\n\ntools:\n  enabled: False\n  top_k: 3\n  similarity_threshold: 0.2\n", "intent": "Route queries to llama3, using domain-based routing, with memory semantic cache, with PII detection, for istio deployment", "deployment_context": "istio", "source": "template", "values": {"decision_name": "general_decision", "model_name": "llama3", "signal_type": "domain", "category1": "business", "category2": "sales", "endpoint_address": "192.168.1.100", "endpoint_port": 8080, "endpoint_weight": 3, "cache_enabled": true, "cache_backend": "memory", "cache_threshold": 0.7, "guard_enabled": true, "guard_threshold": 0.6, "tools_enabled": false, "deployment_context": "istio"}}
{"id": "template_8314", "config": "# Semantic Router Configuration\n# Generated from template\n\ndecisions:\n  - name: \"support_decision\"\n    modelRefs:\n      - model: \"phi4\"\n        use_reasoning: true\n    signals:\n      - type: \"keyword\"\n        categories:\n          - \"business\"\n          - \"finance\"\n\nmodel_config:\n  phi4:\n    reasoning_family: \"phi4\"\n    preferred_endpoints:\n      - \"endpoint_phi4\"\n\nvllm_endpoints:\n  - name: \"endpoint_phi4\"\n    address: \"10.0.0.50\"\n    port: 11434\n    weight: 2\n\nsemantic_cache:\n  enabled: False\n  backend_type: \"milvus\"\n  similarity_threshold: 0.7\n  max_entries: 1000\n  ttl_seconds: 3600\n\nprompt_guard:\n  enabled: False\n  threshold: 0.7\n  use_modernbert: true\n\ntools:\n  enabled: True\n  top_k: 3\n  similarity_threshold: 0.2\n", "intent": "Route queries to phi4, using keyword-based routing, with tools auto-selection, for ai-gateway deployment", "deployment_context": "ai-gateway", "source": "template", "values": {"decision_name": "support_decision", "model_name": "phi4", "signal_type": "keyword", "category1": "business", "category2": "finance", "endpoint_address": "10.0.0.50", "endpoint_port": 11434, "endpoint_weight": 2, "cache_enabled": false, "cache_backend": "milvus", "cache_threshold": 0.7, "guard_enabled": false, "guard_threshold": 0.7, "tools_enabled": true, "deployment_context": "ai-gateway"}}
{"id": "template_87918", "config": "# Semantic Router Configuration\n# Generated from template\n\ndecisions:\n  - name: \"business_decision\"\n    modelRefs:\n      - model: \"qwen3\"\n        use_reasoning: true\n    signals:\n      - type: \"domain\"\n        categories:\n          - \"business\"\n          - \"sales\"\n\nmodel_config:\n  qwen3:\n    reasoning_family: \"qwen3\"\n    preferred_endpoints:\n      - \"endpoint_qwen3\"\n\nvllm_endpoints:\n  - name: \"endpoint_qwen3\"\n    address: \"192.168.1.100\"\n    port: 8002\n    weight: 3\n\nsemantic_cache:\n  enabled: False\n  backend_type: \"milvus\"\n  similarity_threshold: 0.9\n  max_entries: 1000\n  ttl_seconds: 3600\n\nprompt_guard:\n  enabled: False\n  threshold: 0.8\n  use_modernbert: true\n\ntools:\n  enabled: False\n  top_k: 3\n  similarity_threshold: 0.2\n", "intent": "Route queries to qwen3, using domain-based routing, for istio deployment", "deployment_context": "istio", "source": "template", "values": {"decision_name": "business_decision", "model_name": "qwen3", "signal_type": "domain", "category1": "business", "category2": "sales", "endpoint_address": "192.168.1.100", "endpoint_port": 8002, "endpoint_weight": 3, "cache_enabled": false, "cache_backend": "milvus", "cache_threshold": 0.9, "guard_enabled": false, "guard_threshold": 0.8, "tools_enabled": false, "deployment_context": "istio"}}
{"id": "template_3453", "config": "# Semantic Router Configuration\n# Generated from template\n\ndecisions:\n  - name: \"support_decision\"\n    modelRefs:\n      - model: \"qwen3\"\n        use_reasoning: true\n    signals:\n      - type: \"embedding\"\n        categories:\n          - \"business\"\n          - \"finance\"\n\nmodel_config:\n  qwen3:\n    reasoning_family: \"qwen3\"\n    preferred_endpoints:\n      - \"endpoint_qwen3\"\n\nvllm_endpoints:\n  - name: \"endpoint_qwen3\"\n    address: \"10.0.0.50\"\n    port: 8002\n    weight: 1\n\nsemantic_cache:\n  enabled: True\n  backend_type: \"memory\"\n  similarity_threshold: 0.9\n  max_entries: 1000\n  ttl_seconds: 3600\n\nprompt_guard:\n  enabled: True\n  threshold: 0.8\n  use_modernbert: true\n\ntools:\n  enabled: True\n  top_k: 3\n  similarity_threshold: 0.2\n", "intent": "Route queries to qwen3, using embedding-based routing, with memory semantic cache, with PII detection, with tools auto-selection, for istio deployment", "deployment_context": "istio", "source": "template", "values": {"decision_name": "support_decision", "model_name": "qwen3", "signal_type": "embedding", "category1": "business", "category2": "finance", "endpoint_address": "10.0.0.50", "endpoint_port": 8002, "endpoint_weight": 1, "cache_enabled": true, "cache_backend": "memory", "cache_threshold": 0.9, "guard_enabled": true, "guard_threshold": 0.8, "tools_enabled": true, "deployment_context": "istio"}}
{"id": "template_56200", "config": "# Semantic Router Configuration\n# Generated from template\n\ndecisions:\n  - name: \"business_decision\"\n    modelRefs:\n      - model: \"phi4\"\n        use_reasoning: true\n    signals:\n      - type: \"embedding\"\n        categories:\n          - \"support\"\n          - \"engineering\"\n\nmodel_config:\n  phi4:\n    reasoning_family: \"phi4\"\n    preferred_endpoints:\n      - \"endpoint_phi4\"\n\nvllm_endpoints:\n  - name: \"endpoint_phi4\"\n    address: \"10.0.0.50\"\n    port: 8002\n    weight: 2\n\nsemantic_cache:\n  enabled: True\n  backend_type: \"milvus\"\n  similarity_threshold: 0.9\n  max_entries: 1000\n  ttl_seconds: 3600\n\nprompt_guard:\n  enabled: False\n  threshold: 0.8\n  use_modernbert: true\n\ntools:\n  enabled: False\n  top_k: 3\n  similarity_threshold: 0.2\n", "intent": "Route queries to phi4, using embedding-based routing, with milvus semantic cache, for kubernetes deployment", "deployment_context": "kubernetes", "source": "template", "values": {"decision_name": "business_decision", "model_name": "phi4", "signal_type": "embedding", "category1": "support", "category2": "engineering", "endpoint_address": "10.0.0.50", "endpoint_port": 8002, "endpoint_weight": 2, "cache_enabled": true, "cache_backend": "milvus", "cache_threshold": 0.9, "guard_enabled": false, "guard_threshold": 0.8, "tools_enabled": false, "deployment_context": "kubernetes"}}
{"id": "template_65997", "config": "# Semantic Router Configuration\n# Generated from template\n\ndecisions:\n  - name: \"general_decision\"\n    modelRefs:\n      - model: \"phi4\"\n        use_reasoning: true\n    signals:\n      - type: \"domain\"\n        categories:\n          - \"support\"\n          - \"sales\"\n\nmodel_config:\n  phi4:\n    reasoning_family: \"phi4\"\n    preferred_endpoints:\n      - \"endpoint_phi4\"\n\nvllm_endpoints:\n  - name: \"endpoint_phi4\"\n    address: \"172.28.0.20\"\n    port: 8000\n    weight: 1\n\nsemantic_cache:\n  enabled: False\n  backend_type: \"memory\"\n  similarity_threshold: 0.8\n  max_entries: 1000\n  ttl_seconds: 3600\n\nprompt_guard:\n  enabled: False\n  threshold: 0.8\n  use_modernbert: true\n\ntools:\n  enabled: True\n  top_k: 3\n  similarity_threshold: 0.2\n", "intent": "Route queries to phi4, using domain-based routing, with tools auto-selection, for kubernetes deployment", "deployment_context": "kubernetes", "source": "template", "values": {"decision_name": "general_decision", "model_name": "phi4", "signal_type": "domain", "category1": "support", "category2": "sales", "endpoint_address": "172.28.0.20", "endpoint_port": 8000, "endpoint_weight": 1, "cache_enabled": false, "cache_backend": "memory", "cache_threshold": 0.8, "guard_enabled": false, "guard_threshold": 0.8, "tools_enabled": true, "deployment_context": "kubernetes"}}
{"id": "template_53461", "config": "# Semantic Router Configuration\n# Generated from template\n\ndecisions:\n  - name: \"support_decision\"\n    modelRefs:\n      - model: \"qwen3\"\n        use_reasoning: true\n    signals:\n      - type: \"embedding\"\n        categories:\n          - \"technical\"\n          - \"sales\"\n\nmodel_config:\n  qwen3:\n    reasoning_family: \"qwen3\"\n    preferred_endpoints:\n      - \"endpoint_qwen3\"\n\nvllm_endpoints:\n  - name: \"endpoint_qwen3\"\n    address: \"10.0.0.50\"\n    port: 8002\n    weight: 1\n\nsemantic_cache:\n  enabled: True\n  backend_type: \"redis\"\n  similarity_threshold: 0.8\n  max_entries: 1000\n  ttl_seconds: 3600\n\nprompt_guard:\n  enabled: False\n  threshold: 0.8\n  use_modernbert: true\n\ntools:\n  enabled: True\n  top_k: 3\n  similarity_threshold: 0.2\n", "intent": "Route queries to qwen3, using embedding-based routing, with redis semantic cache, with tools auto-selection, for quickstart deployment", "deployment_context": "quickstart", "source": "template", "values": {"decision_name": "support_decision", "model_name": "qwen3", "signal_type": "embedding", "category1": "technical", "category2": "sales", "endpoint_address": "10.0.0.50", "endpoint_port": 8002, "endpoint_weight": 1, "cache_enabled": true, "cache_backend": "redis", "cache_threshold": 0.8, "guard_enabled": false, "guard_threshold": 0.8, "tools_enabled": true, "deployment_context": "quickstart"}}
{"id": "template_27838", "config": "# Semantic Router Configuration\n# Generated from template\n\ndecisions:\n  - name: \"general_decision\"\n    modelRefs:\n      - model: \"phi4\"\n        use_reasoning: true\n    signals:\n      - type: \"keyword\"\n        categories:\n          - \"support\"\n          - \"engineering\"\n\nmodel_config:\n  phi4:\n    reasoning_family: \"phi4\"\n    preferred_endpoints:\n      - \"endpoint_phi4\"\n\nvllm_endpoints:\n  - name: \"endpoint_phi4\"\n    address: \"172.28.0.20\"\n    port: 8002\n    weight: 2\n\nsemantic_cache:\n  enabled: True\n  backend_type: \"redis\"\n  similarity_threshold: 0.8\n  max_entries: 1000\n  ttl_seconds: 3600\n\nprompt_guard:\n  enabled: True\n  threshold: 0.6\n  use_modernbert: true\n\ntools:\n  enabled: True\n  top_k: 3\n  similarity_threshold: 0.2\n", "intent": "Route queries to phi4, using keyword-based routing, with redis semantic cache, with PII detection, with tools auto-selection, for ai-gateway deployment", "deployment_context": "ai-gateway", "source": "template", "values": {"decision_name": "general_decision", "model_name": "phi4", "signal_type": "keyword", "category1": "support", "category2": "engineering", "endpoint_address": "172.28.0.20", "endpoint_port": 8002, "endpoint_weight": 2, "cache_enabled": true, "cache_backend": "redis", "cache_threshold": 0.8, "guard_enabled": true, "guard_threshold": 0.6, "tools_enabled": true, "deployment_context": "ai-gateway"}}
{"id": "template_14081", "config": "# Semantic Router Configuration\n# Generated from template\n\ndecisions:\n  - name: \"business_decision\"\n    modelRefs:\n      - model: \"phi4\"\n        use_reasoning: true\n    signals:\n      - type: \"embedding\"\n        categories:\n          - \"support\"\n          - \"sales\"\n\nmodel_config:\n  phi4:\n    reasoning_family: \"phi4\"\n    preferred_endpoints:\n      - \"endpoint_phi4\"\n\nvllm_endpoints:\n  - name: \"endpoint_phi4\"\n    address: \"192.168.1.100\"\n    port: 8002\n    weight: 1\n\nsemantic_cache:\n  enabled: True\n  backend_type: \"redis\"\n  similarity_threshold: 0.7\n  max_entries: 1000\n  ttl_seconds: 3600\n\nprompt_guard:\n  enabled: False\n  threshold: 0.6\n  use_modernbert: true\n\ntools:\n  enabled: True\n  top_k: 3\n  similarity_threshold: 0.2\n", "intent": "Route queries to phi4, using embedding-based routing, with redis semantic cache, with tools auto-selection, for kubernetes deployment", "deployment_context": "kubernetes", "source": "template", "values": {"decision_name": "business_decision", "model_name": "phi4", "signal_type": "embedding", "category1": "support", "category2": "sales", "endpoint_address": "192.168.1.100", "endpoint_port": 8002, "endpoint_weight": 1, "cache_enabled": true, "cache_backend": "redis", "cache_threshold": 0.7, "guard_enabled": false, "guard_threshold": 0.6, "tools_enabled": true, "deployment_context": "kubernetes"}}
{"id": "template_6961", "config": "# Semantic Router Configuration\n# Generated from template\n\ndecisions:\n  - name: \"general_decision\"\n    modelRefs:\n      - model: \"llama3\"\n        use_reasoning: true\n    signals:\n      - type: \"embedding\"\n        categories:\n          - \"general\"\n          - \"customer_service\"\n\nmodel_config:\n  llama3:\n    reasoning_family: \"llama3\"\n    preferred_endpoints:\n      - \"endpoint_llama3\"\n\nvllm_endpoints:\n  - name: \"endpoint_llama3\"\n    address: \"172.16.0.10\"\n    port: 8002\n    weight: 2\n\nsemantic_cache:\n  enabled: False\n  backend_type: \"milvus\"\n  similarity_threshold: 0.8\n  max_entries: 1000\n  ttl_seconds: 3600\n\nprompt_guard:\n  enabled: False\n  threshold: 0.8\n  use_modernbert: true\n\ntools:\n  enabled: True\n  top_k: 3\n  similarity_threshold: 0.2\n", "intent": "Route queries to llama3, using embedding-based routing, with tools auto-selection, for ai-gateway deployment", "deployment_context": "ai-gateway", "source": "template", "values": {"decision_name": "general_decision", "model_name": "llama3", "signal_type": "embedding", "category1": "general", "category2": "customer_service", "endpoint_address": "172.16.0.10", "endpoint_port": 8002, "endpoint_weight": 2, "cache_enabled": false, "cache_backend": "milvus", "cache_threshold": 0.8, "guard_enabled": false, "guard_threshold": 0.8, "tools_enabled": true, "deployment_context": "ai-gateway"}}
{"id": "template_45671", "config": "# Semantic Router Configuration\n# Generated from template\n\ndecisions:\n  - name: \"business_decision\"\n    modelRefs:\n      - model: \"phi4\"\n        use_reasoning: true\n    signals:\n      - type: \"domain\"\n        categories:\n          - \"general\"\n          - \"customer_service\"\n\nmodel_config:\n  phi4:\n    reasoning_family: \"phi4\"\n    preferred_endpoints:\n      - \"endpoint_phi4\"\n\nvllm_endpoints:\n  - name: \"endpoint_phi4\"\n    address: \"192.168.1.100\"\n    port: 8002\n    weight: 2\n\nsemantic_cache:\n  enabled: False\n  backend_type: \"memory\"\n  similarity_threshold: 0.9\n  max_entries: 1000\n  ttl_seconds: 3600\n\nprompt_guard:\n  enabled: True\n  threshold: 0.7\n  use_modernbert: true\n\ntools:\n  enabled: True\n  top_k: 3\n  similarity_threshold: 0.2\n", "intent": "Route queries to phi4, using domain-based routing, with PII detection, with tools auto-selection, for kubernetes deployment", "deployment_context": "kubernetes", "source": "template", "values": {"decision_name": "business_decision", "model_name": "phi4", "signal_type": "domain", "category1": "general", "category2": "customer_service", "endpoint_address": "192.168.1.100", "endpoint_port": 8002, "endpoint_weight": 2, "cache_enabled": false, "cache_backend": "memory", "cache_threshold": 0.9, "guard_enabled": true, "guard_threshold": 0.7, "tools_enabled": true, "deployment_context": "kubernetes"}}
{"id": "template_89611", "config": "# Semantic Router Configuration\n# Generated from template\n\ndecisions:\n  - name: \"technical_decision\"\n    modelRefs:\n      - model: \"qwen3\"\n        use_reasoning: true\n    signals:\n      - type: \"domain\"\n        categories:\n          - \"support\"\n          - \"sales\"\n\nmodel_config:\n  qwen3:\n    reasoning_family: \"qwen3\"\n    preferred_endpoints:\n      - \"endpoint_qwen3\"\n\nvllm_endpoints:\n  - name: \"endpoint_qwen3\"\n    address: \"172.28.0.20\"\n    port: 11434\n    weight: 1\n\nsemantic_cache:\n  enabled: False\n  backend_type: \"redis\"\n  similarity_threshold: 0.9\n  max_entries: 1000\n  ttl_seconds: 3600\n\nprompt_guard:\n  enabled: True\n  threshold: 0.6\n  use_modernbert: true\n\ntools:\n  enabled: False\n  top_k: 3\n  similarity_threshold: 0.2\n", "intent": "Route queries to qwen3, using domain-based routing, with PII detection, for quickstart deployment", "deployment_context": "quickstart", "source": "template", "values": {"decision_name": "technical_decision", "model_name": "qwen3", "signal_type": "domain", "category1": "support", "category2": "sales", "endpoint_address": "172.28.0.20", "endpoint_port": 11434, "endpoint_weight": 1, "cache_enabled": false, "cache_backend": "redis", "cache_threshold": 0.9, "guard_enabled": true, "guard_threshold": 0.6, "tools_enabled": false, "deployment_context": "quickstart"}}
{"id": "template_85322", "config": "# Semantic Router Configuration\n# Generated from template\n\ndecisions:\n  - name: \"business_decision\"\n    modelRefs:\n      - model: \"qwen3\"\n        use_reasoning: true\n    signals:\n      - type: \"domain\"\n        categories:\n          - \"support\"\n          - \"finance\"\n\nmodel_config:\n  qwen3:\n    reasoning_family: \"qwen3\"\n    preferred_endpoints:\n      - \"endpoint_qwen3\"\n\nvllm_endpoints:\n  - name: \"endpoint_qwen3\"\n    address: \"192.168.1.100\"\n    port: 8080\n    weight: 1\n\nsemantic_cache:\n  enabled: True\n  backend_type: \"memory\"\n  similarity_threshold: 0.9\n  max_entries: 1000\n  ttl_seconds: 3600\n\nprompt_guard:\n  enabled: False\n  threshold: 0.8\n  use_modernbert: true\n\ntools:\n  enabled: True\n  top_k: 3\n  similarity_threshold: 0.2\n", "intent": "Route queries to qwen3, using domain-based routing, with memory semantic cache, with tools auto-selection, for istio deployment", "deployment_context": "istio", "source": "template", "values": {"decision_name": "business_decision", "model_name": "qwen3", "signal_type": "domain", "category1": "support", "category2": "finance", "endpoint_address": "192.168.1.100", "endpoint_port": 8080, "endpoint_weight": 1, "cache_enabled": true, "cache_backend": "memory", "cache_threshold": 0.9, "guard_enabled": false, "guard_threshold": 0.8, "tools_enabled": true, "deployment_context": "istio"}}
{"id": "template_9303", "config": "# Semantic Router Configuration\n# Generated from template\n\ndecisions:\n  - name: \"general_decision\"\n    modelRefs:\n      - model: \"phi4\"\n        use_reasoning: true\n    signals:\n      - type: \"domain\"\n        categories:\n          - \"technical\"\n          - \"sales\"\n\nmodel_config:\n  phi4:\n    reasoning_family: \"phi4\"\n    preferred_endpoints:\n      - \"endpoint_phi4\"\n\nvllm_endpoints:\n  - name: \"endpoint_phi4\"\n    address: \"192.168.1.100\"\n    port: 11434\n    weight: 1\n\nsemantic_cache:\n  enabled: True\n  backend_type: \"redis\"\n  similarity_threshold: 0.8\n  max_entries: 1000\n  ttl_seconds: 3600\n\nprompt_guard:\n  enabled: True\n  threshold: 0.6\n  use_modernbert: true\n\ntools:\n  enabled: True\n  top_k: 3\n  similarity_threshold: 0.2\n", "intent": "Route queries to phi4, using domain-based routing, with redis semantic cache, with PII detection, with tools auto-selection, for ai-gateway deployment", "deployment_context": "ai-gateway", "source": "template", "values": {"decision_name": "general_decision", "model_name": "phi4", "signal_type": "domain", "category1": "technical", "category2": "sales", "endpoint_address": "192.168.1.100", "endpoint_port": 11434, "endpoint_weight": 1, "cache_enabled": true, "cache_backend": "redis", "cache_threshold": 0.8, "guard_enabled": true, "guard_threshold": 0.6, "tools_enabled": true, "deployment_context": "ai-gateway"}}
{"id": "template_10120", "config": "# Semantic Router Configuration\n# Generated from template\n\ndecisions:\n  - name: \"business_decision\"\n    modelRefs:\n      - model: \"mistral\"\n        use_reasoning: true\n    signals:\n      - type: \"embedding\"\n        categories:\n          - \"technical\"\n          - \"finance\"\n\nmodel_config:\n  mistral:\n    reasoning_family: \"mistral\"\n    preferred_endpoints:\n      - \"endpoint_mistral\"\n\nvllm_endpoints:\n  - name: \"endpoint_mistral\"\n    address: \"192.168.1.100\"\n    port: 8080\n    weight: 3\n\nsemantic_cache:\n  enabled: True\n  backend_type: \"redis\"\n  similarity_threshold: 0.9\n  max_entries: 1000\n  ttl_seconds: 3600\n\nprompt_guard:\n  enabled: True\n  threshold: 0.8\n  use_modernbert: true\n\ntools:\n  enabled: True\n  top_k: 3\n  similarity_threshold: 0.2\n", "intent": "Route queries to mistral, using embedding-based routing, with redis semantic cache, with PII detection, with tools auto-selection, for istio deployment", "deployment_context": "istio", "source": "template", "values": {"decision_name": "business_decision", "model_name": "mistral", "signal_type": "embedding", "category1": "technical", "category2": "finance", "endpoint_address": "192.168.1.100", "endpoint_port": 8080, "endpoint_weight": 3, "cache_enabled": true, "cache_backend": "redis", "cache_threshold": 0.9, "guard_enabled": true, "guard_threshold": 0.8, "tools_enabled": true, "deployment_context": "istio"}}
{"id": "template_16427", "config": "# Semantic Router Configuration\n# Generated from template\n\ndecisions:\n  - name: \"technical_decision\"\n    modelRefs:\n      - model: \"phi4\"\n        use_reasoning: true\n    signals:\n      - type: \"domain\"\n        categories:\n          - \"general\"\n          - \"sales\"\n\nmodel_config:\n  phi4:\n    reasoning_family: \"phi4\"\n    preferred_endpoints:\n      - \"endpoint_phi4\"\n\nvllm_endpoints:\n  - name: \"endpoint_phi4\"\n    address: \"10.0.0.50\"\n    port: 8002\n    weight: 2\n\nsemantic_cache:\n  enabled: True\n  backend_type: \"memory\"\n  similarity_threshold: 0.7\n  max_entries: 1000\n  ttl_seconds: 3600\n\nprompt_guard:\n  enabled: True\n  threshold: 0.7\n  use_modernbert: true\n\ntools:\n  enabled: True\n  top_k: 3\n  similarity_threshold: 0.2\n", "intent": "Route queries to phi4, using domain-based routing, with memory semantic cache, with PII detection, with tools auto-selection, for kubernetes deployment", "deployment_context": "kubernetes", "source": "template", "values": {"decision_name": "technical_decision", "model_name": "phi4", "signal_type": "domain", "category1": "general", "category2": "sales", "endpoint_address": "10.0.0.50", "endpoint_port": 8002, "endpoint_weight": 2, "cache_enabled": true, "cache_backend": "memory", "cache_threshold": 0.7, "guard_enabled": true, "guard_threshold": 0.7, "tools_enabled": true, "deployment_context": "kubernetes"}}
{"id": "template_49708", "config": "# Semantic Router Configuration\n# Generated from template\n\ndecisions:\n  - name: \"general_decision\"\n    modelRefs:\n      - model: \"mistral\"\n        use_reasoning: true\n    signals:\n      - type: \"domain\"\n        categories:\n          - \"technical\"\n          - \"engineering\"\n\nmodel_config:\n  mistral:\n    reasoning_family: \"mistral\"\n    preferred_endpoints:\n      - \"endpoint_mistral\"\n\nvllm_endpoints:\n  - name: \"endpoint_mistral\"\n    address: \"192.168.1.100\"\n    port: 8002\n    weight: 1\n\nsemantic_cache:\n  enabled: False\n  backend_type: \"milvus\"\n  similarity_threshold: 0.8\n  max_entries: 1000\n  ttl_seconds: 3600\n\nprompt_guard:\n  enabled: True\n  threshold: 0.6\n  use_modernbert: true\n\ntools:\n  enabled: True\n  top_k: 3\n  similarity_threshold: 0.2\n", "intent": "Route queries to mistral, using domain-based routing, with PII detection, with tools auto-selection, for ai-gateway deployment", "deployment_context": "ai-gateway", "source": "template", "values": {"decision_name": "general_decision", "model_name": "mistral", "signal_type": "domain", "category1": "technical", "category2": "engineering", "endpoint_address": "192.168.1.100", "endpoint_port": 8002, "endpoint_weight": 1, "cache_enabled": false, "cache_backend": "milvus", "cache_threshold": 0.8, "guard_enabled": true, "guard_threshold": 0.6, "tools_enabled": true, "deployment_context": "ai-gateway"}}
{"id": "template_96202", "config": "# Semantic Router Configuration\n# Generated from template\n\ndecisions:\n  - name: \"business_decision\"\n    modelRefs:\n      - model: \"llama3\"\n        use_reasoning: true\n    signals:\n      - type: \"keyword\"\n        categories:\n          - \"technical\"\n          - \"sales\"\n\nmodel_config:\n  llama3:\n    reasoning_family: \"llama3\"\n    preferred_endpoints:\n      - \"endpoint_llama3\"\n\nvllm_endpoints:\n  - name: \"endpoint_llama3\"\n    address: \"192.168.1.100\"\n    port: 8002\n    weight: 2\n\nsemantic_cache:\n  enabled: False\n  backend_type: \"redis\"\n  similarity_threshold: 0.9\n  max_entries: 1000\n  ttl_seconds: 3600\n\nprompt_guard:\n  enabled: True\n  threshold: 0.8\n  use_modernbert: true\n\ntools:\n  enabled: True\n  top_k: 3\n  similarity_threshold: 0.2\n", "intent": "Route queries to llama3, using keyword-based routing, with PII detection, with tools auto-selection, for kubernetes deployment", "deployment_context": "kubernetes", "source": "template", "values": {"decision_name": "business_decision", "model_name": "llama3", "signal_type": "keyword", "category1": "technical", "category2": "sales", "endpoint_address": "192.168.1.100", "endpoint_port": 8002, "endpoint_weight": 2, "cache_enabled": false, "cache_backend": "redis", "cache_threshold": 0.9, "guard_enabled": true, "guard_threshold": 0.8, "tools_enabled": true, "deployment_context": "kubernetes"}}
{"id": "template_95799", "config": "# Semantic Router Configuration\n# Generated from template\n\ndecisions:\n  - name: \"business_decision\"\n    modelRefs:\n      - model: \"phi4\"\n        use_reasoning: true\n    signals:\n      - type: \"embedding\"\n        categories:\n          - \"support\"\n          - \"customer_service\"\n\nmodel_config:\n  phi4:\n    reasoning_family: \"phi4\"\n    preferred_endpoints:\n      - \"endpoint_phi4\"\n\nvllm_endpoints:\n  - name: \"endpoint_phi4\"\n    address: \"10.0.0.50\"\n    port: 11434\n    weight: 1\n\nsemantic_cache:\n  enabled: False\n  backend_type: \"redis\"\n  similarity_threshold: 0.9\n  max_entries: 1000\n  ttl_seconds: 3600\n\nprompt_guard:\n  enabled: False\n  threshold: 0.6\n  use_modernbert: true\n\ntools:\n  enabled: True\n  top_k: 3\n  similarity_threshold: 0.2\n", "intent": "Route queries to phi4, using embedding-based routing, with tools auto-selection, for istio deployment", "deployment_context": "istio", "source": "template", "values": {"decision_name": "business_decision", "model_name": "phi4", "signal_type": "embedding", "category1": "support", "category2": "customer_service", "endpoint_address": "10.0.0.50", "endpoint_port": 11434, "endpoint_weight": 1, "cache_enabled": false, "cache_backend": "redis", "cache_threshold": 0.9, "guard_enabled": false, "guard_threshold": 0.6, "tools_enabled": true, "deployment_context": "istio"}}
{"id": "template_26512", "config": "# Semantic Router Configuration\n# Generated from template\n\ndecisions:\n  - name: \"support_decision\"\n    modelRefs:\n      - model: \"phi4\"\n        use_reasoning: true\n    signals:\n      - type: \"keyword\"\n        categories:\n          - \"business\"\n          - \"sales\"\n\nmodel_config:\n  phi4:\n    reasoning_family: \"phi4\"\n    preferred_endpoints:\n      - \"endpoint_phi4\"\n\nvllm_endpoints:\n  - name: \"endpoint_phi4\"\n    address: \"10.0.0.50\"\n    port: 8080\n    weight: 1\n\nsemantic_cache:\n  enabled: True\n  backend_type: \"milvus\"\n  similarity_threshold: 0.9\n  max_entries: 1000\n  ttl_seconds: 3600\n\nprompt_guard:\n  enabled: True\n  threshold: 0.7\n  use_modernbert: true\n\ntools:\n  enabled: True\n  top_k: 3\n  similarity_threshold: 0.2\n", "intent": "Route queries to phi4, using keyword-based routing, with milvus semantic cache, with PII detection, with tools auto-selection, for quickstart deployment", "deployment_context": "quickstart", "source": "template", "values": {"decision_name": "support_decision", "model_name": "phi4", "signal_type": "keyword", "category1": "business", "category2": "sales", "endpoint_address": "10.0.0.50", "endpoint_port": 8080, "endpoint_weight": 1, "cache_enabled": true, "cache_backend": "milvus", "cache_threshold": 0.9, "guard_enabled": true, "guard_threshold": 0.7, "tools_enabled": true, "deployment_context": "quickstart"}}
{"id": "template_5524", "config": "# Semantic Router Configuration\n# Generated from template\n\ndecisions:\n  - name: \"business_decision\"\n    modelRefs:\n      - model: \"mistral\"\n        use_reasoning: true\n    signals:\n      - type: \"embedding\"\n        categories:\n          - \"support\"\n          - \"sales\"\n\nmodel_config:\n  mistral:\n    reasoning_family: \"mistral\"\n    preferred_endpoints:\n      - \"endpoint_mistral\"\n\nvllm_endpoints:\n  - name: \"endpoint_mistral\"\n    address: \"10.0.0.50\"\n    port: 8080\n    weight: 2\n\nsemantic_cache:\n  enabled: False\n  backend_type: \"redis\"\n  similarity_threshold: 0.7\n  max_entries: 1000\n  ttl_seconds: 3600\n\nprompt_guard:\n  enabled: True\n  threshold: 0.7\n  use_modernbert: true\n\ntools:\n  enabled: False\n  top_k: 3\n  similarity_threshold: 0.2\n", "intent": "Route queries to mistral, using embedding-based routing, with PII detection, for quickstart deployment", "deployment_context": "quickstart", "source": "template", "values": {"decision_name": "business_decision", "model_name": "mistral", "signal_type": "embedding", "category1": "support", "category2": "sales", "endpoint_address": "10.0.0.50", "endpoint_port": 8080, "endpoint_weight": 2, "cache_enabled": false, "cache_backend": "redis", "cache_threshold": 0.7, "guard_enabled": true, "guard_threshold": 0.7, "tools_enabled": false, "deployment_context": "quickstart"}}
{"id": "template_13670", "config": "# Semantic Router Configuration\n# Generated from template\n\ndecisions:\n  - name: \"business_decision\"\n    modelRefs:\n      - model: \"phi4\"\n        use_reasoning: true\n    signals:\n      - type: \"domain\"\n        categories:\n          - \"support\"\n          - \"engineering\"\n\nmodel_config:\n  phi4:\n    reasoning_family: \"phi4\"\n    preferred_endpoints:\n      - \"endpoint_phi4\"\n\nvllm_endpoints:\n  - name: \"endpoint_phi4\"\n    address: \"192.168.1.100\"\n    port: 8002\n    weight: 2\n\nsemantic_cache:\n  enabled: False\n  backend_type: \"memory\"\n  similarity_threshold: 0.7\n  max_entries: 1000\n  ttl_seconds: 3600\n\nprompt_guard:\n  enabled: False\n  threshold: 0.7\n  use_modernbert: true\n\ntools:\n  enabled: False\n  top_k: 3\n  similarity_threshold: 0.2\n", "intent": "Route queries to phi4, using domain-based routing, for kubernetes deployment", "deployment_context": "kubernetes", "source": "template", "values": {"decision_name": "business_decision", "model_name": "phi4", "signal_type": "domain", "category1": "support", "category2": "engineering", "endpoint_address": "192.168.1.100", "endpoint_port": 8002, "endpoint_weight": 2, "cache_enabled": false, "cache_backend": "memory", "cache_threshold": 0.7, "guard_enabled": false, "guard_threshold": 0.7, "tools_enabled": false, "deployment_context": "kubernetes"}}
{"id": "template_28466", "config": "# Semantic Router Configuration\n# Generated from template\n\ndecisions:\n  - name: \"business_decision\"\n    modelRefs:\n      - model: \"mistral\"\n        use_reasoning: true\n    signals:\n      - type: \"embedding\"\n        categories:\n          - \"support\"\n          - \"sales\"\n\nmodel_config:\n  mistral:\n    reasoning_family: \"mistral\"\n    preferred_endpoints:\n      - \"endpoint_mistral\"\n\nvllm_endpoints:\n  - name: \"endpoint_mistral\"\n    address: \"192.168.1.100\"\n    port: 8002\n    weight: 3\n\nsemantic_cache:\n  enabled: False\n  backend_type: \"milvus\"\n  similarity_threshold: 0.8\n  max_entries: 1000\n  ttl_seconds: 3600\n\nprompt_guard:\n  enabled: True\n  threshold: 0.8\n  use_modernbert: true\n\ntools:\n  enabled: False\n  top_k: 3\n  similarity_threshold: 0.2\n", "intent": "Route queries to mistral, using embedding-based routing, with PII detection, for kubernetes deployment", "deployment_context": "kubernetes", "source": "template", "values": {"decision_name": "business_decision", "model_name": "mistral", "signal_type": "embedding", "category1": "support", "category2": "sales", "endpoint_address": "192.168.1.100", "endpoint_port": 8002, "endpoint_weight": 3, "cache_enabled": false, "cache_backend": "milvus", "cache_threshold": 0.8, "guard_enabled": true, "guard_threshold": 0.8, "tools_enabled": false, "deployment_context": "kubernetes"}}
{"id": "template_7239", "config": "# Semantic Router Configuration\n# Generated from template\n\ndecisions:\n  - name: \"support_decision\"\n    modelRefs:\n      - model: \"phi4\"\n        use_reasoning: true\n    signals:\n      - type: \"domain\"\n        categories:\n          - \"general\"\n          - \"engineering\"\n\nmodel_config:\n  phi4:\n    reasoning_family: \"phi4\"\n    preferred_endpoints:\n      - \"endpoint_phi4\"\n\nvllm_endpoints:\n  - name: \"endpoint_phi4\"\n    address: \"10.0.0.50\"\n    port: 11434\n    weight: 2\n\nsemantic_cache:\n  enabled: True\n  backend_type: \"redis\"\n  similarity_threshold: 0.8\n  max_entries: 1000\n  ttl_seconds: 3600\n\nprompt_guard:\n  enabled: True\n  threshold: 0.7\n  use_modernbert: true\n\ntools:\n  enabled: True\n  top_k: 3\n  similarity_threshold: 0.2\n", "intent": "Route queries to phi4, using domain-based routing, with redis semantic cache, with PII detection, with tools auto-selection, for istio deployment", "deployment_context": "istio", "source": "template", "values": {"decision_name": "support_decision", "model_name": "phi4", "signal_type": "domain", "category1": "general", "category2": "engineering", "endpoint_address": "10.0.0.50", "endpoint_port": 11434, "endpoint_weight": 2, "cache_enabled": true, "cache_backend": "redis", "cache_threshold": 0.8, "guard_enabled": true, "guard_threshold": 0.7, "tools_enabled": true, "deployment_context": "istio"}}
{"id": "template_26100", "config": "# Semantic Router Configuration\n# Generated from template\n\ndecisions:\n  - name: \"support_decision\"\n    modelRefs:\n      - model: \"phi4\"\n        use_reasoning: true\n    signals:\n      - type: \"embedding\"\n        categories:\n          - \"support\"\n          - \"finance\"\n\nmodel_config:\n  phi4:\n    reasoning_family: \"phi4\"\n    preferred_endpoints:\n      - \"endpoint_phi4\"\n\nvllm_endpoints:\n  - name: \"endpoint_phi4\"\n    address: \"172.28.0.20\"\n    port: 11434\n    weight: 2\n\nsemantic_cache:\n  enabled: False\n  backend_type: \"redis\"\n  similarity_threshold: 0.7\n  max_entries: 1000\n  ttl_seconds: 3600\n\nprompt_guard:\n  enabled: False\n  threshold: 0.7\n  use_modernbert: true\n\ntools:\n  enabled: False\n  top_k: 3\n  similarity_threshold: 0.2\n", "intent": "Route queries to phi4, using embedding-based routing, for kubernetes deployment", "deployment_context": "kubernetes", "source": "template", "values": {"decision_name": "support_decision", "model_name": "phi4", "signal_type": "embedding", "category1": "support", "category2": "finance", "endpoint_address": "172.28.0.20", "endpoint_port": 11434, "endpoint_weight": 2, "cache_enabled": false, "cache_backend": "redis", "cache_threshold": 0.7, "guard_enabled": false, "guard_threshold": 0.7, "tools_enabled": false, "deployment_context": "kubernetes"}}
{"id": "template_21479", "config": "# Semantic Router Configuration\n# Generated from template\n\ndecisions:\n  - name: \"general_decision\"\n    modelRefs:\n      - model: \"qwen3\"\n        use_reasoning: true\n    signals:\n      - type: \"domain\"\n        categories:\n          - \"general\"\n          - \"sales\"\n\nmodel_config:\n  qwen3:\n    reasoning_family: \"qwen3\"\n    preferred_endpoints:\n      - \"endpoint_qwen3\"\n\nvllm_endpoints:\n  - name: \"endpoint_qwen3\"\n    address: \"192.168.1.100\"\n    port: 8080\n    weight: 1\n\nsemantic_cache:\n  enabled: True\n  backend_type: \"redis\"\n  similarity_threshold: 0.8\n  max_entries: 1000\n  ttl_seconds: 3600\n\nprompt_guard:\n  enabled: True\n  threshold: 0.8\n  use_modernbert: true\n\ntools:\n  enabled: True\n  top_k: 3\n  similarity_threshold: 0.2\n", "intent": "Route queries to qwen3, using domain-based routing, with redis semantic cache, with PII detection, with tools auto-selection, for kubernetes deployment", "deployment_context": "kubernetes", "source": "template", "values": {"decision_name": "general_decision", "model_name": "qwen3", "signal_type": "domain", "category1": "general", "category2": "sales", "endpoint_address": "192.168.1.100", "endpoint_port": 8080, "endpoint_weight": 1, "cache_enabled": true, "cache_backend": "redis", "cache_threshold": 0.8, "guard_enabled": true, "guard_threshold": 0.8, "tools_enabled": true, "deployment_context": "kubernetes"}}
{"id": "template_84974", "config": "# Semantic Router Configuration\n# Generated from template\n\ndecisions:\n  - name: \"business_decision\"\n    modelRefs:\n      - model: \"llama3\"\n        use_reasoning: true\n    signals:\n      - type: \"domain\"\n        categories:\n          - \"technical\"\n          - \"sales\"\n\nmodel_config:\n  llama3:\n    reasoning_family: \"llama3\"\n    preferred_endpoints:\n      - \"endpoint_llama3\"\n\nvllm_endpoints:\n  - name: \"endpoint_llama3\"\n    address: \"172.28.0.20\"\n    port: 8080\n    weight: 1\n\nsemantic_cache:\n  enabled: True\n  backend_type: \"redis\"\n  similarity_threshold: 0.9\n  max_entries: 1000\n  ttl_seconds: 3600\n\nprompt_guard:\n  enabled: True\n  threshold: 0.8\n  use_modernbert: true\n\ntools:\n  enabled: True\n  top_k: 3\n  similarity_threshold: 0.2\n", "intent": "Route queries to llama3, using domain-based routing, with redis semantic cache, with PII detection, with tools auto-selection, for quickstart deployment", "deployment_context": "quickstart", "source": "template", "values": {"decision_name": "business_decision", "model_name": "llama3", "signal_type": "domain", "category1": "technical", "category2": "sales", "endpoint_address": "172.28.0.20", "endpoint_port": 8080, "endpoint_weight": 1, "cache_enabled": true, "cache_backend": "redis", "cache_threshold": 0.9, "guard_enabled": true, "guard_threshold": 0.8, "tools_enabled": true, "deployment_context": "quickstart"}}
{"id": "template_71362", "config": "# Semantic Router Configuration\n# Generated from template\n\ndecisions:\n  - name: \"business_decision\"\n    modelRefs:\n      - model: \"phi4\"\n        use_reasoning: true\n    signals:\n      - type: \"keyword\"\n        categories:\n          - \"general\"\n          - \"customer_service\"\n\nmodel_config:\n  phi4:\n    reasoning_family: \"phi4\"\n    preferred_endpoints:\n      - \"endpoint_phi4\"\n\nvllm_endpoints:\n  - name: \"endpoint_phi4\"\n    address: \"172.16.0.10\"\n    port: 8002\n    weight: 3\n\nsemantic_cache:\n  enabled: False\n  backend_type: \"redis\"\n  similarity_threshold: 0.8\n  max_entries: 1000\n  ttl_seconds: 3600\n\nprompt_guard:\n  enabled: True\n  threshold: 0.8\n  use_modernbert: true\n\ntools:\n  enabled: True\n  top_k: 3\n  similarity_threshold: 0.2\n", "intent": "Route queries to phi4, using keyword-based routing, with PII detection, with tools auto-selection, for quickstart deployment", "deployment_context": "quickstart", "source": "template", "values": {"decision_name": "business_decision", "model_name": "phi4", "signal_type": "keyword", "category1": "general", "category2": "customer_service", "endpoint_address": "172.16.0.10", "endpoint_port": 8002, "endpoint_weight": 3, "cache_enabled": false, "cache_backend": "redis", "cache_threshold": 0.8, "guard_enabled": true, "guard_threshold": 0.8, "tools_enabled": true, "deployment_context": "quickstart"}}
{"id": "template_3854", "config": "# Semantic Router Configuration\n# Generated from template\n\ndecisions:\n  - name: \"business_decision\"\n    modelRefs:\n      - model: \"phi4\"\n        use_reasoning: true\n    signals:\n      - type: \"keyword\"\n        categories:\n          - \"general\"\n          - \"finance\"\n\nmodel_config:\n  phi4:\n    reasoning_family: \"phi4\"\n    preferred_endpoints:\n      - \"endpoint_phi4\"\n\nvllm_endpoints:\n  - name: \"endpoint_phi4\"\n    address: \"172.28.0.20\"\n    port: 8000\n    weight: 2\n\nsemantic_cache:\n  enabled: True\n  backend_type: \"redis\"\n  similarity_threshold: 0.9\n  max_entries: 1000\n  ttl_seconds: 3600\n\nprompt_guard:\n  enabled: True\n  threshold: 0.8\n  use_modernbert: true\n\ntools:\n  enabled: False\n  top_k: 3\n  similarity_threshold: 0.2\n", "intent": "Route queries to phi4, using keyword-based routing, with redis semantic cache, with PII detection, for quickstart deployment", "deployment_context": "quickstart", "source": "template", "values": {"decision_name": "business_decision", "model_name": "phi4", "signal_type": "keyword", "category1": "general", "category2": "finance", "endpoint_address": "172.28.0.20", "endpoint_port": 8000, "endpoint_weight": 2, "cache_enabled": true, "cache_backend": "redis", "cache_threshold": 0.9, "guard_enabled": true, "guard_threshold": 0.8, "tools_enabled": false, "deployment_context": "quickstart"}}
{"id": "template_41083", "config": "# Semantic Router Configuration\n# Generated from template\n\ndecisions:\n  - name: \"technical_decision\"\n    modelRefs:\n      - model: \"llama3\"\n        use_reasoning: true\n    signals:\n      - type: \"embedding\"\n        categories:\n          - \"support\"\n          - \"finance\"\n\nmodel_config:\n  llama3:\n    reasoning_family: \"llama3\"\n    preferred_endpoints:\n      - \"endpoint_llama3\"\n\nvllm_endpoints:\n  - name: \"endpoint_llama3\"\n    address: \"192.168.1.100\"\n    port: 8000\n    weight: 1\n\nsemantic_cache:\n  enabled: False\n  backend_type: \"memory\"\n  similarity_threshold: 0.7\n  max_entries: 1000\n  ttl_seconds: 3600\n\nprompt_guard:\n  enabled: False\n  threshold: 0.6\n  use_modernbert: true\n\ntools:\n  enabled: False\n  top_k: 3\n  similarity_threshold: 0.2\n", "intent": "Route queries to llama3, using embedding-based routing, for ai-gateway deployment", "deployment_context": "ai-gateway", "source": "template", "values": {"decision_name": "technical_decision", "model_name": "llama3", "signal_type": "embedding", "category1": "support", "category2": "finance", "endpoint_address": "192.168.1.100", "endpoint_port": 8000, "endpoint_weight": 1, "cache_enabled": false, "cache_backend": "memory", "cache_threshold": 0.7, "guard_enabled": false, "guard_threshold": 0.6, "tools_enabled": false, "deployment_context": "ai-gateway"}}
{"id": "template_54849", "config": "# Semantic Router Configuration\n# Generated from template\n\ndecisions:\n  - name: \"general_decision\"\n    modelRefs:\n      - model: \"qwen3\"\n        use_reasoning: true\n    signals:\n      - type: \"embedding\"\n        categories:\n          - \"business\"\n          - \"finance\"\n\nmodel_config:\n  qwen3:\n    reasoning_family: \"qwen3\"\n    preferred_endpoints:\n      - \"endpoint_qwen3\"\n\nvllm_endpoints:\n  - name: \"endpoint_qwen3\"\n    address: \"172.16.0.10\"\n    port: 11434\n    weight: 3\n\nsemantic_cache:\n  enabled: True\n  backend_type: \"memory\"\n  similarity_threshold: 0.8\n  max_entries: 1000\n  ttl_seconds: 3600\n\nprompt_guard:\n  enabled: True\n  threshold: 0.6\n  use_modernbert: true\n\ntools:\n  enabled: True\n  top_k: 3\n  similarity_threshold: 0.2\n", "intent": "Route queries to qwen3, using embedding-based routing, with memory semantic cache, with PII detection, with tools auto-selection, for quickstart deployment", "deployment_context": "quickstart", "source": "template", "values": {"decision_name": "general_decision", "model_name": "qwen3", "signal_type": "embedding", "category1": "business", "category2": "finance", "endpoint_address": "172.16.0.10", "endpoint_port": 11434, "endpoint_weight": 3, "cache_enabled": true, "cache_backend": "memory", "cache_threshold": 0.8, "guard_enabled": true, "guard_threshold": 0.6, "tools_enabled": true, "deployment_context": "quickstart"}}
{"id": "template_32856", "config": "# Semantic Router Configuration\n# Generated from template\n\ndecisions:\n  - name: \"general_decision\"\n    modelRefs:\n      - model: \"phi4\"\n        use_reasoning: true\n    signals:\n      - type: \"domain\"\n        categories:\n          - \"business\"\n          - \"finance\"\n\nmodel_config:\n  phi4:\n    reasoning_family: \"phi4\"\n    preferred_endpoints:\n      - \"endpoint_phi4\"\n\nvllm_endpoints:\n  - name: \"endpoint_phi4\"\n    address: \"172.16.0.10\"\n    port: 8080\n    weight: 3\n\nsemantic_cache:\n  enabled: True\n  backend_type: \"milvus\"\n  similarity_threshold: 0.7\n  max_entries: 1000\n  ttl_seconds: 3600\n\nprompt_guard:\n  enabled: False\n  threshold: 0.7\n  use_modernbert: true\n\ntools:\n  enabled: True\n  top_k: 3\n  similarity_threshold: 0.2\n", "intent": "Route queries to phi4, using domain-based routing, with milvus semantic cache, with tools auto-selection, for ai-gateway deployment", "deployment_context": "ai-gateway", "source": "template", "values": {"decision_name": "general_decision", "model_name": "phi4", "signal_type": "domain", "category1": "business", "category2": "finance", "endpoint_address": "172.16.0.10", "endpoint_port": 8080, "endpoint_weight": 3, "cache_enabled": true, "cache_backend": "milvus", "cache_threshold": 0.7, "guard_enabled": false, "guard_threshold": 0.7, "tools_enabled": true, "deployment_context": "ai-gateway"}}
{"id": "template_32600", "config": "# Semantic Router Configuration\n# Generated from template\n\ndecisions:\n  - name: \"general_decision\"\n    modelRefs:\n      - model: \"phi4\"\n        use_reasoning: true\n    signals:\n      - type: \"embedding\"\n        categories:\n          - \"support\"\n          - \"sales\"\n\nmodel_config:\n  phi4:\n    reasoning_family: \"phi4\"\n    preferred_endpoints:\n      - \"endpoint_phi4\"\n\nvllm_endpoints:\n  - name: \"endpoint_phi4\"\n    address: \"192.168.1.100\"\n    port: 8000\n    weight: 3\n\nsemantic_cache:\n  enabled: False\n  backend_type: \"redis\"\n  similarity_threshold: 0.9\n  max_entries: 1000\n  ttl_seconds: 3600\n\nprompt_guard:\n  enabled: False\n  threshold: 0.7\n  use_modernbert: true\n\ntools:\n  enabled: False\n  top_k: 3\n  similarity_threshold: 0.2\n", "intent": "Route queries to phi4, using embedding-based routing, for kubernetes deployment", "deployment_context": "kubernetes", "source": "template", "values": {"decision_name": "general_decision", "model_name": "phi4", "signal_type": "embedding", "category1": "support", "category2": "sales", "endpoint_address": "192.168.1.100", "endpoint_port": 8000, "endpoint_weight": 3, "cache_enabled": false, "cache_backend": "redis", "cache_threshold": 0.9, "guard_enabled": false, "guard_threshold": 0.7, "tools_enabled": false, "deployment_context": "kubernetes"}}
{"id": "template_30282", "config": "# Semantic Router Configuration\n# Generated from template\n\ndecisions:\n  - name: \"technical_decision\"\n    modelRefs:\n      - model: \"mistral\"\n        use_reasoning: true\n    signals:\n      - type: \"keyword\"\n        categories:\n          - \"support\"\n          - \"sales\"\n\nmodel_config:\n  mistral:\n    reasoning_family: \"mistral\"\n    preferred_endpoints:\n      - \"endpoint_mistral\"\n\nvllm_endpoints:\n  - name: \"endpoint_mistral\"\n    address: \"192.168.1.100\"\n    port: 11434\n    weight: 2\n\nsemantic_cache:\n  enabled: True\n  backend_type: \"redis\"\n  similarity_threshold: 0.8\n  max_entries: 1000\n  ttl_seconds: 3600\n\nprompt_guard:\n  enabled: True\n  threshold: 0.7\n  use_modernbert: true\n\ntools:\n  enabled: False\n  top_k: 3\n  similarity_threshold: 0.2\n", "intent": "Route queries to mistral, using keyword-based routing, with redis semantic cache, with PII detection, for quickstart deployment", "deployment_context": "quickstart", "source": "template", "values": {"decision_name": "technical_decision", "model_name": "mistral", "signal_type": "keyword", "category1": "support", "category2": "sales", "endpoint_address": "192.168.1.100", "endpoint_port": 11434, "endpoint_weight": 2, "cache_enabled": true, "cache_backend": "redis", "cache_threshold": 0.8, "guard_enabled": true, "guard_threshold": 0.7, "tools_enabled": false, "deployment_context": "quickstart"}}
{"id": "template_20222", "config": "# Semantic Router Configuration\n# Generated from template\n\ndecisions:\n  - name: \"business_decision\"\n    modelRefs:\n      - model: \"llama3\"\n        use_reasoning: true\n    signals:\n      - type: \"keyword\"\n        categories:\n          - \"support\"\n          - \"sales\"\n\nmodel_config:\n  llama3:\n    reasoning_family: \"llama3\"\n    preferred_endpoints:\n      - \"endpoint_llama3\"\n\nvllm_endpoints:\n  - name: \"endpoint_llama3\"\n    address: \"10.0.0.50\"\n    port: 11434\n    weight: 3\n\nsemantic_cache:\n  enabled: False\n  backend_type: \"redis\"\n  similarity_threshold: 0.8\n  max_entries: 1000\n  ttl_seconds: 3600\n\nprompt_guard:\n  enabled: False\n  threshold: 0.6\n  use_modernbert: true\n\ntools:\n  enabled: True\n  top_k: 3\n  similarity_threshold: 0.2\n", "intent": "Route queries to llama3, using keyword-based routing, with tools auto-selection, for kubernetes deployment", "deployment_context": "kubernetes", "source": "template", "values": {"decision_name": "business_decision", "model_name": "llama3", "signal_type": "keyword", "category1": "support", "category2": "sales", "endpoint_address": "10.0.0.50", "endpoint_port": 11434, "endpoint_weight": 3, "cache_enabled": false, "cache_backend": "redis", "cache_threshold": 0.8, "guard_enabled": false, "guard_threshold": 0.6, "tools_enabled": true, "deployment_context": "kubernetes"}}
{"id": "template_41239", "config": "# Semantic Router Configuration\n# Generated from template\n\ndecisions:\n  - name: \"technical_decision\"\n    modelRefs:\n      - model: \"qwen3\"\n        use_reasoning: true\n    signals:\n      - type: \"domain\"\n        categories:\n          - \"technical\"\n          - \"engineering\"\n\nmodel_config:\n  qwen3:\n    reasoning_family: \"qwen3\"\n    preferred_endpoints:\n      - \"endpoint_qwen3\"\n\nvllm_endpoints:\n  - name: \"endpoint_qwen3\"\n    address: \"192.168.1.100\"\n    port: 8002\n    weight: 3\n\nsemantic_cache:\n  enabled: True\n  backend_type: \"milvus\"\n  similarity_threshold: 0.7\n  max_entries: 1000\n  ttl_seconds: 3600\n\nprompt_guard:\n  enabled: False\n  threshold: 0.8\n  use_modernbert: true\n\ntools:\n  enabled: False\n  top_k: 3\n  similarity_threshold: 0.2\n", "intent": "Route queries to qwen3, using domain-based routing, with milvus semantic cache, for quickstart deployment", "deployment_context": "quickstart", "source": "template", "values": {"decision_name": "technical_decision", "model_name": "qwen3", "signal_type": "domain", "category1": "technical", "category2": "engineering", "endpoint_address": "192.168.1.100", "endpoint_port": 8002, "endpoint_weight": 3, "cache_enabled": true, "cache_backend": "milvus", "cache_threshold": 0.7, "guard_enabled": false, "guard_threshold": 0.8, "tools_enabled": false, "deployment_context": "quickstart"}}
{"id": "template_44990", "config": "# Semantic Router Configuration\n# Generated from template\n\ndecisions:\n  - name: \"business_decision\"\n    modelRefs:\n      - model: \"phi4\"\n        use_reasoning: true\n    signals:\n      - type: \"domain\"\n        categories:\n          - \"business\"\n          - \"customer_service\"\n\nmodel_config:\n  phi4:\n    reasoning_family: \"phi4\"\n    preferred_endpoints:\n      - \"endpoint_phi4\"\n\nvllm_endpoints:\n  - name: \"endpoint_phi4\"\n    address: \"10.0.0.50\"\n    port: 8002\n    weight: 1\n\nsemantic_cache:\n  enabled: True\n  backend_type: \"milvus\"\n  similarity_threshold: 0.8\n  max_entries: 1000\n  ttl_seconds: 3600\n\nprompt_guard:\n  enabled: False\n  threshold: 0.7\n  use_modernbert: true\n\ntools:\n  enabled: True\n  top_k: 3\n  similarity_threshold: 0.2\n", "intent": "Route queries to phi4, using domain-based routing, with milvus semantic cache, with tools auto-selection, for kubernetes deployment", "deployment_context": "kubernetes", "source": "template", "values": {"decision_name": "business_decision", "model_name": "phi4", "signal_type": "domain", "category1": "business", "category2": "customer_service", "endpoint_address": "10.0.0.50", "endpoint_port": 8002, "endpoint_weight": 1, "cache_enabled": true, "cache_backend": "milvus", "cache_threshold": 0.8, "guard_enabled": false, "guard_threshold": 0.7, "tools_enabled": true, "deployment_context": "kubernetes"}}
{"id": "template_61943", "config": "# Semantic Router Configuration\n# Generated from template\n\ndecisions:\n  - name: \"technical_decision\"\n    modelRefs:\n      - model: \"qwen3\"\n        use_reasoning: true\n    signals:\n      - type: \"domain\"\n        categories:\n          - \"support\"\n          - \"sales\"\n\nmodel_config:\n  qwen3:\n    reasoning_family: \"qwen3\"\n    preferred_endpoints:\n      - \"endpoint_qwen3\"\n\nvllm_endpoints:\n  - name: \"endpoint_qwen3\"\n    address: \"172.28.0.20\"\n    port: 11434\n    weight: 2\n\nsemantic_cache:\n  enabled: True\n  backend_type: \"memory\"\n  similarity_threshold: 0.8\n  max_entries: 1000\n  ttl_seconds: 3600\n\nprompt_guard:\n  enabled: False\n  threshold: 0.7\n  use_modernbert: true\n\ntools:\n  enabled: False\n  top_k: 3\n  similarity_threshold: 0.2\n", "intent": "Route queries to qwen3, using domain-based routing, with memory semantic cache, for quickstart deployment", "deployment_context": "quickstart", "source": "template", "values": {"decision_name": "technical_decision", "model_name": "qwen3", "signal_type": "domain", "category1": "support", "category2": "sales", "endpoint_address": "172.28.0.20", "endpoint_port": 11434, "endpoint_weight": 2, "cache_enabled": true, "cache_backend": "memory", "cache_threshold": 0.8, "guard_enabled": false, "guard_threshold": 0.7, "tools_enabled": false, "deployment_context": "quickstart"}}
{"id": "template_78516", "config": "# Semantic Router Configuration\n# Generated from template\n\ndecisions:\n  - name: \"technical_decision\"\n    modelRefs:\n      - model: \"llama3\"\n        use_reasoning: true\n    signals:\n      - type: \"keyword\"\n        categories:\n          - \"technical\"\n          - \"customer_service\"\n\nmodel_config:\n  llama3:\n    reasoning_family: \"llama3\"\n    preferred_endpoints:\n      - \"endpoint_llama3\"\n\nvllm_endpoints:\n  - name: \"endpoint_llama3\"\n    address: \"172.28.0.20\"\n    port: 8002\n    weight: 3\n\nsemantic_cache:\n  enabled: False\n  backend_type: \"redis\"\n  similarity_threshold: 0.8\n  max_entries: 1000\n  ttl_seconds: 3600\n\nprompt_guard:\n  enabled: False\n  threshold: 0.6\n  use_modernbert: true\n\ntools:\n  enabled: True\n  top_k: 3\n  similarity_threshold: 0.2\n", "intent": "Route queries to llama3, using keyword-based routing, with tools auto-selection, for quickstart deployment", "deployment_context": "quickstart", "source": "template", "values": {"decision_name": "technical_decision", "model_name": "llama3", "signal_type": "keyword", "category1": "technical", "category2": "customer_service", "endpoint_address": "172.28.0.20", "endpoint_port": 8002, "endpoint_weight": 3, "cache_enabled": false, "cache_backend": "redis", "cache_threshold": 0.8, "guard_enabled": false, "guard_threshold": 0.6, "tools_enabled": true, "deployment_context": "quickstart"}}
{"id": "template_60679", "config": "# Semantic Router Configuration\n# Generated from template\n\ndecisions:\n  - name: \"business_decision\"\n    modelRefs:\n      - model: \"llama3\"\n        use_reasoning: true\n    signals:\n      - type: \"embedding\"\n        categories:\n          - \"technical\"\n          - \"customer_service\"\n\nmodel_config:\n  llama3:\n    reasoning_family: \"llama3\"\n    preferred_endpoints:\n      - \"endpoint_llama3\"\n\nvllm_endpoints:\n  - name: \"endpoint_llama3\"\n    address: \"10.0.0.50\"\n    port: 8000\n    weight: 1\n\nsemantic_cache:\n  enabled: True\n  backend_type: \"memory\"\n  similarity_threshold: 0.9\n  max_entries: 1000\n  ttl_seconds: 3600\n\nprompt_guard:\n  enabled: False\n  threshold: 0.8\n  use_modernbert: true\n\ntools:\n  enabled: True\n  top_k: 3\n  similarity_threshold: 0.2\n", "intent": "Route queries to llama3, using embedding-based routing, with memory semantic cache, with tools auto-selection, for istio deployment", "deployment_context": "istio", "source": "template", "values": {"decision_name": "business_decision", "model_name": "llama3", "signal_type": "embedding", "category1": "technical", "category2": "customer_service", "endpoint_address": "10.0.0.50", "endpoint_port": 8000, "endpoint_weight": 1, "cache_enabled": true, "cache_backend": "memory", "cache_threshold": 0.9, "guard_enabled": false, "guard_threshold": 0.8, "tools_enabled": true, "deployment_context": "istio"}}
{"id": "template_3187", "config": "# Semantic Router Configuration\n# Generated from template\n\ndecisions:\n  - name: \"business_decision\"\n    modelRefs:\n      - model: \"phi4\"\n        use_reasoning: true\n    signals:\n      - type: \"domain\"\n        categories:\n          - \"general\"\n          - \"sales\"\n\nmodel_config:\n  phi4:\n    reasoning_family: \"phi4\"\n    preferred_endpoints:\n      - \"endpoint_phi4\"\n\nvllm_endpoints:\n  - name: \"endpoint_phi4\"\n    address: \"172.28.0.20\"\n    port: 8000\n    weight: 2\n\nsemantic_cache:\n  enabled: True\n  backend_type: \"milvus\"\n  similarity_threshold: 0.8\n  max_entries: 1000\n  ttl_seconds: 3600\n\nprompt_guard:\n  enabled: True\n  threshold: 0.6\n  use_modernbert: true\n\ntools:\n  enabled: True\n  top_k: 3\n  similarity_threshold: 0.2\n", "intent": "Route queries to phi4, using domain-based routing, with milvus semantic cache, with PII detection, with tools auto-selection, for ai-gateway deployment", "deployment_context": "ai-gateway", "source": "template", "values": {"decision_name": "business_decision", "model_name": "phi4", "signal_type": "domain", "category1": "general", "category2": "sales", "endpoint_address": "172.28.0.20", "endpoint_port": 8000, "endpoint_weight": 2, "cache_enabled": true, "cache_backend": "milvus", "cache_threshold": 0.8, "guard_enabled": true, "guard_threshold": 0.6, "tools_enabled": true, "deployment_context": "ai-gateway"}}
{"id": "template_14332", "config": "# Semantic Router Configuration\n# Generated from template\n\ndecisions:\n  - name: \"general_decision\"\n    modelRefs:\n      - model: \"phi4\"\n        use_reasoning: true\n    signals:\n      - type: \"embedding\"\n        categories:\n          - \"support\"\n          - \"customer_service\"\n\nmodel_config:\n  phi4:\n    reasoning_family: \"phi4\"\n    preferred_endpoints:\n      - \"endpoint_phi4\"\n\nvllm_endpoints:\n  - name: \"endpoint_phi4\"\n    address: \"192.168.1.100\"\n    port: 11434\n    weight: 3\n\nsemantic_cache:\n  enabled: False\n  backend_type: \"memory\"\n  similarity_threshold: 0.9\n  max_entries: 1000\n  ttl_seconds: 3600\n\nprompt_guard:\n  enabled: False\n  threshold: 0.6\n  use_modernbert: true\n\ntools:\n  enabled: False\n  top_k: 3\n  similarity_threshold: 0.2\n", "intent": "Route queries to phi4, using embedding-based routing, for quickstart deployment", "deployment_context": "quickstart", "source": "template", "values": {"decision_name": "general_decision", "model_name": "phi4", "signal_type": "embedding", "category1": "support", "category2": "customer_service", "endpoint_address": "192.168.1.100", "endpoint_port": 11434, "endpoint_weight": 3, "cache_enabled": false, "cache_backend": "memory", "cache_threshold": 0.9, "guard_enabled": false, "guard_threshold": 0.6, "tools_enabled": false, "deployment_context": "quickstart"}}
